Workbook
Name CalendarYear: [1]January!$K$5
Name ColumnTitleRegion1..H12.6: #REF!
Name ColumnTitleRegion1..H12.6: #REF!
Name ColumnTitleRegion1..H12.6: #REF!
Name ColumnTitleRegion1..H12.6: #REF!
Name ColumnTitleRegion1..H12.6: #REF!
Name ColumnTitleRegion1..H12.6: #REF!
Name ColumnTitleRegion2..C14.6: #REF!
Name ColumnTitleRegion2..C14.6: #REF!
Name ColumnTitleRegion2..C14.6: #REF!
Name ColumnTitleRegion2..C14.6: #REF!
Name ColumnTitleRegion2..C14.6: #REF!
Name ColumnTitleRegion2..C14.6: #REF!
Name DaysAndWeeks: {0,1,2,3,4,5,6} + {0;1;2;3;4;5}*7
Name Raw_data: OFFSET([2]로데이터!$A$1,0,0,COUNTA([2]로데이터!$A:$A),COUNTA([2]로데이터!$1:$1))
Name WeekStart: [1]January!$L$5

Sheet Price Jun_Water Purifier
C2: Promotion Price June 2026
E3: Outright + 2Y Service | I3: Service Cycle | J3: Subscription Fee
J4: Contract 5Y | AB4: Contract 7Y
J5: VISIT | S5: SELF | AB5: VISIT | AK5: SELF
B6: Classification | C6: Model | E6: Visit | F6: Discount 10% | G6: Self | H6: Discount 10% | J6: Visit 5Y Monthly price | K6: Total Month | L6: Normal total price | M6: Cost | N6: Promotion Jun (6 รอบบิล) | O6: Disc.50% (12 รอบบิล) | P6: Disc.50% (18 รอบบิล) | Q6: Promotion Net | R6: Disc | S6: Self 5Y Monthly price | T6: Total Month | U6: Normal total price | V6: Cost | W6: Promotion Jun (6 รอบบิล) | X6: Disc.50% (12 รอบบิล) | Y6: Disc.50% (18 รอบบิล) | Z6: Promotion Net | AA6: Disc | AB6: Visit 7Y Monthly price | AC6: Total Month | AD6: Normal total price | AE6: Cost | AF6: Promotion Jun (6 รอบบิล) | AG6: Disc.50% (12 รอบบิล) | AH6: Disc.50% (18 รอบบิล) | AI6: Promotion Net | AJ6: Disc | AK6: Self 7Y Monthly price | AL6: Total Month | AM6: Normal total price | AN6: Cost | AO6: Promotion Jun (6 รอบบิล) | AP6: Disc.50% (12 รอบบิล) | AQ6: Disc.50% (18 รอบบิล) | AR6: Promotion Net | AS6: Disc
B7: WP | C7: WD516AN.ACNPLMT | D7: ATOM 4D+ Calming Navy | E7: 37900 | F7: =ROUNDDOWN(E7*0.9,0) -> 34110 | G7: 34900 | H7: =ROUNDDOWN(G7*0.9,0) -> 31410 | I7: 6M | J7: 799 | K7: 60 | L7: =K7*J7 -> 47940 | N7: 149 | Q7: =(N7*6)+(J7*54) -> 44040 | R7: =L7-Q7 -> 3900 | S7: 699 | T7: 60 | U7: =T7*S7 -> 41940 | W7: 149 | Z7: =(W7*6)+(S7*54) -> 38640 | AA7: =U7-Z7 -> 3300 | AB7: 599 | AC7: 84 | AD7: =AC7*AB7 -> 50316 | AF7: 149 | AI7: =(AF7*6)+(AB7*78) -> 47616 | AJ7: =AD7-AI7 -> 2700 | AK7: 499 | AL7: 84 | AM7: =AL7*AK7 -> 41916 | AO7: 149 | AR7: =(AO7*6)+(AK7*78) -> 39816 | AS7: =AM7-AR7 -> 2100
C8: WD516AN.AEWPLMT | D8: ATOM 4D+ Essense White | E8: 37900 | F8: =ROUNDDOWN(E8*0.9,0) -> 34110 | G8: 34900 | H8: =ROUNDDOWN(G8*0.9,0) -> 31410 | I8: 6M | J8: 799 | K8: 60 | L8: =K8*J8 -> 47940 | N8: 149 | Q8: =(N8*6)+(J8*54) -> 44040 | R8: =L8-Q8 -> 3900 | S8: 699 | T8: 60 | U8: =T8*S8 -> 41940 | W8: 149 | Z8: =(W8*6)+(S8*54) -> 38640 | AA8: =U8-Z8 -> 3300 | AB8: 599 | AC8: 84 | AD8: =AC8*AB8 -> 50316 | AF8: 149 | AI8: =(AF8*6)+(AB8*78) -> 47616 | AJ8: =AD8-AI8 -> 2700 | AK8: 499 | AL8: 84 | AM8: =AL8*AK8 -> 41916 | AO8: 149 | AR8: =(AO8*6)+(AK8*78) -> 39816 | AS8: =AM8-AR8 -> 2100
C9: WD516AN.ASLPLMT | D9: ATOM 4D+ Silver | E9: 37900 | F9: =ROUNDDOWN(E9*0.9,0) -> 34110 | G9: 34900 | H9: =ROUNDDOWN(G9*0.9,0) -> 31410 | I9: 6M | J9: 799 | K9: 60 | L9: =K9*J9 -> 47940 | N9: 149 | Q9: =(N9*6)+(J9*54) -> 44040 | R9: =L9-Q9 -> 3900 | S9: 699 | T9: 60 | U9: =T9*S9 -> 41940 | W9: 149 | Z9: =(W9*6)+(S9*54) -> 38640 | AA9: =U9-Z9 -> 3300 | AB9: 599 | AC9: 84 | AD9: =AC9*AB9 -> 50316 | AF9: 149 | AI9: =(AF9*6)+(AB9*78) -> 47616 | AJ9: =AD9-AI9 -> 2700 | AK9: 499 | AL9: 84 | AM9: =AL9*AK9 -> 41916 | AO9: 149 | AR9: =(AO9*6)+(AK9*78) -> 39816 | AS9: =AM9-AR9 -> 2100
C10: WD518AN.ABGPLMT | D10: ATOM V Calming Beige | E10: 37900 | F10: =ROUNDDOWN(E10*0.9,0) -> 34110 | G10: 34900 | H10: =ROUNDDOWN(G10*0.9,0) -> 31410 | I10: 6M | J10: 799 | K10: 60 | L10: =K10*J10 -> 47940 | N10: 149 | Q10: =(N10*6)+(J10*54) -> 44040 | R10: =L10-Q10 -> 3900 | S10: 699 | T10: 60 | U10: =T10*S10 -> 41940 | W10: 149 | Z10: =(W10*6)+(S10*54) -> 38640 | AA10: =U10-Z10 -> 3300 | AB10: 599 | AC10: 84 | AD10: =AC10*AB10 -> 50316 | AF10: 149 | AI10: =(AF10*6)+(AB10*78) -> 47616 | AJ10: =AD10-AI10 -> 2700 | AK10: 499 | AL10: 84 | AM10: =AL10*AK10 -> 41916 | AO10: 149 | AR10: =(AO10*6)+(AK10*78) -> 39816 | AS10: =AM10-AR10 -> 2100
C11: WD518AN.AWHPLMT | D11: ATOM V Calming Cream White | E11: 37900 | F11: =ROUNDDOWN(E11*0.9,0) -> 34110 | G11: 34900 | H11: =ROUNDDOWN(G11*0.9,0) -> 31410 | I11: 6M | J11: 799 | K11: 60 | L11: =K11*J11 -> 47940 | N11: 149 | Q11: =(N11*6)+(J11*54) -> 44040 | R11: =L11-Q11 -> 3900 | S11: 699 | T11: 60 | U11: =T11*S11 -> 41940 | W11: 149 | Z11: =(W11*6)+(S11*54) -> 38640 | AA11: =U11-Z11 -> 3300 | AB11: 599 | AC11: 84 | AD11: =AC11*AB11 -> 50316 | AF11: 149 | AI11: =(AF11*6)+(AB11*78) -> 47616 | AJ11: =AD11-AI11 -> 2700 | AK11: 499 | AL11: 84 | AM11: =AL11*AK11 -> 41916 | AO11: 149 | AR11: =(AO11*6)+(AK11*78) -> 39816 | AS11: =AM11-AR11 -> 2100
C12: WD518AN.ACGPLMT | D12: ATOM V Cream Gray | E12: 37900 | F12: =ROUNDDOWN(E12*0.9,0) -> 34110 | G12: 34900 | H12: =ROUNDDOWN(G12*0.9,0) -> 31410 | I12: 6M | J12: 799 | K12: 60 | L12: =K12*J12 -> 47940 | N12: 149 | Q12: =(N12*6)+(J12*54) -> 44040 | R12: =L12-Q12 -> 3900 | S12: 699 | T12: 60 | U12: =T12*S12 -> 41940 | W12: 149 | Z12: =(W12*6)+(S12*54) -> 38640 | AA12: =U12-Z12 -> 3300 | AB12: 599 | AC12: 84 | AD12: =AC12*AB12 -> 50316 | AF12: 149 | AI12: =(AF12*6)+(AB12*78) -> 47616 | AJ12: =AD12-AI12 -> 2700 | AK12: 499 | AL12: 84 | AM12: =AL12*AK12 -> 41916 | AO12: 149 | AR12: =(AO12*6)+(AK12*78) -> 39816 | AS12: =AM12-AR12 -> 2100
C13: WD110MN.ABGPLMT | D13: MX Calming Beige | E13: 0 | F13: =ROUNDDOWN(E13*0.9,0) -> 0 | G13: 0 | H13: =ROUNDDOWN(G13*0.9,0) -> 0 | I13: 6M | J13: 549 | K13: 60 | L13: =K13*J13 -> 32940 | N13: 99 | Q13: =(N13*6)+(J13*54) -> 30240 | R13: =L13-Q13 -> 2700 | S13: 499 | T13: 60 | U13: =T13*S13 -> 29940 | W13: 99 | Z13: =(W13*6)+(S13*54) -> 27540 | AA13: =U13-Z13 -> 2400 | AB13: 449 | AC13: 84 | AD13: =AC13*AB13 -> 37716 | AF13: 99 | AI13: =(AF13*6)+(AB13*78) -> 35616 | AJ13: =AD13-AI13 -> 2100 | AK13: 399 | AL13: 84 | AM13: =AL13*AK13 -> 33516 | AO13: 99 | AR13: =(AO13*6)+(AK13*78) -> 31716 | AS13: =AM13-AR13 -> 1800
C14: WS510SN.AWHPLMT | D14: Stand Water Purifier White | E14: 0 | F14: =ROUNDDOWN(E14*0.9,0) -> 0 | G14: 0 | H14: =ROUNDDOWN(G14*0.9,0) -> 0 | I14: 3M | J14: =1049+50 -> 1099 | K14: 60 | L14: =K14*J14 -> 65940 | N14: 149 | Q14: =(N14*6)+(J14*54) -> 60240 | R14: =L14-Q14 -> 5700 | U14: =T14*S14 -> 0 | Z14: =(W14*6)+(S14*54) -> 0 | AA14: =U14-Z14 -> 0 | AB14: =849+50 -> 899 | AC14: 84 | AD14: =AC14*AB14 -> 75516 | AF14: 149 | AI14: =(AF14*6)+(AB14*78) -> 71016 | AJ14: =AD14-AI14 -> 4500 | AM14: =AL14*AK14 -> 0 | AO14: -

Sheet REF, WM, Styler,DW,MWO
E1: Promotion Price June 2026
K3: Contract 5Y | AQ3: Contract 6Y
K4: VISIT | AB4: SELF | AQ4: VISIT | BH4: SELF
C5: Classification | D5: Remark | E5: Model | G5: PTO model Promotion Free Gift | H5: Product (1) | I5: Product (2) | J5: Service Cycle | K5: Visit 5Y Monthly price | L5: Total Month | M5: Normal total price | N5: Cost | O5: Promotion Jun | P5: Promotion | Q5: Disc.50% (3 รอบบิล) | R5: Disc.50% (2 รอบบิล) | S5: Disc.50% (5 รอบบิล) | T5: Disc.50% (6 รอบบิล) | U5: Disc.50% (11 รอบบิล) | V5: Disc.50% (12 รอบบิล) | W5: Promotion Jun (1 รอบบิล) | X5: Promotion Jun (3 รอบบิล) | Y5: Promotion Jun (6 รอบบิล) | Z5: Promotion Net | AA5: Disc from Normal | AB5: Self 5Y Monthly price | AC5: Total Month | AD5: Normal total price | AE5: Cost | AF5: Promotion Jun | AG5: Promotion | AH5: Disc.50% (5 รอบบิล) | AI5: Disc.50% (6 รอบบิล) | AJ5: Disc.50% (11 รอบบิล) | AK5: Disc.50% (12 รอบบิล) | AL5: Promotion Jun (1 รอบบิล) | AM5: Promotion Jun (3 รอบบิล) | AN5: Promotion Jun (6 รอบบิล) | AO5: Promotion Net | AP5: Disc from Normal | AQ5: Visit 6Y Monthly price | AR5: Total Month | AS5: Normal total price | AT5: Cost | AU5: Promotion Jun | AV5: Promotion | AW5: Disc.50% (3 รอบบิล) | AX5: Disc.50% (2 รอบบิล) | AY5: Disc.50% (5 รอบบิล) | AZ5: Disc.50% (6 รอบบิล) | BA5: Disc.50% (11 รอบบิล) | BB5: Disc.50% (12 รอบบิล) | BC5: Promotion Jun (1 รอบบิล) | BD5: Promotion Jun (3 รอบบิล) | BE5: Promotion Jun (6 รอบบิล) | BF5: Promotion Net | BG5: Disc from Normal | BH5: Self 6Y Monthly price | BI5: Total Month | BJ5: Normal total price | BK5: Cost | BL5: Promotion Jun | BM5: Promotion | BN5: Disc.50% (5 รอบบิล) | BO5: Disc.50% (6 รอบบิล) | BP5: Disc.50% (11 รอบบิล) | BQ5: Disc.50% (12 รอบบิล) | BR5: Promotion Jun (1 รอบบิล) | BS5: Promotion Jun (3 รอบบิล) | BT5: Promotion Jun (6 รอบบิล) | BU5: Promotion Net | BV5: Disc from Normal
C6: REF | E6: GC-X257CMEW.ATEPLMT | F6: Side-By-Side /SIZE : 22.4 คิว/ 635 ลิตร | J6: 24M | K6: =1199+50 -> 1249 | L6: 60 | M6: =L6*K6 -> 74940 | P6: =MIN(K6,O6)*57 -> 71193 | R6: =ROUNDDOWN(MIN(K6,O6)*0.5,0) -> 624 | W6: 149 | Z6: =P6+(W6*1)+(R6*2) -> 72590 | AA6: =M6-Z6 -> 2350 | AQ6: =999+50 -> 1049 | AR6: 72 | AS6: =AR6*AQ6 -> 75528 | AV6: =MIN(AQ6,AU6)*69 -> 72381 | AX6: =ROUNDDOWN(MIN(AQ6,AU6)*0.5,0) -> 524 | BC6: 149 | BF6: =AV6+(BC6*1)+(AX6*2) -> 73578 | BG6: =AS6-BF6 -> 1950
E7: GC-J257SQZW.AEPPLMT | F7: Side-By-Side /Door in Door/22.4Q/ 635 ลิตร | J7: 24M | K7: =949+50+50 -> 1049 | L7: 60 | M7: =L7*K7 -> 62940 | P7: =MIN(K7,O7)*57 -> 59793 | R7: =ROUNDDOWN(MIN(K7,O7)*0.5,0) -> 524 | W7: 149 | Z7: =P7+(W7*1)+(R7*2) -> 60990 | AA7: =M7-Z7 -> 1950 | AQ7: =799+50+50 -> 899 | AR7: 72 | AS7: =AR7*AQ7 -> 64728 | AV7: =MIN(AQ7,AU7)*69 -> 62031 | AX7: =ROUNDDOWN(MIN(AQ7,AU7)*0.5,0) -> 449 | BC7: 149 | BF7: =AV7+(BC7*1)+(AX7*2) -> 63078 | BG7: =AS7-BF7 -> 1650
E8: GC-L257SFZW.APYPLMT | F8: Side-By-Side/ 22.4 Q/ 635 ลิตร | J8: 24M | K8: 849 | L8: 60 | M8: =L8*K8 -> 50940 | P8: =MIN(K8,O8)*57 -> 48393 | Q8: =ROUNDDOWN(MIN(K8,O8)*0.5,0) -> 424 | Z8: =P8+(Q8*3) -> 49665 | AA8: =M8-Z8 -> 1275 | AQ8: 749 | AR8: 72 | AS8: =AR8*AQ8 -> 53928 | AV8: =MIN(AQ8,AU8)*69 -> 51681 | AW8: =ROUNDDOWN(MIN(AQ8,AU8)*0.5,0) -> 374 | BF8: =AV8+(AW8*3) -> 52803 | BG8: =AS8-BF8 -> 1125
E9: GC-X257CMHW.AEEPLMT | F9: Side-By-Side /SIZE : 22.4 คิว/ 635 ลิตร/ Plumbing/Smart Inverter Compressor | G9: PTOX257CMHW.APTO | H9: GC-X257CMHW.AEEPLMT | I9: REF3FILTER2.AETC | J9: 6M | K9: =1349+100 -> 1449 | L9: 60 | M9: =L9*K9 -> 86940 | P9: =MIN(K9,O9)*60 -> 86940 | Z9: =P9+(Q9*3) -> 86940 | AA9: =M9-Z9 -> 0 | AQ9: =1149+100 -> 1249 | AR9: 72 | AS9: =AR9*AQ9 -> 89928 | AV9: =MIN(AQ9,AU9)*72 -> 89928 | BF9: =AV9+(AW9*3) -> 89928 | BG9: =AS9-BF9 -> 0
E10: GV-V25FFGRB.ABMPLMT | F10: Multi-Door 21.6 คิว/ 612 ลิตร Smart Inverter Compressor | J10: 24M | K10: =949+50 -> 999 | L10: 60 | M10: =L10*K10 -> 59940 | P10: =MIN(K10,O10)*57 -> 56943 | Q10: =ROUNDDOWN(MIN(K10,O10)*0.5,0) -> 499 | Z10: =P10+(Q10*3) -> 58440 | AA10: =M10-Z10 -> 1500 | AQ10: =899+50 -> 949 | AR10: 72 | AS10: =AR10*AQ10 -> 68328 | AV10: =MIN(AQ10,AU10)*69 -> 65481 | AW10: =ROUNDDOWN(MIN(AQ10,AU10)*0.5,0) -> 474 | BF10: =AV10+(AW10*3) -> 66903 | BG10: =AS10-BF10 -> 1425
E11: GC-V22FFQMB.AEPPLMT | F11: Multi Door 18.7 Q/ 530 ลิตร | J11: 24M | K11: =849+50+50 -> 949 | L11: 60 | M11: =L11*K11 -> 56940 | P11: =MIN(K11,O11)*57 -> 54093 | R11: =ROUNDDOWN(MIN(K11,O11)*0.5,0) -> 474 | W11: 149 | Z11: =P11+(W11*1)+(R11*2) -> 55190 | AA11: =M11-Z11 -> 1750 | AQ11: =699+50+50 -> 799 | AR11: 72 | AS11: =AR11*AQ11 -> 57528 | AV11: =MIN(AQ11,AU11)*69 -> 55131 | AX11: =ROUNDDOWN(MIN(AQ11,AU11)*0.5,0) -> 399 | BC11: 149 | BF11: =AV11+(BC11*1)+(AX11*2) -> 56078 | BG11: =AS11-BF11 -> 1450
E12: GC-G24FFQKB.AEEPLM1 | F12: Multi Door 4D F/D Swing 22.5 คิว/ 637 ลิตร | J12: 24M | K12: =1299+50 -> 1349 | L12: 60 | M12: =L12*K12 -> 80940 | P12: =MIN(K12,O12)*57 -> 76893 | R12: =ROUNDDOWN(MIN(K12,O12)*0.5,0) -> 674 | W12: 149 | Z12: =P12+(W12*1)+(R12*2) -> 78390 | AA12: =M12-Z12 -> 2550 | AQ12: =1099+50 -> 1149 | AR12: 72 | AS12: =AR12*AQ12 -> 82728 | AV12: =MIN(AQ12,AU12)*69 -> 79281 | AX12: =ROUNDDOWN(MIN(AQ12,AU12)*0.5,0) -> 574 | BC12: 149 | BF12: =AV12+(BC12*1)+(AX12*2) -> 80578 | BG12: =AS12-BF12 -> 2150
E13: GC-X24FFCRB.AEVPLM1 | F13: Multi-Door 22.7 คิว/ 642 ลิตร Plumbing/Smart Inverter Compressor | G13: PTOX24FFCR2.APTO | H13: GC-X24FFCRB.AEVPLM1 | I13: REF3FILTER2.AETC | J13: 6M | K13: =1849-500+100 -> 1449 | L13: 60 | M13: =L13*K13 -> 86940 | P13: =MIN(K13,O13)*57 -> 82593 | X13: 149 | Z13: =P13+(X13*3) -> 83040 | AA13: =M13-Z13 -> 3900 | AQ13: =1649-500+100 -> 1249 | AR13: 72 | AS13: =AR13*AQ13 -> 89928 | AV13: =MIN(AQ13,AU13)*69 -> 86181 | BD13: 149 | BF13: =AV13+(BD13*3) -> 86628 | BG13: =AS13-BF13 -> 3300
E14: GC-L24FFCBB.AEVPLM1 | F14: Multi-Door 22.6 คิว/ 641 ลิตร/ Plumbing/Smart Inverter Compressor | G14: PTOL24FFCB2.APTO | H14: GC-L24FFCBB.AEVPLM1 | I14: REF3FILTER2.AETC | J14: 6M | K14: =1649-500+100 -> 1249 | L14: 60 | M14: =L14*K14 -> 74940 | P14: =MIN(K14,O14)*57 -> 71193 | X14: 149 | Z14: =P14+(X14*3) -> 71640 | AA14: =M14-Z14 -> 3300 | AQ14: =1449-500+100 -> 1049 | AR14: 72 | AS14: =AR14*AQ14 -> 75528 | AV14: =MIN(AQ14,AU14)*69 -> 72381 | BD14: 149 | BF14: =AV14+(BD14*3) -> 72828 | BG14: =AS14-BF14 -> 2700
E15: GN-F452PQAK.AEPPLMT | F15: 2 Doors | J15: 24M | K15: =549+50 -> 599 | L15: 60 | M15: =L15*K15 -> 35940 | P15: =MIN(K15,O15)*57 -> 34143 | Q15: =ROUNDDOWN(MIN(K15,O15)*0.5,0) -> 299 | Z15: =P15+(Q15*3) -> 35040 | AA15: =M15-Z15 -> 900 | AQ15: =449+50 -> 499 | AR15: 72 | AS15: =AR15*AQ15 -> 35928 | AV15: =MIN(AQ15,AU15)*69 -> 34431 | AW15: =ROUNDDOWN(MIN(AQ15,AU15)*0.5,0) -> 249 | BF15: =AV15+(AW15*3) -> 35178 | BG15: =AS15-BF15 -> 750
E16: GN-V389FQEF.AEPPLMT | F16: 2 Doors 12Q/ Bottom freezer Smart Inverter | J16: 24M | K16: 649 | L16: 60 | M16: =L16*K16 -> 38940 | P16: =MIN(K16,O16)*57 -> 36993 | Q16: =ROUNDDOWN(MIN(K16,O16)*0.5,0) -> 324 | Z16: =P16+(Q16*3) -> 37965 | AA16: =M16-Z16 -> 975 | AQ16: 549 | AR16: 72 | AS16: =AR16*AQ16 -> 39528 | AV16: =MIN(AQ16,AU16)*69 -> 37881 | AW16: =ROUNDDOWN(MIN(AQ16,AU16)*0.5,0) -> 274 | BF16: =AV16+(AW16*3) -> 38703 | BG16: =AS16-BF16 -> 825
D17: OBS Subs. | E17: GC-L257KQKW.AEPPLMT | F17: Side-By-Side/ 22.6 Q/ 641 ลิตร | J17: 24M | K17: =749+100-100 -> 749 | L17: 60 | M17: =L17*K17 -> 44940 | P17: =MIN(K17,O17)*60 -> 44940 | Z17: =P17+(Q17) -> 44940 | AA17: =M17-Z17 -> 0 | AQ17: =649+100-100 -> 649 | AR17: 72 | AS17: =AR17*AQ17 -> 46728 | AV17: =MIN(AQ17,AU17)*72 -> 46728 | BF17: =AV17+(AW17*3) -> 46728 | BG17: =AS17-BF17 -> 0
D18: OBS Subs | E18: GC-B257SQYL.AMCPLMT | F18: Side-By-Side/ 22.9 Q/ 649 ลิตร | J18: 24M | K18: =599-50 -> 549 | L18: 60 | M18: =L18*K18 -> 32940 | P18: =MIN(K18,O18)*60 -> 32940 | Z18: =P18+(Q18*3) -> 32940 | AA18: =M18-Z18 -> 0 | AQ18: =499-50 -> 449 | AR18: 72 | AS18: =AR18*AQ18 -> 32328 | AV18: =MIN(AQ18,AU18)*72 -> 32328 | BF18: =AV18+(AW18*3) -> 32328 | BG18: =AS18-BF18 -> 0
D19: OBS Subs. | E19: GV-B25FFGDB.ABMPLMT | F19: Multi-Door / 21.6 คิว / 611 ลิตร/ Black glass | J19: 24M | K19: =849-150 -> 699 | L19: 60 | M19: =L19*K19 -> 41940 | P19: =MIN(K19,O19)*60 -> 41940 | Z19: =P19+(V19*12) -> 41940 | AA19: =M19-Z19 -> 0 | AQ19: =699-100 -> 599 | AR19: 72 | AS19: =AR19*AQ19 -> 43128 | AV19: =MIN(AQ19,AU19)*72 -> 43128 | BF19: =AV19+(BB19*12) -> 43128 | BG19: =AS19-BF19 -> 0
D20: OBS Subs. | E20: GN-F392PQAK.AEPPLM1 | F20: 2 Doors Top Freezer | J20: 24M | K20: =499-50 -> 449 | L20: 60 | M20: =L20*K20 -> 26940 | P20: =MIN(K20,O20)*60 -> 26940 | Z20: =P20+(Q20*3) -> 26940 | AA20: =M20-Z20 -> 0 | AQ20: =399-50 -> 349 | AR20: 72 | AS20: =AR20*AQ20 -> 25128 | AV20: =MIN(AQ20,AU20)*72 -> 25128 | BF20: =AV20+(AW20) -> 25128 | BG20: =AS20-BF20 -> 0
C21: WM | E21: WT2520NHEG.ABGPETH | F21: Wash Tower 25 Kg (Green/Beige) | J21: 12M | K21: 2399 | L21: 60 | M21: =L21*K21 -> 143940 | P21: =MIN(K21,O21)*54 -> 129546 | Q21: =ROUNDDOWN(MIN(J21,N21)*0.5,0) -> 0 | S21: =ROUNDDOWN(MIN(K21,O21)*0.5,0) -> 1199 | W21: 149 | Z21: =P21+(W21*1)+(S21*5) -> 135690 | AA21: =M21-Z21 -> 8250 | AB21: 2199 | AC21: 60 | AD21: =AC21*AB21 -> 131940 | AG21: =MIN(AB21,AF21)*54 -> 118746 | AH21: =ROUNDDOWN((MIN(AB21,AF21)*0.5),0) -> 1099 | AL21: 149 | AO21: =(AB21*54)+(AL21*1)+(AH21*5) -> 124390 | AP21: =AD21-AO21 -> 7550 | AQ21: 2199 | AR21: 72 | AS21: =AR21*AQ21 -> 158328 | AV21: =MIN(AQ21,AU21)*66 -> 145134 | AY21: =ROUNDDOWN(MIN(AQ21,AU21)*0.5,0) -> 1099 | BC21: 149 | BF21: =AV21+(BC21*1)+(AY21*5) -> 150778 | BG21: =AS21-BF21 -> 7550 | BH21: 1999 | BI21: 72 | BJ21: =BI21*BH21 -> 143928 | BM21: =MIN(BH21,BL21)*66 -> 131934 | BN21: =ROUNDDOWN((MIN(BH21,BL21)*0.5),0) -> 999 | BR21: 149 | BU21: =BM21+(BR21*1)+(BN21*5) -> 137078 | BV21: =BJ21-BU21 -> 6850
E22: WT2520NHEN.ABNPETH | F22: Wash Tower 25 Kg (Navy/Beige) | J22: 12M | K22: 2399 | L22: 60 | M22: =L22*K22 -> 143940 | P22: =MIN(K22,O22)*54 -> 129546 | Q22: =ROUNDDOWN(MIN(J22,N22)*0.5,0) -> 0 | S22: =ROUNDDOWN(MIN(K22,O22)*0.5,0) -> 1199 | W22: 149 | Z22: =P22+(W22*1)+(S22*5) -> 135690 | AA22: =M22-Z22 -> 8250 | AB22: 2199 | AC22: 60 | AD22: =AC22*AB22 -> 131940 | AG22: =MIN(AB22,AF22)*54 -> 118746 | AH22: =ROUNDDOWN((MIN(AB22,AF22)*0.5),0) -> 1099 | AL22: 149 | AO22: =(AB22*54)+(AL22*1)+(AH22*5) -> 124390 | AP22: =AD22-AO22 -> 7550 | AQ22: 2199 | AR22: 72 | AS22: =AR22*AQ22 -> 158328 | AV22: =MIN(AQ22,AU22)*66 -> 145134 | AY22: =ROUNDDOWN(MIN(AQ22,AU22)*0.5,0) -> 1099 | BC22: 149 | BF22: =AV22+(BC22*1)+(AY22*5) -> 150778 | BG22: =AS22-BF22 -> 7550 | BH22: 1999 | BI22: 72 | BJ22: =BI22*BH22 -> 143928 | BM22: =MIN(BH22,BL22)*66 -> 131934 | BN22: =ROUNDDOWN((MIN(BH22,BL22)*0.5),0) -> 999 | BR22: 149 | BU22: =BM22+(BR22*1)+(BN22*5) -> 137078 | BV22: =BJ22-BU22 -> 6850
E23: WT2116SHEG.ABGPETH | F23: Wash Tower 21 Kg | J23: 12M | K23: 1999 | L23: 60 | M23: =L23*K23 -> 119940 | P23: =MIN(K23,O23)*54 -> 107946 | Q23: =ROUNDDOWN(MIN(J23,N23)*0.5,0) -> 0 | S23: =ROUNDDOWN(MIN(K23,O23)*0.5,0) -> 999 | W23: 149 | Z23: =P23+(W23*1)+(S23*5) -> 113090 | AA23: =M23-Z23 -> 6850 | AB23: 1899 | AC23: 60 | AD23: =AC23*AB23 -> 113940 | AG23: =MIN(AB23,AF23)*54 -> 102546 | AH23: =ROUNDDOWN((MIN(AB23,AF23)*0.5),0) -> 949 | AL23: 149 | AO23: =(AB23*54)+(AL23*1)+(AH23*5) -> 107440 | AP23: =AD23-AO23 -> 6500 | AQ23: 1749 | AR23: 72 | AS23: =AR23*AQ23 -> 125928 | AV23: =MIN(AQ23,AU23)*66 -> 115434 | AY23: =ROUNDDOWN(MIN(AQ23,AU23)*0.5,0) -> 874 | BC23: 149 | BF23: =AV23+(BC23*1)+(AY23*5) -> 119953 | BG23: =AS23-BF23 -> 5975 | BH23: 1649 | BI23: 72 | BJ23: =BI23*BH23 -> 118728 | BM23: =MIN(BH23,BL23)*66 -> 108834 | BN23: =ROUNDDOWN((MIN(BH23,BL23)*0.5),0) -> 824 | BR23: 149 | BU23: =BM23+(BR23*1)+(BN23*5) -> 113103 | BV23: =BJ23-BU23 -> 5625
E24: WT1410NHEG.ABGPQTH | F24: Wash Tower 14 Kg (Green/Beige) | J24: 12M | K24: 1599 | L24: 60 | M24: =L24*K24 -> 95940 | P24: =MIN(K24,O24)*54 -> 86346 | Q24: =ROUNDDOWN(MIN(J24,N24)*0.5,0) -> 0 | S24: =ROUNDDOWN(MIN(K24,O24)*0.5,0) -> 799 | W24: 149 | Z24: =P24+(W24*1)+(S24*5) -> 90490 | AA24: =M24-Z24 -> 5450 | AB24: 1499 | AC24: 60 | AD24: =AC24*AB24 -> 89940 | AG24: =MIN(AB24,AF24)*54 -> 80946 | AH24: =ROUNDDOWN((MIN(AB24,AF24)*0.5),0) -> 749 | AL24: 149 | AO24: =(AB24*54)+(AL24*1)+(AH24*5) -> 84840 | AP24: =AD24-AO24 -> 5100 | AQ24: 1399 | AR24: 72 | AS24: =AR24*AQ24 -> 100728 | AV24: =MIN(AQ24,AU24)*66 -> 92334 | AY24: =ROUNDDOWN(MIN(AQ24,AU24)*0.5,0) -> 699 | BC24: 149 | BF24: =AV24+(BC24*1)+(AY24*5) -> 95978 | BG24: =AS24-BF24 -> 4750 | BH24: 1299 | BI24: 72 | BJ24: =BI24*BH24 -> 93528 | BM24: =MIN(BH24,BL24)*66 -> 85734 | BN24: =ROUNDDOWN((MIN(BH24,BL24)*0.5),0) -> 649 | BR24: 149 | BU24: =BM24+(BR24*1)+(BN24*5) -> 89128 | BV24: =BJ24-BU24 -> 4400
E25: WT1410NHEN.ABNPQTH | F25: Wash Tower 14 Kg (Navy/Beige) | J25: 12M | K25: 1599 | L25: 60 | M25: =L25*K25 -> 95940 | P25: =MIN(K25,O25)*54 -> 86346 | Q25: =ROUNDDOWN(MIN(J25,N25)*0.5,0) -> 0 | S25: =ROUNDDOWN(MIN(K25,O25)*0.5,0) -> 799 | W25: 149 | Z25: =P25+(W25*1)+(S25*5) -> 90490 | AA25: =M25-Z25 -> 5450 | AB25: 1499 | AC25: 60 | AD25: =AC25*AB25 -> 89940 | AG25: =MIN(AB25,AF25)*54 -> 80946 | AH25: =ROUNDDOWN((MIN(AB25,AF25)*0.5),0) -> 749 | AL25: 149 | AO25: =(AB25*54)+(AL25*1)+(AH25*5) -> 84840 | AP25: =AD25-AO25 -> 5100 | AQ25: 1399 | AR25: 72 | AS25: =AR25*AQ25 -> 100728 | AV25: =MIN(AQ25,AU25)*66 -> 92334 | AY25: =ROUNDDOWN(MIN(AQ25,AU25)*0.5,0) -> 699 | BC25: 149 | BF25: =AV25+(BC25*1)+(AY25*5) -> 95978 | BG25: =AS25-BF25 -> 4750 | BH25: 1299 | BI25: 72 | BJ25: =BI25*BH25 -> 93528 | BM25: =MIN(BH25,BL25)*66 -> 85734 | BN25: =ROUNDDOWN((MIN(BH25,BL25)*0.5),0) -> 649 | BR25: 149 | BU25: =BM25+(BR25*1)+(BN25*5) -> 89128 | BV25: =BJ25-BU25 -> 4400
E26: F2520RNTB.AEBPETH | F26: Wash&Dry (Wash20 Kg.Dry 10 Kg) | J26: 12M | K26: 899 | L26: 60 | M26: =L26*K26 -> 53940 | P26: =MIN(K26,O26)*54 -> 48546 | Q26: =ROUNDDOWN(MIN(J26,N26)*0.5,0) -> 0 | T26: =ROUNDDOWN(MIN(K26,O26)*0.5,0) -> 449 | Z26: =P26+(T26*6) -> 51240 | AA26: =M26-Z26 -> 2700 | AB26: 849 | AC26: 60 | AD26: =AC26*AB26 -> 50940 | AG26: =MIN(AB26,AF26)*54 -> 45846 | AI26: =ROUNDDOWN((MIN(AB26,AF26)*0.5),0) -> 424 | AO26: =(AB26*54)+(AI26*6) -> 48390 | AP26: =AD26-AO26 -> 2550 | AQ26: 849 | AR26: 72 | AS26: =AR26*AQ26 -> 61128 | AV26: =MIN(AQ26,AU26)*66 -> 56034 | AZ26: =ROUNDDOWN(MIN(AQ26,AU26)*0.5,0) -> 424 | BF26: =AV26+(AZ26*6) -> 58578 | BG26: =AS26-BF26 -> 2550 | BH26: 799 | BI26: 72 | BJ26: =BI26*BH26 -> 57528 | BM26: =MIN(BH26,BL26)*72 -> 57528 | BO26: =ROUNDDOWN((MIN(BH26,BL26)*0.5),0) -> 399 | BU26: =(BH26*66)+(BO26*6) -> 55128 | BV26: =BJ26-BU26 -> 2400
E27: FV1413H4M.AMBPETH | F27: Wash&Dry (Wash13 Kg.Dry 8 Kg) | J27: 12M | K27: 749 | L27: 60 | M27: =L27*K27 -> 44940 | P27: =MIN(K27,O27)*57 -> 42693 | X27: 149 | Z27: =P27+(X27*3) -> 43140 | AA27: =M27-Z27 -> 1800 | AB27: 649 | AC27: 60 | AD27: =AC27*AB27 -> 38940 | AG27: =MIN(AB27,AF27)*57 -> 36993 | AM27: 149 | AO27: =AG27+(AM27*3) -> 37440 | AP27: =AD27-AO27 -> 1500 | AQ27: 649 | AR27: 72 | AS27: =AR27*AQ27 -> 46728 | AV27: =MIN(AQ27,AU27)*69 -> 44781 | BD27: 149 | BF27: =AV27+(BD27*3) -> 45228 | BG27: =AS27-BF27 -> 1500 | BH27: 599 | BI27: 72 | BJ27: =BI27*BH27 -> 43128 | BM27: =MIN(BH27,BL27)*69 -> 41331 | BS27: 149 | BU27: =BM27+(BS27*3) -> 41778 | BV27: =BJ27-BU27 -> 1350
E28: FV1413S4M.AMBPETH | F28: 13kg Wash Only | J28: 12M | K28: 699 | L28: 60 | M28: =L28*K28 -> 41940 | P28: =MIN(K28,O28)*54 -> 37746 | Q28: =ROUNDDOWN(MIN(J28,N28)*0.5,0) -> 0 | T28: =ROUNDDOWN(MIN(K28,O28)*0.5,0) -> 349 | Z28: =P28+(T28*6) -> 39840 | AA28: =M28-Z28 -> 2100 | AB28: 599 | AC28: 60 | AD28: =AC28*AB28 -> 35940 | AG28: =MIN(AB28,AF28)*54 -> 32346 | AI28: =ROUNDDOWN((MIN(AB28,AF28)*0.5),0) -> 299 | AO28: =(AB28*54)+(AI28*6) -> 34140 | AP28: =AD28-AO28 -> 1800 | AQ28: 599 | AR28: 72 | AS28: =AR28*AQ28 -> 43128 | AV28: =MIN(AQ28,AU28)*66 -> 39534 | AZ28: =ROUNDDOWN(MIN(AQ28,AU28)*0.5,0) -> 299 | BF28: =AV28+(AZ28*6) -> 41328 | BG28: =AS28-BF28 -> 1800 | BH28: 549 | BI28: 72 | BJ28: =BI28*BH28 -> 39528 | BM28: =MIN(BH28,BL28)*66 -> 36234 | BO28: =ROUNDDOWN((MIN(BH28,BL28)*0.5),0) -> 274 | BU28: =BM28+(BO28*6) -> 37878 | BV28: =BJ28-BU28 -> 1650
E29: TX2723ST5J.APBPETH | F29: T/L V+ 23kg | J29: 12M | K29: =549+50+50 -> 649 | L29: 60 | M29: =L29*K29 -> 38940 | P29: =MIN(K29,O29)*60 -> 38940 | Q29: =ROUNDDOWN(MIN(J29,N29)*0.5,0) -> 0 | Z29: =P29+(T29*6) -> 38940 | AA29: =M29-Z29 -> 0 | AB29: =499+50+50 -> 599 | AC29: 60 | AD29: =AC29*AB29 -> 35940 | AG29: =MIN(AB29,AF29)*60 -> 35940 | AO29: =(AB29*60)+(AI29*0) -> 35940 | AP29: =AD29-AO29 -> 0 | AQ29: =499+50+50 -> 599 | AR29: 72 | AS29: =AR29*AQ29 -> 43128 | AV29: =MIN(AQ29,AU29)*72 -> 43128 | BF29: =AV29+(AZ29*0) -> 43128 | BG29: =AS29-BF29 -> 0 | BH29: =449+50+50 -> 549 | BI29: 72 | BJ29: =BI29*BH29 -> 39528 | BM29: =MIN(BH29,BL29)*72 -> 39528 | BU29: =BM29+(BO29*6) -> 39528 | BV29: =BJ29-BU29 -> 0
E30: TX2315DT5G.DEGPETH | F30: T/L 15 Kg | J30: 12M | K30: =499+50 -> 549 | L30: 60 | M30: =L30*K30 -> 32940 | P30: =MIN(K30,O30)*60 -> 32940 | Z30: =P30 -> 32940 | AA30: =M30-Z30 -> 0 | AB30: =399+50 -> 449 | AC30: 60 | AD30: =AC30*AB30 -> 26940 | AG30: =MIN(AB30,AF30)*60 -> 26940 | AO30: =AG30+(AI30*6) -> 26940 | AP30: =AD30-AO30 -> 0 | AQ30: =399+50+50 -> 499 | AR30: 72 | AS30: =AR30*AQ30 -> 35928 | AV30: =MIN(AQ30,AU30)*72 -> 35928 | BF30: =AV30 -> 35928 | BG30: =AS30-BF30 -> 0 | BH30: =299+50+50 -> 399 | BI30: 72 | BJ30: =BI30*BH30 -> 28728 | BM30: =MIN(BH30,BL30)*72 -> 28728 | BU30: =BM30 -> 28728 | BV30: =BJ30-BU30 -> 0
D31: OBS Subs. | E31: FV1409H4W.ABWPETH | F31: Wash&Dry (Wash9 Kg.Dry 5Kg) | J31: 12M | K31: =499-100 -> 399 | L31: 60 | M31: =L31*K31 -> 23940 | P31: =MIN(K31,O31)*60 -> 23940 | Z31: =P31+(V31*60) -> 23940 | AA31: =M31-Z31 -> 0 | AB31: =449-100 -> 349 | AC31: 60 | AD31: =AC31*AB31 -> 20940 | AG31: =MIN(AB31,AF31)*60 -> 20940 | AO31: =AG31+(AK31*60) -> 20940 | AP31: =AD31-AO31 -> 0 | AQ31: =449-100 -> 349 | AR31: 72 | AS31: =AR31*AQ31 -> 25128 | AV31: =MIN(AQ31,AU31)*72 -> 25128 | BF31: =AV31+(BB31*72) -> 25128 | BG31: =AS31-BF31 -> 0 | BH31: =399-100 -> 299 | BI31: 72 | BJ31: =BI31*BH31 -> 21528 | BM31: =MIN(BH31,BL31)*72 -> 21528 | BU31: =BM31+(BQ31*72) -> 21528 | BV31: =BJ31-BU31 -> 0
D32: OBS Subs. | E32: TX2725AT9G.AEGPETH | F32: T/L LG AI DD™ Inverter 25kg | J32: 12M | K32: =649+50+50-100 -> 649 | L32: 60 | M32: =L32*K32 -> 38940 | P32: =MIN(K32,O32)*60 -> 38940 | Z32: =P32 -> 38940 | AA32: =M32-Z32 -> 0 | AB32: =599+50+50-100 -> 599 | AC32: 60 | AD32: =AC32*AB32 -> 35940 | AG32: =MIN(AB32,AF32)*60 -> 35940 | AO32: =AG32+(AI32*0) -> 35940 | AP32: =AD32-AO32 -> 0 | AQ32: =599+50+50-100 -> 599 | AR32: 72 | AS32: =AR32*AQ32 -> 43128 | AV32: =MIN(AQ32,AU32)*72 -> 43128 | BF32: =AV32 -> 43128 | BG32: =AS32-BF32 -> 0 | BH32: =549+50+50-100 -> 549 | BI32: 72 | BJ32: =BI32*BH32 -> 39528 | BM32: =MIN(BH32,BL32)*72 -> 39528 | BU32: =BM32 -> 39528 | BV32: =BJ32-BU32 -> 0
C33: Dryer | E33: RV10VHP4B.BMBPETH | F33: 10kg | J33: 12M | K33: 849 | L33: 60 | M33: =L33*K33 -> 50940 | P33: =MIN(K33,O33)*54 -> 45846 | Q33: =ROUNDDOWN(MIN(J33,N33)*0.5,0) -> 0 | T33: =ROUNDDOWN(MIN(K33,O33)*0.5,0) -> 424 | Z33: =P33+(T33*6) -> 48390 | AA33: =M33-Z33 -> 2550 | AB33: 749 | AC33: 60 | AD33: =AC33*AB33 -> 44940 | AG33: =MIN(AB33,AF33)*54 -> 40446 | AI33: =ROUNDDOWN((MIN(AB33,AF33)*0.5),0) -> 374 | AO33: =AG33+(AI33*6) -> 42690 | AP33: =AD33-AO33 -> 2250 | AQ33: 749 | AR33: 72 | AS33: =AR33*AQ33 -> 53928 | AV33: =MIN(AQ33,AU33)*66 -> 49434 | AZ33: =ROUNDDOWN(MIN(AQ33,AU33)*0.5,0) -> 374 | BF33: =AV33+(AZ33*6) -> 51678 | BG33: =AS33-BF33 -> 2250 | BH33: 649 | BI33: 72 | BJ33: =BI33*BH33 -> 46728 | BM33: =MIN(BH33,BL33)*66 -> 42834 | BO33: =ROUNDDOWN((MIN(BH33,BL33)*0.5),0) -> 324 | BU33: =BM33+(BO33*6) -> 44778 | BV33: =BJ33-BU33 -> 1950
C34: STYLER | E34: S3MFC.ALBPETH | F34: 3 Coat hangers | J34: 12M | Z34: =P34+(T34*6) -> 0 | AB34: 899 | AC34: 60 | AD34: =AC34*AB34 -> 53940 | AG34: =MIN(AB34,AF34)*48 -> 43152 | AJ34: =ROUNDDOWN((MIN(AB34,AF34)*0.5),0) -> 449 | AL34: 149 | AO34: =AG34+(AL34*1)+(AJ34*11) -> 48240 | AP34: =AD34-AO34 -> 5700 | BH34: 799 | BI34: 72 | BJ34: =BI34*BH34 -> 57528 | BM34: =MIN(BH34,BL34)*60 -> 47940 | BP34: =ROUNDDOWN((MIN(BH34,BL34)*0.5),0) -> 399 | BR34: 149 | BU34: =BM34+(BR34*1)+(BP34*11) -> 52478 | BV34: =BJ34-BU34 -> 5050
C35: DW | E35: DFC335HM.ABMPETH | F35: Dish Washer | J35: 12M | K35: 899 | L35: 60 | M35: =L35*K35 -> 53940 | P35: =MIN(K35,O35)*48 -> 43152 | U35: =ROUNDDOWN((MIN(K35,O35)*0.5),0) -> 449 | W35: 149 | Z35: =P35+(W35*1)+(U35*11) -> 48240 | AA35: =M35-Z35 -> 5700 | AB35: 849 | AC35: 60 | AD35: =AC35*AB35 -> 50940 | AG35: =MIN(AB35,AF35)*48 -> 40752 | AJ35: =ROUNDDOWN((MIN(AB35,AF35)*0.5),0) -> 424 | AL35: 149 | AO35: =AG35+(AL35*1)+(AJ35*11) -> 45565 | AP35: =AD35-AO35 -> 5375 | AQ35: 799 | AR35: 72 | AS35: =AR35*AQ35 -> 57528 | AV35: =MIN(AQ35,AU35)*60 -> 47940 | BA35: =ROUNDDOWN(MIN(AQ35,AU35)*0.5,0) -> 399 | BC35: 149 | BF35: =AV35+(BC35*1)+(BA35*11) -> 52478 | BG35: =AS35-BF35 -> 5050 | BH35: 749 | BI35: 72 | BJ35: =BI35*BH35 -> 53928 | BM35: =MIN(BH35,BL35)*60 -> 44940 | BP35: =ROUNDDOWN((MIN(BH35,BL35)*0.5),0) -> 374 | BR35: 149 | BU35: =BM35+(BR35*1)+(BP35*11) -> 49203 | BV35: =BJ35-BU35 -> 4725
E36: DFC533FV.APYPETH | F36: Dish Washer | J36: 12M | K36: 749 | L36: 60 | M36: =L36*K36 -> 44940 | P36: =MIN(K36,O36)*48 -> 35952 | U36: =ROUNDDOWN((MIN(K36,O36)*0.5),0) -> 374 | W36: 149 | Z36: =P36+(W36*1)+(U36*11) -> 40215 | AA36: =M36-Z36 -> 4725 | AB36: 699 | AC36: 60 | AD36: =AC36*AB36 -> 41940 | AG36: =MIN(AB36,AF36)*48 -> 33552 | AJ36: =ROUNDDOWN((MIN(AB36,AF36)*0.5),0) -> 349 | AL36: 149 | AO36: =AG36+(AL36*1)+(AJ36*11) -> 37540 | AP36: =AD36-AO36 -> 4400 | AQ36: 649 | AR36: 72 | AS36: =AR36*AQ36 -> 46728 | AV36: =MIN(AQ36,AU36)*60 -> 38940 | BA36: =ROUNDDOWN(MIN(AQ36,AU36)*0.5,0) -> 324 | BC36: 149 | BF36: =AV36+(BC36*1)+(BA36*11) -> 42653 | BG36: =AS36-BF36 -> 4075 | BH36: 599 | BI36: 72 | BJ36: =BI36*BH36 -> 43128 | BM36: =MIN(BH36,BL36)*60 -> 35940 | BP36: =ROUNDDOWN((MIN(BH36,BL36)*0.5),0) -> 299 | BR36: 149 | BU36: =BM36+(BR36*1)+(BP36*11) -> 39378 | BV36: =BJ36-BU36 -> 3750
C37: MWO | E37: MS4295DIS.BBKPETH | F37: Microwave 42 ลิตร | J37: NoService 6Y | K37: =59+10+20+10 -> 99 | M37: =K37*72 -> 7128

Sheet VCC, AP, Dehumidifier
E1: Promotion Price June 2026
F2: Service | G2: Subscription Fee
G3: Contract 5Y
G4: VISIT | S4: SELF
C5: Classification | D5: Model | F5: Service Cycle | G5: Visit 5Y Monthly price | H5: Total Month | I5: Normal total price | J5: Cost | K5: Promotion Jun | L5: Promotion | M5: Disc.50% (6 รอบบิล) | N5: Promotion Jun (3 รอบบิล) | O5: Promotion Jun (6 รอบบิล) | P5: Disc.50% (25 รอบบิล) | Q5: Promotion Net | R5: Disc from Normal | S5: Self 5Y Monthly price | T5: Total Month | U5: Normal total price | V5: Cost | W5: Promotion Jun | X5: Promotion | Y5: Disc.50% (3 รอบบิล) | Z5: Disc.50% (6 รอบบิล) | AA5: Promotion Jun (3 รอบบิล) | AB5: Promotion Jun (6 รอบบิล) | AC5: Disc.50% (25 รอบบิล) | AD5: Promotion Net | AE5: Disc from Normal
C6: VCC | D6: VCC | E6: A9T-ULTRA.DCBPETH | F6: 12M | I6: =H6*G6 -> 0 | L6: =MIN(G6,K6)*56 -> 0 | S6: =649+50+50 -> 749 | T6: 60 | U6: =T6*S6 -> 44940 | X6: =MIN(S6,W6)*57 -> 42693 | Y6: =ROUNDDOWN((MIN(S6,W6)*0.5),0) -> 374 | AD6: =X6+(Y6*3) -> 43815 | AE6: =U6-AD6 -> 1125
E7: A9T-LITE.DCGPETH | F7: 12M | I7: =H7*G7 -> 0 | L7: =MIN(G7,K7)*56 -> 0 | S7: =499+50 -> 549 | T7: 60 | U7: =T7*S7 -> 32940 | X7: =MIN(S7,W7)*60 -> 32940 | AD7: =X7+(AB7*60) -> 32940 | AE7: =U7-AD7 -> 0
C8: AP | D8: Air Purifier | E8: AS60GHWG0.ABAE | F8: 12M | G8: =549-100 -> 449 | H8: 60 | I8: =H8*G8 -> 26940 | L8: =MIN(G8,K8)*54 -> 24246 | M8: =ROUNDDOWN(MIN(G8,K8)*0.5,0) -> 224 | Q8: =L8+(M8*6) -> 25590 | R8: =I8-Q8 -> 1350 | S8: =499-100 -> 399 | T8: 60 | U8: =T8*S8 -> 23940 | X8: =MIN(S8,W8)*54 -> 21546 | Z8: =ROUNDDOWN((MIN(S8,W8)*0.5),0) -> 199 | AD8: =X8+(Z8*6) -> 22740 | AE8: =U8-AD8 -> 1200
E9: AS60GHWG0.ABAE | F9: 6M | G9: =599-100 -> 499 | H9: 60 | I9: =H9*G9 -> 29940 | L9: =MIN(G9,K9)*54 -> 26946 | M9: =ROUNDDOWN(MIN(G9,K9)*0.5,0) -> 249 | Q9: =L9+(M9*6) -> 28440 | R9: =I9-Q9 -> 1500 | S9: =549-100 -> 449 | T9: 60 | U9: =T9*S9 -> 26940 | X9: =MIN(S9,W9)*54 -> 24246 | Z9: =ROUNDDOWN((MIN(S9,W9)*0.5),0) -> 224 | AD9: =X9+(Z9*6) -> 25590 | AE9: =U9-AD9 -> 1350
E10: AS65GDBY0.ABAE | F10: 12M | G10: =849-100 -> 749 | H10: 60 | I10: =H10*G10 -> 44940 | L10: =MIN(G10,K10)*57 -> 42693 | N10: 149 | Q10: =L10+(N10*3) -> 43140 | R10: =I10-Q10 -> 1800 | S10: =799-100 -> 699 | T10: 60 | U10: =T10*S10 -> 41940 | X10: =MIN(S10,W10)*57 -> 39843 | AA10: 149 | AD10: =X10+(AA10*3) -> 40290 | AE10: =U10-AD10 -> 1650
E11: AS65GDBY0.ABAE | F11: 6M | G11: =899-100 -> 799 | H11: 60 | I11: =H11*G11 -> 47940 | L11: =MIN(G11,K11)*57 -> 45543 | N11: 149 | Q11: =L11+(N11*3) -> 45990 | R11: =I11-Q11 -> 1950 | S11: =849-100 -> 749 | T11: 60 | U11: =T11*S11 -> 44940 | X11: =MIN(S11,W11)*57 -> 42693 | AA11: 149 | AD11: =X11+(AA11*3) -> 43140 | AE11: =U11-AD11 -> 1800
E12: AS10GDBY0.ABAE | F12: 12M | G12: =1299-150 -> 1149 | H12: 60 | I12: =H12*G12 -> 68940 | L12: =MIN(G12,K12)*57 -> 65493 | N12: 149 | Q12: =L12+(N12*3) -> 65940 | R12: =I12-Q12 -> 3000 | S12: =1249-150 -> 1099 | T12: 60 | U12: =T12*S12 -> 65940 | X12: =MIN(S12,W12)*57 -> 62643 | AA12: 149 | AD12: =X12+(AA12*3) -> 63090 | AE12: =U12-AD12 -> 2850
E13: AS10GDBY0.ABAE | F13: 6M | G13: =1349-150 -> 1199 | H13: 60 | I13: =H13*G13 -> 71940 | L13: =MIN(G13,K13)*57 -> 68343 | N13: 149 | Q13: =L13+(N13*3) -> 68790 | R13: =I13-Q13 -> 3150 | S13: =1299-150 -> 1149 | T13: 60 | U13: =T13*S13 -> 68940 | X13: =MIN(S13,W13)*57 -> 65493 | AA13: 149 | AD13: =X13+(AA13*3) -> 65940 | AE13: =U13-AD13 -> 3000
E14: AS25GCBY0.ABAE | F14: 12M | G14: 599 | H14: 60 | I14: =H14*G14 -> 35940 | L14: =MIN(G14,K14)*54 -> 32346 | M14: =ROUNDDOWN(G14*0.5,0) -> 299 | Q14: =L14+(M14*6) -> 34140 | R14: =I14-Q14 -> 1800 | S14: 549 | T14: 60 | U14: =S14*60 -> 32940 | X14: =S14*54 -> 29646 | Z14: =ROUNDDOWN(S14*0.5,0) -> 274 | AD14: =X14+(Z14*6) -> 31290 | AE14: =U14-AD14 -> 1650
D15: OBS Subs. | E15: AS35GGW10.ATH | F15: 6M | G15: =349-50-50 -> 249 | H15: 60 | I15: =H15*G15 -> 14940 | L15: =MIN(G15,K15)*60 -> 14940 | Q15: =L15+(O15*60) -> 14940 | R15: =I15-Q15 -> 0 | S15: =299-50-50 -> 199 | T15: 60 | U15: =T15*S15 -> 11940 | X15: =MIN(S15,W15)*60 -> 11940 | AD15: =X15+(AB15*60) -> 11940 | AE15: =U15-AD15 -> 0
C16: Dehumidifier | E16: DD23GMWE1.ATH | F16: 12M | G16: 599 | H16: 60 | I16: =H16*G16 -> 35940 | L16: =MIN(G16,K16)*54 -> 32346 | O16: 149 | Q16: =L16+(O16*6) -> 33240 | R16: =I16-Q16 -> 2700 | S16: 549 | T16: 60 | U16: =S16*60 -> 32940 | X16: =S16*54 -> 29646 | AB16: 149 | AD16: =X16+(AB16*6) -> 30540 | AE16: =U16-AD16 -> 2400
D17: OBS Subs. | E17: MD19GQGA1.ATH | F17: 12M | G17: =549-100 -> 449 | H17: 60 | I17: =H17*G17 -> 26940 | L17: =MIN(G17,K17)*60 -> 26940 | Q17: =L17+(O17*6) -> 26940 | R17: =I17-Q17 -> 0 | S17: =499-100 -> 399 | T17: 60 | U17: =S17*60 -> 23940 | X17: =S17*60 -> 23940 | AD17: =X17+(AB17*6) -> 23940 | AE17: =U17-AD17 -> 0

Sheet RAC, SAC
E1: Promotion Price Jun 2026
L2: Service | M2: Subscription Fee
M3: Contract 5Y
C4: Classification | D4: Model | I4: PTO 1 | J4: PTO 2 | K4: PTO 3 | L4: Service Cycle | M4: Visit 5Y Monthly price | N4: Total Month | O4: Normal total price | P4: Cost | Q4: Promotion Jun | R4: Promotion | S4: Promotion Jun (1 รอบบิล) | T4: Disc.50% (5 รอบบิล) | U4: Disc.50% (6 รอบบิล) | V4: Disc.50% (12 รอบบิล) | W4: Promotion Net | X4: Disc from Normal
C5: RAC | E5: SAQ11A.S11 | F5: เบอร์ 5/Dual Cool /5 Star/WiFi | G5: SAQ11AN.S11 | H5: SAQ11AU.S11 | L5: 12M | M5: =749+50 -> 799 | N5: 60 | O5: =N5*M5 -> 47940 | R5: =MIN(M5,Q5)*54 -> 43146 | U5: =ROUNDDOWN(MIN(M5,Q5)*0.5,0) -> 399 | W5: =R5+(U5*6) -> 45540 | X5: =O5-W5 -> 2400
E6: SAQ11A.S11 | L6: 6M | M6: =849+50 -> 899 | N6: 60 | O6: =N6*M6 -> 53940 | R6: =MIN(M6,Q6)*54 -> 48546 | U6: =ROUNDDOWN(MIN(M6,Q6)*0.5,0) -> 449 | W6: =R6+(U6*6) -> 51240 | X6: =O6-W6 -> 2700
E7: SAQ13A.S11 | G7: SAQ13AN.S11 | H7: SAQ13AU.S11 | L7: 12M | M7: =799+50 -> 849 | N7: 60 | O7: =N7*M7 -> 50940 | R7: =MIN(M7,Q7)*54 -> 45846 | U7: =ROUNDDOWN(MIN(M7,Q7)*0.5,0) -> 424 | W7: =R7+(U7*6) -> 48390 | X7: =O7-W7 -> 2550
E8: SAQ13A.S11 | L8: 6M | M8: =899+50 -> 949 | N8: 60 | O8: =N8*M8 -> 56940 | R8: =MIN(M8,Q8)*54 -> 51246 | U8: =ROUNDDOWN(MIN(M8,Q8)*0.5,0) -> 474 | W8: =R8+(U8*6) -> 54090 | X8: =O8-W8 -> 2850
E9: SAQ18B.S21 | F9: เบอร์ 5/Dual Cool /4 Star/WiFi | G9: SAQ18BN.S21 | H9: SAQ18BU.S21 | L9: 12M | M9: =999+50 -> 1049 | N9: 60 | O9: =N9*M9 -> 62940 | R9: =MIN(M9,Q9)*54 -> 56646 | U9: =ROUNDDOWN(MIN(M9,Q9)*0.5,0) -> 524 | W9: =R9+(U9*6) -> 59790 | X9: =O9-W9 -> 3150
E10: SAQ18B.S21 | L10: 6M | M10: =1099+50 -> 1149 | N10: 60 | O10: =N10*M10 -> 68940 | R10: =MIN(M10,Q10)*54 -> 62046 | U10: =ROUNDDOWN(MIN(M10,Q10)*0.5,0) -> 574 | W10: =R10+(U10*6) -> 65490 | X10: =O10-W10 -> 3450
E11: SAQ24B.S21 | F11: เบอร์ 5/Dual Cool /3 Star/WiFi | G11: SAQ24BN.S21 | H11: SAQ24BU.S21 | L11: 12M | M11: 1199 | N11: 60 | O11: =N11*M11 -> 71940 | R11: =MIN(M11,Q11)*54 -> 64746 | U11: =ROUNDDOWN(MIN(M11,Q11)*0.5,0) -> 599 | W11: =R11+(U11*6) -> 68340 | X11: =O11-W11 -> 3600
E12: SAQ24B.S21 | L12: 6M | M12: 1299 | N12: 60 | O12: =N12*M12 -> 77940 | R12: =MIN(M12,Q12)*54 -> 70146 | U12: =ROUNDDOWN(MIN(M12,Q12)*0.5,0) -> 649 | W12: =R12+(U12*6) -> 74040 | X12: =O12-W12 -> 3900
E13: SIQ11B.S01 | F13: เบอร์ 5/Dual Cool /1 Star/WiFi | G13: SIQ11BN.S01 | H13: SIQ11BU.S01 | L13: 12M | M13: 599 | N13: 60 | O13: =N13*M13 -> 35940 | R13: =MIN(M13,Q13)*54 -> 32346 | U13: =ROUNDDOWN(MIN(M13,Q13)*0.5,0) -> 299 | W13: =R13+(U13*6) -> 34140 | X13: =O13-W13 -> 1800
E14: SIQ11B.S01 | L14: 6M | M14: 699 | N14: 60 | O14: =N14*M14 -> 41940 | R14: =MIN(M14,Q14)*54 -> 37746 | U14: =ROUNDDOWN(MIN(M14,Q14)*0.5,0) -> 349 | W14: =R14+(U14*6) -> 39840 | X14: =O14-W14 -> 2100
E15: SIQ13B.S01 | G15: SIQ13BN.S01 | H15: SIQ13BU.S01 | L15: 12M | M15: 699 | N15: 60 | O15: =N15*M15 -> 41940 | R15: =MIN(M15,Q15)*54 -> 37746 | U15: =ROUNDDOWN(MIN(M15,Q15)*0.5,0) -> 349 | W15: =R15+(U15*6) -> 39840 | X15: =O15-W15 -> 2100
E16: SIQ13B.S01 | L16: 6M | M16: 799 | N16: 60 | O16: =N16*M16 -> 47940 | R16: =MIN(M16,Q16)*54 -> 43146 | U16: =ROUNDDOWN(MIN(M16,Q16)*0.5,0) -> 399 | W16: =R16+(U16*6) -> 45540 | X16: =O16-W16 -> 2400
E17: SIQ18B.S11 | G17: SIQ18BN.S11 | H17: SIQ18BU.S11 | L17: 12M | M17: 899 | N17: 60 | O17: =N17*M17 -> 53940 | R17: =MIN(M17,Q17)*54 -> 48546 | U17: =ROUNDDOWN(MIN(M17,Q17)*0.5,0) -> 449 | W17: =R17+(U17*6) -> 51240 | X17: =O17-W17 -> 2700
E18: SIQ18B.S11 | L18: 6M | M18: 999 | N18: 60 | O18: =N18*M18 -> 59940 | R18: =MIN(M18,Q18)*54 -> 53946 | U18: =ROUNDDOWN(MIN(M18,Q18)*0.5,0) -> 499 | W18: =R18+(U18*6) -> 56940 | X18: =O18-W18 -> 3000
E19: SIQ24B.S11 | G19: SIQ24BN.S11 | H19: SIQ24BU.S11 | L19: 12M | M19: 1099 | N19: 60 | O19: =N19*M19 -> 65940 | R19: =MIN(M19,Q19)*54 -> 59346 | U19: =ROUNDDOWN(MIN(M19,Q19)*0.5,0) -> 549 | W19: =R19+(U19*6) -> 62640 | X19: =O19-W19 -> 3300
E20: SIQ24B.S11 | L20: 6M | M20: 1199 | N20: 60 | O20: =N20*M20 -> 71940 | R20: =MIN(M20,Q20)*54 -> 64746 | U20: =ROUNDDOWN(MIN(M20,Q20)*0.5,0) -> 599 | W20: =R20+(U20*6) -> 68340 | X20: =O20-W20 -> 3600
D21: New June ArtCool | E21: ART13A.SR1 | F21: Artcool | G21: ART13AN.SR1 | H21: ART13AU.SR1 | L21: 12M | M21: 949 | N21: 60 | O21: =N21*M21 -> 56940 | R21: =MIN(M21,Q21)*54 -> 51246 | S21: 149 | T21: =ROUNDDOWN(MIN(M21,Q21)*0.5,0) -> 474 | W21: =R21+(S21*1)+(T21*5) -> 53765 | X21: =O21-W21 -> 3175
E22: ART13A.SR1 | L22: 6M | M22: 1049 | N22: 60 | O22: =N22*M22 -> 62940 | R22: =MIN(M22,Q22)*54 -> 56646 | S22: 149 | T22: =ROUNDDOWN(MIN(M22,Q22)*0.5,0) -> 524 | W22: =R22+(S22*1)+(T22*5) -> 59415 | X22: =O22-W22 -> 3525
D23: New June ArtCool | E23: ART18A.SR1 | G23: ART18AN.SR1 | H23: ART18AU.SR1 | L23: 12M | M23: 1149 | N23: 60 | O23: =N23*M23 -> 68940 | R23: =MIN(M23,Q23)*54 -> 62046 | S23: 149 | T23: =ROUNDDOWN(MIN(M23,Q23)*0.5,0) -> 574 | W23: =R23+(S23*1)+(T23*5) -> 65065 | X23: =O23-W23 -> 3875
E24: ART18A.SR1 | L24: 6M | M24: 1249 | N24: 60 | O24: =N24*M24 -> 74940 | R24: =MIN(M24,Q24)*54 -> 67446 | S24: 149 | T24: =ROUNDDOWN(MIN(M24,Q24)*0.5,0) -> 624 | W24: =R24+(S24*1)+(T24*5) -> 70715 | X24: =O24-W24 -> 4225
D25: OBS Subs. | E25: IXY11A.JU1 | F25: เบอร์ 5/Dual Cool / 0 star/ Wifi | G25: IXY11AN.JU1 | H25: IXY11AU.JU1 | L25: 12M | M25: =499-100 -> 399 | N25: 60 | O25: =N25*M25 -> 23940 | R25: =MIN(M25,Q25)*60 -> 23940 | W25: =R25+(V25*60) -> 23940 | X25: =O25-W25 -> 0
E26: IXY11A.JU1 | L26: 6M | M26: =599-100 -> 499 | N26: 60 | O26: =N26*M26 -> 29940 | R26: =MIN(M26,Q26)*60 -> 29940 | W26: =R26+(V26*60) -> 29940 | X26: =O26-W26 -> 0
D27: OBS Subs. | E27: IXY13A.JU1 | G27: IXY13AN.JU1 | H27: IXY13AU.JU1 | L27: 12M | M27: =549-100 -> 449 | N27: 60 | O27: =N27*M27 -> 26940 | R27: =MIN(M27,Q27)*60 -> 26940 | W27: =R27+(V27*60) -> 26940 | X27: =O27-W27 -> 0
E28: IXY13A.JU1 | L28: 6M | M28: =649-100 -> 549 | N28: 60 | O28: =N28*M28 -> 32940 | R28: =MIN(M28,Q28)*60 -> 32940 | W28: =R28+(V28*60) -> 32940 | X28: =O28-W28 -> 0
D29: OBS Subs. | E29: IXY18A.KU1 | G29: IXY18AN.KU1 | H29: IXY18AU.KU1 | L29: 12M | M29: =749-150 -> 599 | N29: 60 | O29: =N29*M29 -> 35940 | R29: =MIN(M29,Q29)*60 -> 35940 | W29: =R29+(V29*60) -> 35940 | X29: =O29-W29 -> 0
E30: IXY18A.KU1 | L30: 6M | M30: =849-150 -> 699 | N30: 60 | O30: =N30*M30 -> 41940 | R30: =MIN(M30,Q30)*60 -> 41940 | W30: =R30+(V30*60) -> 41940 | X30: =O30-W30 -> 0
D31: OBS Subs. | E31: IXY24A.KU1 | G31: IXY24AN.KU1 | H31: IXY24AU.KU1 | L31: 12M | M31: =899-150 -> 749 | N31: 60 | O31: =N31*M31 -> 44940 | R31: =MIN(M31,Q31)*60 -> 44940 | W31: =R31+(V31*60) -> 44940 | X31: =O31-W31 -> 0
E32: IXY24A.KU1 | L32: 6M | M32: =999-150 -> 849 | N32: 60 | O32: =N32*M32 -> 50940 | R32: =MIN(M32,Q32)*60 -> 50940 | W32: =R32+(V32*60) -> 50940 | X32: =O32-W32 -> 0
C33: SAC | D33: Ceiling | E33: ZV-Q18GM1E0.EWGHATH | F33: Ceiling Type/ 17100 Btu | G33: ZVNQ18GM1E0.ENWTATH | H33: ZVUQ18GM1E0.EWGHATH | K33: PWFMDD200.ENCXLEU | L33: 4M | M33: =1399+100+100 -> 1599 | N33: 60 | O33: =N33*M33 -> 95940
D34: Cassette 4 Way | E34: ZT-Q18GPLE0.EWGHATH | F34: 4 Way | G34: ZTNQ18GPLE0.ENWHATH | H34: ZTUQ18GPLE0.EWGHATH | I34: PT-MPGW0.ENCXCOM | J34: PTAHMP0.ENCXCOM | K34: PWFMDD200.ENCXLEU | L34: 4M | M34: =1649+100+100+100 -> 1949 | N34: 60 | O34: =N34*M34 -> 116940
D35: Cassette 1 way | E35: ZT-Q12GULA0.EWGHATH | F35: 1 way | G35: ZTNQ12GULA0.ENWHATH | H35: ZTUQ12GULA0.EWGHATH | I35: PT-UPHG0.ENCXCOM | J35: PTAHTP0.ENCXCOM | K35: PWFMDD200.ENCXLEU | L35: 4M | M35: =1299+100+100 -> 1499 | N35: 60 | O35: =N35*M35 -> 89940
D36: Cassette Round | E36: ZT-Q48GYLA0.EWGHATH | F36: Round | G36: ZTNQ48GYLA0.ENWBATH | H36: ZTUQ48GYLA0.EWGHATH | J36: PTAHYP0.ENCXGLO | K36: PWFMDD200.ENCXLEU | L36: 4M | M36: =2499+100+100+100 -> 2799 | N36: 60 | O36: =N36*M36 -> 167940
K39: PWFMDD200.ENCXLEU -> PWFMDD202.ENCXCOM
H42: OUTRIGHT_SELF_2Y_B2B_SC ASSET

Sheet TV, MNT, AV
E1: Promotion Price Jun 2026
C2: Classification | D2: Model | G2: Contract | H2: Monthly fee | I2: Advance Payment 50% 12M | J2: Subscription Fee
J3: Montly fee | K3: Contract 5Y
J4: 1M-12M | K4: Service Cycle | L4: Total Month | M4: Normal total price | N4: Cost | O4: Promotion Jun | P4: 13M-60M (48) | Q4: 13M-15M (3) | R4: 16M-60M (45) | S4: 13M-18M (6) | T4: 19M-60M (42) | U4: 13M-24M (12) | V4: 13M-42M (30) | W4: 43M-60M (18) | X4: 25M-60M (36) | Y4: Promotion Net | Z4: Disc from Normal
C5: TV | E5: OLED77C6PSA.ATM | G5: 5 Y | H5: 1999 | I5: =J5*12 -> 11994 | J5: =H5*0.5 -> 999.5 | K5: No | L5: 60 | M5: =H5*L5 -> 119940 | O5: 13M~18M (6 Months 50% Discount) | S5: =ROUNDDOWN(H5*0.5,0) -> 999 | T5: =H5 -> 1999 | Y5: =I5+(J5*12)+(S5*6)+(T5*42) -> 113940 | Z5: =M5-Y5 -> 6000
E6: OLED65C6PSA.ATM | G6: 5 Y | H6: 1299 | I6: =J6*12 -> 7794 | J6: =H6*0.5 -> 649.5 | K6: No | L6: 60 | M6: =H6*L6 -> 77940 | O6: 13M~18M (6 Months 50% Discount) | S6: =ROUNDDOWN(H6*0.5,0) -> 649 | T6: =H6 -> 1299 | Y6: =I6+(J6*12)+(S6*6)+(T6*42) -> 74040 | Z6: =M6-Y6 -> 3900
E7: OLED55C6PSA.ATM | G7: 5 Y | H7: 1099 | I7: =J7*12 -> 6594 | J7: =H7*0.5 -> 549.5 | K7: No | L7: 60 | M7: =H7*L7 -> 65940 | O7: 13M~18M (6 Months 50% Discount) | S7: =ROUNDDOWN(H7*0.5,0) -> 549 | T7: =H7 -> 1099 | Y7: =I7+(J7*12)+(S7*6)+(T7*42) -> 62640 | Z7: =M7-Y7 -> 3300
D8: New June | E8: 100QNED86BS.ATM | F8: (W24 8-14/6) /ทีวี 100" LG QNED evo AI Mini LED QNED86 4K | G8: 5 Y | H8: 2599 | I8: =J8*12 -> 15594 | J8: =MIN(U8,H8)*50% -> 1299.5 | K8: No | L8: 60 | M8: =H8*L8 -> 155940 | O8: 13M~18M (6 Months 50% Discount) | S8: =ROUNDDOWN(H8*0.5,0) -> 1299 | T8: =H8 -> 2599 | Y8: =I8+(J8*12)+(S8*6)+(T8*42) -> 148140 | Z8: =M8-Y8 -> 7800
E9: 85QNED80BSA.ATM | G9: 5 Y | H9: 1349 | I9: =J9*12 -> 8094 | J9: =MIN(U9,H9)*50% -> 674.5 | K9: No | L9: 60 | M9: =H9*L9 -> 80940 | P9: =H9 -> 1349 | Y9: =I9+(J9*12)+(P9*48) -> 80940 | Z9: =M9-Y9 -> 0
E10: 65QNED80BSA.ATM | G10: 5 Y | H10: 649 | I10: =J10*12 -> 3894 | J10: =MIN(U10,H10)*50% -> 324.5 | K10: No | L10: 60 | M10: =H10*L10 -> 38940 | P10: =H10 -> 649 | Y10: =I10+(J10*12)+(P10*48) -> 38940 | Z10: =M10-Y10 -> 0
E11: 55QNED80BSA.ATM | G11: 5 Y | H11: 549 | I11: =J11*12 -> 3294 | J11: =MIN(U11,H11)*50% -> 274.5 | K11: No | L11: 60 | M11: =H11*L11 -> 32940 | P11: =H11 -> 549 | Y11: =I11+(J11*12)+(P11*48) -> 32940 | Z11: =M11-Y11 -> 0
D12: New June | E12: 75NU855BPSA.ATM | F12: (W24 8-14/6) | H12: 699 | I12: =J12*12 -> 4194 | J12: =MIN(U12,H12)*50% -> 349.5 | K12: No | L12: 60 | M12: =H12*L12 -> 41940 | P12: =H12 -> 699 | Y12: =I12+(J12*12)+(P12*48) -> 41940 | Z12: =M12-Y12 -> 0
E13: 65NU855BPSA.ATM | F13: (W17 20-26/4) | G13: 5 Y | H13: =499+50 -> 549 | I13: =J13*12 -> 3294 | J13: =MIN(U13,H13)*50% -> 274.5 | K13: No | L13: 60 | M13: =H13*L13 -> 32940 | P13: =H13 -> 549 | Y13: =I13+(J13*12)+(P13*48) -> 32940 | Z13: =M13-Y13 -> 0
E14: 27LX6TDGA.ATM | F14: Continue | G14: 5 Y | H14: =649+100 -> 749 | I14: =J14*12 -> 4494 | J14: =H14*0.5 -> 374.5 | K14: No | L14: 60 | M14: =H14*L14 -> 44940 | O14: 13M~24M (12 Months 50% Discount) | U14: =ROUNDDOWN(H14*0.5,0) -> 374 | X14: =H14 -> 749 | Y14: =I14+(J14*12)+(U14*12)+(X14*36) -> 40440 | Z14: =M14-Y14 -> 4500
D15: OBS Subs. | E15: OLED48C6PSA.ATM | G15: 5 Y | H15: =799-100 -> 699 | I15: =J15*12 -> 4194 | J15: =H15*0.5 -> 349.5 | K15: No | L15: 60 | M15: =H15*L15 -> 41940 | P15: =H15 -> 699 | Y15: =I15+(J15*12)+(P15*48) -> 41940 | Z15: =M15-Y15 -> 0
D16: OBS Subs. | E16: 75QNED86BSA.ATM | G16: 5 Y | H16: =999-150 -> 849 | I16: =J16*12 -> 5094 | J16: =MIN(U16,H16)*50% -> 424.5 | K16: No | L16: 60 | M16: =H16*L16 -> 50940 | P16: =H16 -> 849 | Y16: =I16+(J16*12)+(P16*48) -> 50940 | Z16: =M16-Y16 -> 0
C17: MNT | E17: 45GX950A-B.ATM | G17: 5Y | H17: =1399+100 -> 1499 | I17: =J17*12 -> 8994 | J17: =H17*0.5 -> 749.5 | K17: No | L17: 60 | M17: =H17*L17 -> 89940 | O17: 13M~18M (6 Months 50% Discount) | S17: =ROUNDDOWN(H17*0.5,0) -> 749 | T17: =H17 -> 1499 | Y17: =I17+(J17*12)+(S17*6)+(T17*42) -> 85440 | Z17: =M17-Y17 -> 4500
D18: New June | E18: 52G930B-B.ATM | G18: 5Y | H18: 1199 | I18: =J18*12 -> 7194 | J18: =H18*0.5 -> 599.5 | K18: No | L18: 60 | M18: =H18*L18 -> 71940 | O18: 13M~18M (6 Months 50% Discount) | S18: =ROUNDDOWN(H18*0.5,0) -> 599 | T18: =H18 -> 1199 | Y18: =I18+(J18*12)+(S18*6)+(T18*42) -> 68340 | Z18: =M18-Y18 -> 3600
D19: New June | E19: 40U990A-W.ATM | F19: W/in | G19: 5Y | H19: 999 | I19: =J19*12 -> 5994 | J19: =H19*0.5 -> 499.5 | K19: No | L19: 60 | M19: =H19*L19 -> 59940 | O19: 13M~18M (6 Months 50% Discount) | S19: =ROUNDDOWN(H19*0.5,0) -> 499 | T19: =H19 -> 999 | Y19: =I19+(J19*12)+(S19*6)+(T19*42) -> 56940 | Z19: =M19-Y19 -> 3000
E20: 32U889SA-W.ATM | G20: 5 Y | H20: =599+100 -> 699 | I20: =J20*12 -> 4194 | J20: =H20*0.5 -> 349.5 | K20: No | L20: 60 | M20: =H20*L20 -> 41940 | O20: 13M~24M (12 Months 50% Discount) | U20: =ROUNDDOWN(H20*0.5,0) -> 349 | X20: =H20 -> 699 | Y20: =I20+(J20*12)+(U20*12)+(X20*36) -> 37740 | Z20: =M20-Y20 -> 4200
E21: 34U650A-B.ATM | F21: (W13 | G21: 5 Y | H21: 399 | I21: =J21*12 -> 2394 | J21: =H21*0.5 -> 199.5 | K21: No | L21: 60 | M21: =H21*L21 -> 23940 | P21: =H21 -> 399 | Y21: =I21+(J21*12)+(P21*48) -> 23940 | Z21: =M21-Y21 -> 0
D22: OBS Subs. | E22: 27GX704A-B.ATM | G22: 5Y | H22: =449-100 -> 349 | I22: =J22*12 -> 2094 | J22: =MIN(U22,H22)*50% -> 174.5 | K22: No | L22: 60 | M22: =H22*L22 -> 20940 | O22: 13M~15M (3 Months 50% Discount) | Q22: =ROUNDDOWN(H22*0.5,0) -> 174 | R22: =H22 -> 349 | Y22: =I22+(J22*12)+(Q22*3)+(R22*45) -> 20415 | Z22: =M22-Y22 -> 525
C23: AV | E23: GRAB.ATHALBK | G23: 5 Y | H23: =79+20+10 -> 109 | I23: =J23*12 -> 654 | J23: =MIN(U23,H23)*50% -> 54.5 | K23: No | L23: 60 | M23: =H23*L23 -> 6540 | P23: =H23 -> 109 | Y23: =I23+(J23*12)+(P23*48) -> 6540 | Z23: =M23-Y23 -> 0
E24: BOUNCE.ATHALBK | G24: 5 Y | H24: =109+20+10 -> 139 | I24: =J24*12 -> 834 | J24: =MIN(U24,H24)*50% -> 69.5 | K24: No | L24: 60 | M24: =H24*L24 -> 8340 | P24: =H24 -> 139 | Y24: =I24+(J24*12)+(P24*48) -> 8340 | Z24: =M24-Y24 -> 0
E25: STAGE301.ATHALBK | G25: 5Y | H25: 299 | I25: =J25*12 -> 1794 | J25: =MIN(U25,H25)*50% -> 149.5 | K25: No | L25: 60 | M25: =H25*L25 -> 17940 | P25: =H25 -> 299 | Y25: =I25+(J25*12)+(P25*48) -> 17940 | Z25: =M25-Y25 -> 0
E26: S95TR.DTHALLK | G26: 5 Y | H26: =329+70+50 -> 449 | I26: =J26*12 -> 2694 | J26: =MIN(U26,H26)*50% -> 224.5 | K26: No | L26: 60 | M26: =H26*L26 -> 26940 | P26: =H26 -> 449 | Y26: =I26+(J26*12)+(P26*48) -> 26940 | Z26: =M26-Y26 -> 0
D27: Temporary Closed/ Supply W26 22/6 | E27: S70TY.ATHALLD | G27: 5 Y | H27: =159+10+20 -> 189 | I27: =J27*12 -> 1134 | J27: =MIN(U27,H27)*50% -> 94.5 | K27: No | L27: 60 | M27: =H27*L27 -> 11340 | P27: =H27 -> 189 | Y27: =I27+(J27*12)+(P27*48) -> 11340 | Z27: =M27-Y27 -> 0

Sheet 2606_RAW_All Channel
AQ1: =AVERAGE(AQ4:AQ183) -> 0.029616195
P2: As Is | AC2: To Be | BH2: To Be (August)
A3: Month | B3: Division | C3: Operation | D3: Model | G3: Exclusive Model | H3: Outright Price | I3: Contract (Year) | J3: Care Type | K3: Service Cycle (M) | L3: Original Price | M3: Original Total Price | N3: COI 2026 | O3: Sales (EA/Mon) | P3: As Is Price (THB) | Q3: Discount (THB) | R3: As Is Total Price (THB) | S3: COI | T3: Special Price | U3: Special Price Discount (Month) | V3: 50% Discount (Month) | W3: Total Promotion (THB) | X3: Total Promotion Price (THB) | Y3: Promotion % | Z3: vs Outright | AA3: COI Promotion | AB3: Bad Debt | AC3: To Be Price (THB) | AD3: Increase (To be - As Is) | AE3: Logic | AF3: To be Total Price (THB) | AG3: Increase Total Price (To be - As Is) | AH3: Special Price | AI3: COI | AJ3: Special Price 149THB/Month | AK3: 50% Discount (Month) | AL3: Total Promotion (THB) | AM3: Total Promotion Price (THB) | AN3: Promotion % | AO3: vs Outright | AP3: Increase (To be - As Is) | AQ3: Increase % (To be - As Is) | AR3: COI Promotion | AS3: Remark | AT3: Reflection | AU3: As Is Norma l - To be | AV3: Same | AW3: To Be Price (THB) | AX3: Increase (To be - As) | AY3: To be Total Price (THB) | AZ3: Special Price | BA3: 50% Discount (Month) | BB3: Total Promotion (THB) | BC3: Total Operation Price (THB) | BD3: Increase (To be - As) | BE3: Increase % (To be - As) | BF3: COI Promotion | BG3: Remark | BH3: To Be Price (THB) | BI3: To Be Price (THB) | BJ3: Increase (To be - As) | BK3: To be Total Price (THB) | BL3: Special Price | BM3: 50% Discount (Month) | BN3: Total Promotion (THB) | BO3: Total Operation Price (THB) | BP3: Increase (To be - As) | BQ3: Increase % (To be - As) | BR3: COI Promotion | BS3: Remark | BT3: Apr Sales | BW3: =IF(AA4>17%,AA4-2%,AA4) -> -0.10188921
A4: 2606 | B4: REF | C4: DST | D4: PTOX24FFCR2.APTO | E4: GC-X24FFCRB.AEVPLM1 | F4: REF3FILTER2.AETC | G4: =IFERROR(VLOOKUP(D4,[3]전용!E:J,6,0),"") | H4: 77666.667 | I4: 5 | J4: Visit | K4: 6 | L4: 1749 | M4: =L4*LEFT(I4,1)*12 -> 104940 | N4: 0.15 | P4: 1349 | Q4: =L4-P4 -> 400 | R4: =P4*LEFT(I4,1)*12 -> 80940 | S4: =AA4-(Y4/2) -> -0.089389211 | V4: 3 | W4: =(P4-T4)*U4+V4*P4*0.5 -> 2023.5 | X4: =R4-W4 -> 78916.5 | Y4: =X4/R4-1 -> -0.025 | Z4: =IFERROR(X4/H4,"") -> 1.0160923 | AA4: -0.10188921 | AB4: 0.0213149 | AC4: =P4+AD4 -> 1449 | AD4: 100 | AE4: =IF(AA4>10%,0,IF(AA4>5%,P4*0.04,IF(AA4>0%,P4*0.04, P4*0.1))) -> 134.9 | AF4: =AC4*LEFT(I4,1)*12 -> 86940 | AG4: =AF4/R4-1 -> 0.074128984 | AH4: 149 | AI4: =AR4+(AN4/2) -> -0.048192758 | AJ4: 3 | AK4: 0 | AL4: =(AC4-AH4)*AJ4+AK4*AC4*0.5 -> 3900 | AM4: =AF4-AL4 -> 83040 | AN4: =AM4/AF4-1 -> -0.044858523 | AO4: =IFERROR(AM4/H4,"") -> 1.0691845 | AP4: =AM4-X4 -> 4123.5 | AQ4: =AM4/X4-1 -> 0.05225143 | AR4: =IFERROR(AA4+AQ4*0.5,"")+5% -> -0.025763496 | AS4: Service Fee: 250 | BT4: {=vlook} -> #NAME? | BU4: =AP4/X4 -> 0.05225143 | BV4: 0.05 | BW4: =IF(AA4>19%,AA4-3.8%,AA4) -> -0.10188921
A5: 2606 | B5: REF | C5: DST | D5: PTOX24FFCR2.APTO | E5: GC-X24FFCRB.AEVPLM1 | F5: REF3FILTER2.AETC | G5: =IFERROR(VLOOKUP(D5,[3]전용!E:J,6,0),"") | H5: 77666.667 | I5: 6 | J5: Visit | K5: 6 | L5: 1549 | M5: =L5*LEFT(I5,1)*12 -> 111528 | N5: 0.15 | P5: 1149 | Q5: =L5-P5 -> 400 | R5: =P5*LEFT(I5,1)*12 -> 82728 | S5: =AA5-(Y5/2) -> -0.091472545 | V5: 3 | W5: =(P5-T5)*U5+V5*P5*0.5 -> 1723.5 | X5: =R5-W5 -> 81004.5 | Y5: =X5/R5-1 -> -0.020833333 | Z5: =IFERROR(X5/H5,"") -> 1.0429764 | AA5: -0.10188921 | AB5: 0.0213149 | AC5: =P5+AD5 -> 1249 | AD5: 100 | AE5: =IF(AA5>10%,0,IF(AA5>5%,P5*0.04,IF(AA5>0%,P5*0.04, P5*0.1))) -> 114.9 | AF5: =AC5*LEFT(I5,1)*12 -> 89928 | AG5: =AF5/R5-1 -> 0.087032202 | AH5: 149 | AI5: =AR5+(AN5/2) -> -0.035526189 | AJ5: 3 | AK5: 0 | AL5: =(AC5-AH5)*AJ5+AK5*AC5*0.5 -> 3300 | AM5: =AF5-AL5 -> 86628 | AN5: =AM5/AF5-1 -> -0.036696023 | AO5: =IFERROR(AM5/H5,"") -> 1.115382 | AP5: =AM5-X5 -> 5623.5 | AQ5: =AM5/X5-1 -> 0.069422069 | AR5: =IFERROR(AA5+AQ5*0.5,"")+5% -> -0.017178177 | AS5: Service Fee: 250 | BU5: =AP5/X5 -> 0.069422069 | BV5: 0.05 | BW5: =IF(AA5>19%,AA5-3.8%,AA5) -> -0.10188921
A6: 2606 | B6: REF | C6: EOL after inventory depletion | D6: PTOL24FFCB2.APTO | E6: GC-L24FFCBB.AEVPLM1 | F6: REF3FILTER2.AETC | G6: =IFERROR(VLOOKUP(D6,[3]전용!E:J,6,0),"") | H6: 62111.111 | I6: 5 | J6: Visit | K6: 6 | L6: 1549 | M6: =L6*LEFT(I6,1)*12 -> 92940 | N6: 0.15 | P6: 1149 | Q6: =L6-P6 -> 400 | R6: =P6*LEFT(I6,1)*12 -> 68940 | S6: =AA6-(Y6/2) -> -0.25137495 | V6: 3 | W6: =(P6-T6)*U6+V6*P6*0.5 -> 1723.5 | X6: =R6-W6 -> 67216.5 | Y6: =X6/R6-1 -> -0.025 | Z6: =IFERROR(X6/H6,"") -> 1.0821977 | AA6: -0.26387495 | AB6: 0.018432619 | AC6: =P6+AD6 -> 1249 | AD6: 100 | AE6: =IF(AA6>10%,0,IF(AA6>5%,P6*0.04,IF(AA6>0%,P6*0.04, P6*0.1))) -> 114.9 | AF6: =AC6*LEFT(I6,1)*12 -> 74940 | AG6: =AF6/R6-1 -> 0.087032202 | AH6: 149 | AI6: =AR6+(AN6/2) -> -0.11324478 | AJ6: 3 | AK6: 0 | AL6: =(AC6-AH6)*AJ6+AK6*AC6*0.5 -> 3300 | AM6: =AF6-AL6 -> 71640 | AN6: =AM6/AF6-1 -> -0.044035228 | AO6: =IFERROR(AM6/H6,"") -> 1.1534168 | AP6: =AM6-X6 -> 4423.5 | AQ6: =AM6/X6-1 -> 0.065809734 | AR6: =IFERROR(AA6+AQ6*0.8,"")+12% -> -0.091227167 | AS6: Service Fee: 200 | BU6: =AP6/X6 -> 0.065809734 | BV6: 0.03 | BW6: =IF(AA6>19%,AA6-3.8%,AA6) -> -0.26387495
A7: 2606 | B7: REF | C7: EOL after inventory depletion | D7: PTOL24FFCB2.APTO | E7: GC-L24FFCBB.AEVPLM1 | F7: REF3FILTER2.AETC | G7: =IFERROR(VLOOKUP(D7,[3]전용!E:J,6,0),"") | H7: 62111.111 | I7: 6 | J7: Visit | K7: 6 | L7: 1349 | M7: =L7*LEFT(I7,1)*12 -> 97128 | N7: 0.15 | P7: 949 | Q7: =L7-P7 -> 400 | R7: =P7*LEFT(I7,1)*12 -> 68328 | S7: =AA7-(Y7/2) -> -0.25345829 | V7: 3 | W7: =(P7-T7)*U7+V7*P7*0.5 -> 1423.5 | X7: =R7-W7 -> 66904.5 | Y7: =X7/R7-1 -> -0.020833333 | Z7: =IFERROR(X7/H7,"") -> 1.0771744 | AA7: -0.26387495 | AB7: 0.018432619 | AC7: =P7+AD7 -> 1049 | AD7: 100 | AE7: =IF(AA7>10%,0,IF(AA7>5%,P7*0.04,IF(AA7>0%,P7*0.04, P7*0.1))) -> 94.9 | AF7: =AC7*LEFT(I7,1)*12 -> 75528 | AG7: =AF7/R7-1 -> 0.10537408 | AH7: 149 | AI7: =AR7+(AN7/2) -> -0.1109198 | AJ7: 3 | AK7: 0 | AL7: =(AC7-AH7)*AJ7+AK7*AC7*0.5 -> 2700 | AM7: =AF7-AL7 -> 72828 | AN7: =AM7/AF7-1 -> -0.035748332 | AO7: =IFERROR(AM7/H7,"") -> 1.1725438 | AP7: =AM7-X7 -> 5923.5 | AQ7: =AM7/X7-1 -> 0.088536646 | AR7: =IFERROR(AA7+AQ7*0.8,"")+10% -> -0.093045638 | AS7: Service Fee: 200 | BU7: =AP7/X7 -> 0.088536646 | BV7: 0.03 | BW7: =IF(AA7>19%,AA7-3.8%,AA7) -> -0.26387495
A8: 2606 | B8: REF | C8: DST | D8: PTOV25FFGR3.APTO | E8: GV-V25FFGRB.ABMPLMT | G8: =IFERROR(VLOOKUP(D8,[3]전용!E:J,6,0),"") | H8: 53222.222 | I8: 5 | J8: Visit | K8: 24 | L8: 949 | M8: =L8*LEFT(I8,1)*12 -> 56940 | N8: 0.18477592 | P8: 949 | Q8: =L8-P8 -> 0 | R8: =P8*LEFT(I8,1)*12 -> 56940 | S8: =AA8-(Y8/2) -> -0.049170477 | V8: 6 | W8: =(P8-T8)*U8+V8*P8*0.5 -> 2847 | X8: =R8-W8 -> 54093 | Y8: =X8/R8-1 -> -0.05 | Z8: =IFERROR(X8/H8,"") -> 1.0163612 | AA8: -0.074170477 | AB8: 0.075190742 | AC8: =P8+AD8 -> 999 | AD8: 50 | AE8: =IF(AA8>10%,0,IF(AA8>5%,P8*0.04,IF(AA8>0%,P8*0.075, P8*0.1))) -> 94.9 | AF8: =AC8*LEFT(I8,1)*12 -> 59940 | AG8: =AF8/R8-1 -> 0.052687039 | AH8: 0 | AI8: =AR8+(AN8/2) -> -0.018436879 | AJ8: 0 | AK8: 3 | AL8: =(AC8-AH8)*AJ8+AK8*AC8*0.5 -> 1498.5 | AM8: =AF8-AL8 -> 58441.5 | AN8: =AM8/AF8-1 -> -0.025 | AO8: =IFERROR(AM8/H8,"") -> 1.0980658 | AP8: =AM8-X8 -> 4348.5 | AQ8: =AM8/X8-1 -> 0.080389329 | AR8: =IFERROR(AA8+AQ8*0.6,"")+2% -> -0.0059368794 | BU8: =AP8/X8 -> 0.080389329 | BV8: 0.01 | BW8: =IF(AA8>19%,AA8-3.8%,AA8) -> -0.074170477
A9: 2606 | B9: REF | C9: DST | D9: PTOV25FFGR3.APTO | E9: GV-V25FFGRB.ABMPLMT | G9: =IFERROR(VLOOKUP(D9,[3]전용!E:J,6,0),"") | H9: 53222.222 | I9: 6 | J9: Visit | K9: 24 | L9: 899 | M9: =L9*LEFT(I9,1)*12 -> 64728 | N9: 0.18477592 | P9: 899 | Q9: =L9-P9 -> 0 | R9: =P9*LEFT(I9,1)*12 -> 64728 | S9: =AA9-(Y9/2) -> -0.053337144 | V9: 6 | W9: =(P9-T9)*U9+V9*P9*0.5 -> 2697 | X9: =R9-W9 -> 62031 | Y9: =X9/R9-1 -> -0.041666667 | Z9: =IFERROR(X9/H9,"") -> 1.1655094 | AA9: -0.074170477 | AB9: 0.075190742 | AC9: =P9+AD9 -> 949 | AD9: 50 | AE9: =IF(AA9>10%,0,IF(AA9>5%,P9*0.04,IF(AA9>0%,P9*0.075, P9*0.1))) -> 89.9 | AF9: =AC9*LEFT(I9,1)*12 -> 68328 | AG9: =AF9/R9-1 -> 0.055617353 | AH9: 0 | AI9: =AR9+(AN9/2) -> -0.01744781 | AJ9: 0 | AK9: 3 | AL9: =(AC9-AH9)*AJ9+AK9*AC9*0.5 -> 1423.5 | AM9: =AF9-AL9 -> 66904.5 | AN9: =AM9/AF9-1 -> -0.020833333 | AO9: =IFERROR(AM9/H9,"") -> 1.2570783 | AP9: =AM9-X9 -> 4873.5 | AQ9: =AM9/X9-1 -> 0.078565556 | AR9: =IFERROR(AA9+AQ9*0.6,"")+2% -> -0.0070311436 | BU9: =AP9/X9 -> 0.078565556 | BV9: 0.01 | BW9: =IF(AA9>19%,AA9-3.8%,AA9) -> -0.074170477
A10: 2606 | B10: REF | C10: DST | D10: GC-G24FFQKB.AEEPLM1 | G10: =IFERROR(VLOOKUP(D10,[3]전용!E:J,6,0),"") | H10: 61000 | I10: 5 | J10: Visit | K10: 24 | L10: 1299 | M10: =L10*LEFT(I10,1)*12 -> 77940 | N10: 0.17841392 | P10: 1299 | Q10: =L10-P10 -> 0 | R10: =P10*LEFT(I10,1)*12 -> 77940 | S10: =AA10-(Y10/2) -> 0.081027598 | V10: 6 | W10: =(P10-T10)*U10+V10*P10*0.5 -> 3897 | X10: =R10-W10 -> 74043 | Y10: =X10/R10-1 -> -0.05 | Z10: =IFERROR(X10/H10,"") -> 1.2138197 | AA10: 0.056027598 | AB10: 0.036888813 | AC10: =P10+AD10 -> 1349 | AD10: 50 | AE10: =IF(AA10>10%,0,IF(AA10>5%,P10*0.04,IF(AA10>0%,P10*0.075, P10*0.1))) -> 51.96 | AF10: =AC10*LEFT(I10,1)*12 -> 80940 | AG10: =AF10/R10-1 -> 0.038491147 | AH10: 0 | AI10: =AR10+(AN10/2) -> 0.076437528 | AJ10: 0 | AK10: 3 | AL10: =(AC10-AH10)*AJ10+AK10*AC10*0.5 -> 2023.5 | AM10: =AF10-AL10 -> 78916.5 | AN10: =AM10/AF10-1 -> -0.025 | AO10: =IFERROR(AM10/H10,"") -> 1.2937131 | AP10: =AM10-X10 -> 4873.5 | AQ10: =AM10/X10-1 -> 0.065819861 | AR10: =IFERROR(AA10+AQ10*0.5,"") -> 0.088937528 | BU10: =AP10/X10 -> 0.065819861 | BV10: 0.087150387 | BW10: =IF(AA10>19%,AA10-3.8%,AA10) -> 0.056027598
A11: 2606 | B11: REF | C11: DST | D11: GC-G24FFQKB.AEEPLM1 | G11: =IFERROR(VLOOKUP(D11,[3]전용!E:J,6,0),"") | H11: 61000 | I11: 6 | J11: Visit | K11: 24 | L11: 1099 | M11: =L11*LEFT(I11,1)*12 -> 79128 | N11: 0.17926517 | P11: 1099 | Q11: =L11-P11 -> 0 | R11: =P11*LEFT(I11,1)*12 -> 79128 | S11: =AA11-(Y11/2) -> 0.076860931 | V11: 6 | W11: =(P11-T11)*U11+V11*P11*0.5 -> 3297 | X11: =R11-W11 -> 75831 | Y11: =X11/R11-1 -> -0.041666667 | Z11: =IFERROR(X11/H11,"") -> 1.2431311 | AA11: 0.056027598 | AB11: 0.036888813 | AC11: =P11+AD11 -> 1149 | AD11: 50 | AE11: =IF(AA11>10%,0,IF(AA11>5%,P11*0.04,IF(AA11>0%,P11*0.075, P11*0.1))) -> 43.96 | AF11: =AC11*LEFT(I11,1)*12 -> 82728 | AG11: =AF11/R11-1 -> 0.045495905 | AH11: 0 | AI11: =AR11+(AN11/2) -> 0.07972297 | AJ11: 0 | AK11: 3 | AL11: =(AC11-AH11)*AJ11+AK11*AC11*0.5 -> 1723.5 | AM11: =AF11-AL11 -> 81004.5 | AN11: =AM11/AF11-1 -> -0.020833333 | AO11: =IFERROR(AM11/H11,"") -> 1.3279426 | AP11: =AM11-X11 -> 5173.5 | AQ11: =AM11/X11-1 -> 0.068224077 | AR11: =IFERROR(AA11+AQ11*0.5,"") -> 0.090139636 | BU11: =AP11/X11 -> 0.068224077 | BV11: 0.057150387 | BW11: =IF(AA11>19%,AA11-3.8%,AA11) -> 0.056027598
A12: 2606 | B12: REF | C12: DST | D12: PTOX257CMHW.APTO | E12: GC-X257CMHW.AEEPLMT | G12: =IFERROR(VLOOKUP(D12,[3]전용!E:J,6,0),"") | H12: 72666.667 | I12: 5 | J12: Visit | K12: 6 | L12: 1349 | M12: =L12*LEFT(I12,1)*12 -> 80940 | N12: 0.08 | P12: 1349 | Q12: =L12-P12 -> 0 | R12: =P12*LEFT(I12,1)*12 -> 80940 | S12: =AA12-(Y12/2) -> 0.011446918 | V12: 0 | W12: =(P12-T12)*U12+V12*P12*0.5 -> 0 | X12: =R12-W12 -> 80940 | Y12: =X12/R12-1 -> 0 | Z12: =IFERROR(X12/H12,"") -> 1.1138532 | AA12: 0.011446918 | AB12: 3.2227929e-05 | AC12: =P12+AD12 -> 1449 | AD12: 100 | AE12: =IF(AA12>10%,0,IF(AA12>5%,P12*0.04,IF(AA12>0%,P12*0.075, P12*0.1))) -> 101.175 | AF12: =AC12*LEFT(I12,1)*12 -> 86940 | AG12: =AF12/R12-1 -> 0.074128984 | AH12: 0 | AI12: =AR12+(AN12/2) -> 0.04851141 | AJ12: 0 | AK12: 0 | AL12: =(AC12-AH12)*AJ12+AK12*AC12*0.5 -> 0 | AM12: =AF12-AL12 -> 86940 | AN12: =AM12/AF12-1 -> 0 | AO12: =IFERROR(AM12/H12,"") -> 1.196422 | AP12: =AM12-X12 -> 6000 | AQ12: =AM12/X12-1 -> 0.074128984 | AR12: =IFERROR(AA12+AQ12*0.5,"") -> 0.04851141 | AS12: Service Fee: 250 | BU12: =AP12/X12 -> 0.074128984 | BV12: 0.02 | BW12: =IF(AA12>19%,AA12-3.8%,AA12) -> 0.011446918
A13: 2606 | B13: REF | C13: DST | D13: PTOX257CMHW.APTO | E13: GC-X257CMHW.AEEPLMT | G13: =IFERROR(VLOOKUP(D13,[3]전용!E:J,6,0),"") | H13: 72666.667 | I13: 6 | J13: Visit | K13: 6 | L13: 1149 | M13: =L13*LEFT(I13,1)*12 -> 82728 | N13: 0.09 | P13: 1149 | Q13: =L13-P13 -> 0 | R13: =P13*LEFT(I13,1)*12 -> 82728 | S13: =AA13-(Y13/2) -> 0.011446918 | V13: 0 | W13: =(P13-T13)*U13+V13*P13*0.5 -> 0 | X13: =R13-W13 -> 82728 | Y13: =X13/R13-1 -> 0 | Z13: =IFERROR(X13/H13,"") -> 1.1384587 | AA13: 0.011446918 | AB13: 3.2227929e-05 | AC13: =P13+AD13 -> 1249 | AD13: 100 | AE13: =IF(AA13>10%,0,IF(AA13>5%,P13*0.04,IF(AA13>0%,P13*0.075, P13*0.1))) -> 86.175 | AF13: =AC13*LEFT(I13,1)*12 -> 89928 | AG13: =AF13/R13-1 -> 0.087032202 | AH13: 0 | AI13: =AR13+(AN13/2) -> 0.054963019 | AJ13: 0 | AK13: 0 | AL13: =(AC13-AH13)*AJ13+AK13*AC13*0.5 -> 0 | AM13: =AF13-AL13 -> 89928 | AN13: =AM13/AF13-1 -> 0 | AO13: =IFERROR(AM13/H13,"") -> 1.2375413 | AP13: =AM13-X13 -> 7200 | AQ13: =AM13/X13-1 -> 0.087032202 | AR13: =IFERROR(AA13+AQ13*0.5,"") -> 0.054963019 | AS13: Service Fee: 250 | BU13: =AP13/X13 -> 0.087032202 | BV13: 0.02 | BW13: =IF(AA13>19%,AA13-3.8%,AA13) -> 0.011446918
A14: 2606 | B14: REF | C14: DST | D14: GC-X257CMEW.ATEPLMT | G14: =IFERROR(VLOOKUP(D14,[3]전용!E:J,6,0),"") | H14: 66555.556 | I14: 5 | J14: Visit | K14: 24 | L14: 1199 | M14: =L14*LEFT(I14,1)*12 -> 71940 | N14: 0.24824138 | P14: 1199 | Q14: =L14-P14 -> 0 | R14: =P14*LEFT(I14,1)*12 -> 71940 | S14: =AA14-(Y14/2) -> 0.062547215 | V14: 6 | W14: =(P14-T14)*U14+V14*P14*0.5 -> 3597 | X14: =R14-W14 -> 68343 | Y14: =X14/R14-1 -> -0.05 | Z14: =IFERROR(X14/H14,"") -> 1.0268564 | AA14: 0.037547215 | AB14: 0.11607894 | AC14: =P14+AD14 -> 1249 | AD14: 50 | AE14: =IF(AA14>10%,0,IF(AA14>5%,P14*0.04,IF(AA14>0%,P14*0.075, P14*0.1))) -> 89.925 | AF14: =AC14*LEFT(I14,1)*12 -> 74940 | AG14: =AF14/R14-1 -> 0.041701418 | AH14: 0 | AI14: =AR14+(AN14/2) -> 0.059604521 | AJ14: 0 | AK14: 3 | AL14: =(AC14-AH14)*AJ14+AK14*AC14*0.5 -> 1873.5 | AM14: =AF14-AL14 -> 73066.5 | AN14: =AM14/AF14-1 -> -0.025 | AO14: =IFERROR(AM14/H14,"") -> 1.0978272 | AP14: =AM14-X14 -> 4723.5 | AQ14: =AM14/X14-1 -> 0.069114613 | AR14: =IFERROR(AA14+AQ14*0.5,"") -> 0.072104521 | BU14: =AP14/X14 -> 0.069114613 | BV14: 0.063 | BW14: =IF(AA14>19%,AA14-3.8%,AA14) -> 0.037547215
A15: 2606 | B15: REF | C15: DST | D15: GC-X257CMEW.ATEPLMT | G15: =IFERROR(VLOOKUP(D15,[3]전용!E:J,6,0),"") | H15: 66555.556 | I15: 6 | J15: Visit | K15: 24 | L15: 999 | M15: =L15*LEFT(I15,1)*12 -> 71928 | N15: 0.2554274 | P15: 999 | Q15: =L15-P15 -> 0 | R15: =P15*LEFT(I15,1)*12 -> 71928 | S15: =AA15-(Y15/2) -> 0.058380548 | V15: 6 | W15: =(P15-T15)*U15+V15*P15*0.5 -> 2997 | X15: =R15-W15 -> 68931 | Y15: =X15/R15-1 -> -0.041666667 | Z15: =IFERROR(X15/H15,"") -> 1.0356912 | AA15: 0.037547215 | AB15: 0.11607894 | AC15: =P15+AD15 -> 1049 | AD15: 50 | AE15: =IF(AA15>10%,0,IF(AA15>5%,P15*0.04,IF(AA15>0%,P15*0.075, P15*0.1))) -> 74.925 | AF15: =AC15*LEFT(I15,1)*12 -> 75528 | AG15: =AF15/R15-1 -> 0.05005005 | AH15: 0 | AI15: =AR15+(AN15/2) -> 0.063569161 | AJ15: 0 | AK15: 3 | AL15: =(AC15-AH15)*AJ15+AK15*AC15*0.5 -> 1573.5 | AM15: =AF15-AL15 -> 73954.5 | AN15: =AM15/AF15-1 -> -0.020833333 | AO15: =IFERROR(AM15/H15,"") -> 1.1111694 | AP15: =AM15-X15 -> 5023.5 | AQ15: =AM15/X15-1 -> 0.072877225 | AR15: =IFERROR(AA15+AQ15*0.5,"") -> 0.073985827 | BU15: =AP15/X15 -> 0.072877225 | BV15: 0.063 | BW15: =IF(AA15>19%,AA15-3.8%,AA15) -> 0.037547215
A16: 2606 | B16: REF | C16: DST | D16: GC-J257SQZW.AEPPLMT | G16: =IFERROR(VLOOKUP(D16,[3]전용!E:J,6,0),"") | H16: 51000 | I16: 5 | J16: Visit | K16: 24 | L16: 999 | M16: =L16*LEFT(I16,1)*12 -> 59940 | N16: 0.18738601 | P16: 999 | Q16: =L16-P16 -> 0 | R16: =P16*LEFT(I16,1)*12 -> 59940 | S16: =AA16-(Y16/2) -> 0.030548057 | V16: 3 | W16: =(P16-T16)*U16+V16*P16*0.5 -> 1498.5 | X16: =R16-W16 -> 58441.5 | Y16: =X16/R16-1 -> -0.025 | Z16: =IFERROR(X16/H16,"") -> 1.1459118 | AA16: 0.018048057 | AB16: 0.086625988 | AC16: =P16+AD16 -> 1049 | AD16: 50 | AE16: =IF(AA16>10%,0,IF(AA16>5%,P16*0.04,IF(AA16>0%,P16*0.075, P16*0.1))) -> 74.925 | AF16: =AC16*LEFT(I16,1)*12 -> 62940 | AG16: =AF16/R16-1 -> 0.05005005 | AH16: 0 | AI16: =AR16+(AN16/2) -> 0.030573082 | AJ16: 0 | AK16: 3 | AL16: =(AC16-AH16)*AJ16+AK16*AC16*0.5 -> 1573.5 | AM16: =AF16-AL16 -> 61366.5 | AN16: =AM16/AF16-1 -> -0.025 | AO16: =IFERROR(AM16/H16,"") -> 1.2032647 | AP16: =AM16-X16 -> 2925 | AQ16: =AM16/X16-1 -> 0.05005005 | AR16: =IFERROR(AA16+AQ16*0.5,"") -> 0.043073082 | BV16: 0.013747711 | BW16: =IF(AA16>19%,AA16-3.8%,AA16) -> 0.018048057
A17: 2606 | B17: REF | C17: DST | D17: GC-J257SQZW.AEPPLMT | G17: =IFERROR(VLOOKUP(D17,[3]전용!E:J,6,0),"") | H17: 51000 | I17: 6 | J17: Visit | K17: 24 | L17: 849 | M17: =L17*LEFT(I17,1)*12 -> 61128 | N17: 0.20178188 | P17: 849 | Q17: =L17-P17 -> 0 | R17: =P17*LEFT(I17,1)*12 -> 61128 | S17: =AA17-(Y17/2) -> 0.028464724 | V17: 3 | W17: =(P17-T17)*U17+V17*P17*0.5 -> 1273.5 | X17: =R17-W17 -> 59854.5 | Y17: =X17/R17-1 -> -0.020833333 | Z17: =IFERROR(X17/H17,"") -> 1.1736176 | AA17: 0.018048057 | AB17: 0.086625988 | AC17: =P17+AD17 -> 899 | AD17: 50 | AE17: =IF(AA17>10%,0,IF(AA17>5%,P17*0.04,IF(AA17>0%,P17*0.075, P17*0.1))) -> 63.675 | AF17: =AC17*LEFT(I17,1)*12 -> 64728 | AG17: =AF17/R17-1 -> 0.058892815 | AH17: 0 | AI17: =AR17+(AN17/2) -> 0.037077798 | AJ17: 0 | AK17: 3 | AL17: =(AC17-AH17)*AJ17+AK17*AC17*0.5 -> 1348.5 | AM17: =AF17-AL17 -> 63379.5 | AN17: =AM17/AF17-1 -> -0.020833333 | AO17: =IFERROR(AM17/H17,"") -> 1.2427353 | AP17: =AM17-X17 -> 3525 | AQ17: =AM17/X17-1 -> 0.058892815 | AR17: =IFERROR(AA17+AQ17*0.5,"") -> 0.047494464 | BV17: 0.013747711 | BW17: =IF(AA17>19%,AA17-3.8%,AA17) -> 0.018048057
A18: 2606 | B18: REF | C18: DST | D18: GC-V22FFQMB.AEPPLMT | G18: =IFERROR(VLOOKUP(D18,[3]전용!E:J,6,0),"") | H18: 51000 | I18: 5 | J18: Visit | K18: 24 | L18: 899 | M18: =L18*LEFT(I18,1)*12 -> 53940 | N18: 0.14146421 | P18: 899 | Q18: =L18-P18 -> 0 | R18: =P18*LEFT(I18,1)*12 -> 53940 | S18: =AA18-(Y18/2) -> 0.038275817 | V18: 6 | W18: =(P18-T18)*U18+V18*P18*0.5 -> 2697 | X18: =R18-W18 -> 51243 | Y18: =X18/R18-1 -> -0.05 | Z18: =IFERROR(X18/H18,"") -> 1.0047647 | AA18: 0.013275817 | AB18: 0.081203062 | AC18: =P18+AD18 -> 949 | AD18: 50 | AE18: =IF(AA18>10%,0,IF(AA18>5%,P18*0.04,IF(AA18>0%,P18*0.075, P18*0.1))) -> 67.425 | AF18: =AC18*LEFT(I18,1)*12 -> 56940 | AG18: =AF18/R18-1 -> 0.055617353 | AH18: 0 | AI18: =AR18+(AN18/2) -> 0.042474195 | AJ18: 0 | AK18: 3 | AL18: =(AC18-AH18)*AJ18+AK18*AC18*0.5 -> 1423.5 | AM18: =AF18-AL18 -> 55516.5 | AN18: =AM18/AF18-1 -> -0.025 | AO18: =IFERROR(AM18/H18,"") -> 1.0885588 | AP18: =AM18-X18 -> 4273.5 | AQ18: =AM18/X18-1 -> 0.083396757 | AR18: =IFERROR(AA18+AQ18*0.5,"") -> 0.054974195 | BV18: 0.0063999121 | BW18: =IF(AA18>19%,AA18-3.8%,AA18) -> 0.013275817
A19: 2606 | B19: REF | C19: DST | D19: GC-V22FFQMB.AEPPLMT | G19: =IFERROR(VLOOKUP(D19,[3]전용!E:J,6,0),"") | H19: 51000 | I19: 6 | J19: Visit | K19: 24 | L19: 749 | M19: =L19*LEFT(I19,1)*12 -> 53928 | N19: 0.16213639 | P19: 749 | Q19: =L19-P19 -> 0 | R19: =P19*LEFT(I19,1)*12 -> 53928 | S19: =AA19-(Y19/2) -> 0.03410915 | V19: 6 | W19: =(P19-T19)*U19+V19*P19*0.5 -> 2247 | X19: =R19-W19 -> 51681 | Y19: =X19/R19-1 -> -0.041666667 | Z19: =IFERROR(X19/H19,"") -> 1.0133529 | AA19: 0.013275817 | AB19: 0.081203062 | AC19: =P19+AD19 -> 799 | AD19: 50 | AE19: =IF(AA19>10%,0,IF(AA19>5%,P19*0.04,IF(AA19>0%,P19*0.075, P19*0.1))) -> 56.175 | AF19: =AC19*LEFT(I19,1)*12 -> 57528 | AG19: =AF19/R19-1 -> 0.066755674 | AH19: 0 | AI19: =AR19+(AN19/2) -> 0.047832157 | AJ19: 0 | AK19: 3 | AL19: =(AC19-AH19)*AJ19+AK19*AC19*0.5 -> 1198.5 | AM19: =AF19-AL19 -> 56329.5 | AN19: =AM19/AF19-1 -> -0.020833333 | AO19: =IFERROR(AM19/H19,"") -> 1.1045 | AP19: =AM19-X19 -> 4648.5 | AQ19: =AM19/X19-1 -> 0.089946015 | AR19: =IFERROR(AA19+AQ19*0.5,"") -> 0.058248824 | BV19: 0.0063999121 | BW19: =IF(AA19>19%,AA19-3.8%,AA19) -> 0.013275817
A20: 2606 | B20: REF | C20: DST | D20: GN-V389FQEF.AEPPLMT | G20: =IFERROR(VLOOKUP(D20,[3]전용!E:J,6,0),"") | H20: 27766.667 | I20: 5 | J20: Visit | K20: 24 | L20: 649 | M20: =L20*LEFT(I20,1)*12 -> 38940 | N20: 0.22972636 | P20: 649 | Q20: =L20-P20 -> 0 | R20: =P20*LEFT(I20,1)*12 -> 38940 | S20: =AA20-(Y20/2) -> 0.14611356 | V20: 3 | W20: =(P20-T20)*U20+V20*P20*0.5 -> 973.5 | X20: =R20-W20 -> 37966.5 | Y20: =X20/R20-1 -> -0.025 | Z20: =IFERROR(X20/H20,"") -> 1.3673409 | AA20: 0.13361356 | AB20: 0.016592189 | AC20: =P20+AD20 -> 649 | AE20: =IF(AA20>10%,0,IF(AA20>5%,P20*0.04,IF(AA20>0%,P20*0.075, P20*0.1))) -> 0 | AF20: =AC20*LEFT(I20,1)*12 -> 38940 | AG20: =AF20/R20-1 -> 0 | AH20: 0 | AI20: =AR20+(AN20/2) -> 0.12111356 | AJ20: 0 | AK20: 3 | AL20: =(AC20-AH20)*AJ20+AK20*AC20*0.5 -> 973.5 | AM20: =AF20-AL20 -> 37966.5 | AN20: =AM20/AF20-1 -> -0.025 | AO20: =IFERROR(AM20/H20,"") -> 1.3673409 | AP20: =AM20-X20 -> 0 | AQ20: =AM20/X20-1 -> 0 | AR20: =IFERROR(AA20+AQ20*0.5,"") -> 0.13361356 | BV20: 0.13361356 | BW20: =IF(AA20>19%,AA20-3.8%,AA20) -> 0.13361356
A21: 2606 | B21: REF | C21: DST | D21: GN-V389FQEF.AEPPLMT | G21: =IFERROR(VLOOKUP(D21,[3]전용!E:J,6,0),"") | H21: 27766.667 | I21: 6 | J21: Visit | K21: 24 | L21: 549 | M21: =L21*LEFT(I21,1)*12 -> 39528 | N21: 0.21962535 | P21: 549 | Q21: =L21-P21 -> 0 | R21: =P21*LEFT(I21,1)*12 -> 39528 | S21: =AA21-(Y21/2) -> 0.14403022 | V21: 3 | W21: =(P21-T21)*U21+V21*P21*0.5 -> 823.5 | X21: =R21-W21 -> 38704.5 | Y21: =X21/R21-1 -> -0.020833333 | Z21: =IFERROR(X21/H21,"") -> 1.3939196 | AA21: 0.13361356 | AB21: 0.016592189 | AC21: =P21+AD21 -> 549 | AE21: =IF(AA21>10%,0,IF(AA21>5%,P21*0.04,IF(AA21>0%,P21*0.075, P21*0.1))) -> 0 | AF21: =AC21*LEFT(I21,1)*12 -> 39528 | AG21: =AF21/R21-1 -> 0 | AH21: 0 | AI21: =AR21+(AN21/2) -> 0.12319689 | AJ21: 0 | AK21: 3 | AL21: =(AC21-AH21)*AJ21+AK21*AC21*0.5 -> 823.5 | AM21: =AF21-AL21 -> 38704.5 | AN21: =AM21/AF21-1 -> -0.020833333 | AO21: =IFERROR(AM21/H21,"") -> 1.3939196 | AP21: =AM21-X21 -> 0 | AQ21: =AM21/X21-1 -> 0 | AR21: =IFERROR(AA21+AQ21*0.5,"") -> 0.13361356 | BV21: 0.13361356 | BW21: =IF(AA21>19%,AA21-3.8%,AA21) -> 0.13361356
A22: 2606 | B22: REF | C22: EOL after inventory depletion | D22: GC-L257SFZW.APYPLMT | G22: =IFERROR(VLOOKUP(D22,[3]전용!E:J,6,0),"") | H22: 39888.889 | I22: 5 | J22: Visit | K22: 24 | L22: 849 | M22: =L22*LEFT(I22,1)*12 -> 50940 | N22: 0.15 | P22: 849 | Q22: =L22-P22 -> 0 | R22: =P22*LEFT(I22,1)*12 -> 50940 | S22: =AA22-(Y22/2) -> 0.10151141 | V22: 3 | W22: =(P22-T22)*U22+V22*P22*0.5 -> 1273.5 | X22: =R22-W22 -> 49666.5 | Y22: =X22/R22-1 -> -0.025 | Z22: =IFERROR(X22/H22,"") -> 1.2451212 | AA22: 0.089011414 | AB22: 0.098248976 | AC22: =P22+AD22 -> 849 | AE22: =IF(AA22>10%,0,IF(AA22>5%,P22*0.04,IF(AA22>0%,P22*0.075, P22*0.1))) -> 33.96 | AF22: =AC22*LEFT(I22,1)*12 -> 50940 | AG22: =AF22/R22-1 -> 0 | AH22: 0 | AI22: =AR22+(AN22/2) -> 0.076511414 | AJ22: 0 | AK22: 3 | AL22: =(AC22-AH22)*AJ22+AK22*AC22*0.5 -> 1273.5 | AM22: =AF22-AL22 -> 49666.5 | AN22: =AM22/AF22-1 -> -0.025 | AO22: =IFERROR(AM22/H22,"") -> 1.2451212 | AP22: =AM22-X22 -> 0 | AQ22: =AM22/X22-1 -> 0 | AR22: =IFERROR(AA22+AQ22*0.5,"") -> 0.089011414 | BV22: 0.091559924 | BW22: =IF(AA22>19%,AA22-3.8%,AA22) -> 0.089011414
A23: 2606 | B23: REF | C23: EOL after inventory depletion | D23: GC-L257SFZW.APYPLMT | G23: =IFERROR(VLOOKUP(D23,[3]전용!E:J,6,0),"") | H23: 39888.889 | I23: 6 | J23: Visit | K23: 24 | L23: 749 | M23: =L23*LEFT(I23,1)*12 -> 53928 | N23: 0.15 | P23: 749 | Q23: =L23-P23 -> 0 | R23: =P23*LEFT(I23,1)*12 -> 53928 | S23: =AA23-(Y23/2) -> 0.099428081 | V23: 3 | W23: =(P23-T23)*U23+V23*P23*0.5 -> 1123.5 | X23: =R23-W23 -> 52804.5 | Y23: =X23/R23-1 -> -0.020833333 | Z23: =IFERROR(X23/H23,"") -> 1.3237897 | AA23: 0.089011414 | AB23: 0.098248976 | AC23: =P23+AD23 -> 749 | AE23: =IF(AA23>10%,0,IF(AA23>5%,P23*0.04,IF(AA23>0%,P23*0.075, P23*0.1))) -> 29.96 | AF23: =AC23*LEFT(I23,1)*12 -> 53928 | AG23: =AF23/R23-1 -> 0 | AH23: 0 | AI23: =AR23+(AN23/2) -> 0.078594748 | AJ23: 0 | AK23: 3 | AL23: =(AC23-AH23)*AJ23+AK23*AC23*0.5 -> 1123.5 | AM23: =AF23-AL23 -> 52804.5 | AN23: =AM23/AF23-1 -> -0.020833333 | AO23: =IFERROR(AM23/H23,"") -> 1.3237897 | AP23: =AM23-X23 -> 0 | AQ23: =AM23/X23-1 -> 0 | AR23: =IFERROR(AA23+AQ23*0.5,"") -> 0.089011414 | BV23: 0.091559924 | BW23: =IF(AA23>19%,AA23-3.8%,AA23) -> 0.089011414
A24: 2606 | B24: REF | C24: DST | D24: GN-F452PQAK.AEPPLMT | G24: =IFERROR(VLOOKUP(D24,[3]전용!E:J,6,0),"") | H24: 24433.333 | I24: 5 | J24: Visit | K24: 24 | L24: 549 | M24: =L24*LEFT(I24,1)*12 -> 32940 | N24: 0.23679272 | P24: 549 | Q24: =L24-P24 -> 0 | R24: =P24*LEFT(I24,1)*12 -> 32940 | S24: =AA24-(Y24/2) -> 0.01573178 | V24: 3 | W24: =(P24-T24)*U24+V24*P24*0.5 -> 823.5 | X24: =R24-W24 -> 32116.5 | Y24: =X24/R24-1 -> -0.025 | Z24: =IFERROR(X24/H24,"") -> 1.3144543 | AA24: 0.0032317803 | AB24: 0.14451313 | AC24: =P24+AD24 -> 599 | AD24: 50 | AE24: =IF(AA24>10%,0,IF(AA24>5%,P24*0.04,IF(AA24>0%,P24*0.075, P24*0.1))) -> 41.175 | AF24: =AC24*LEFT(I24,1)*12 -> 35940 | AG24: =AF24/R24-1 -> 0.091074681 | AH24: 0 | AI24: =AR24+(AN24/2) -> 0.036269121 | AJ24: 0 | AK24: 3 | AL24: =(AC24-AH24)*AJ24+AK24*AC24*0.5 -> 898.5 | AM24: =AF24-AL24 -> 35041.5 | AN24: =AM24/AF24-1 -> -0.025 | AO24: =IFERROR(AM24/H24,"") -> 1.4341678 | AP24: =AM24-X24 -> 2925 | AQ24: =AM24/X24-1 -> 0.091074681 | AR24: =IFERROR(AA24+AQ24*0.5,"") -> 0.048769121 | BV24: 0.02 | BW24: =IF(AA24>19%,AA24-3.8%,AA24) -> 0.0032317803
A25: 2606 | B25: REF | C25: DST | D25: GN-F452PQAK.AEPPLMT | G25: =IFERROR(VLOOKUP(D25,[3]전용!E:J,6,0),"") | H25: 24433.333 | I25: 6 | J25: Visit | K25: 24 | L25: 449 | M25: =L25*LEFT(I25,1)*12 -> 32328 | N25: 0.18308536 | P25: 449 | Q25: =L25-P25 -> 0 | R25: =P25*LEFT(I25,1)*12 -> 32328 | S25: =AA25-(Y25/2) -> 0.013648447 | V25: 3 | W25: =(P25-T25)*U25+V25*P25*0.5 -> 673.5 | X25: =R25-W25 -> 31654.5 | Y25: =X25/R25-1 -> -0.020833333 | Z25: =IFERROR(X25/H25,"") -> 1.2955457 | AA25: 0.0032317803 | AB25: 0.14451313 | AC25: =P25+AD25 -> 499 | AD25: 50 | AE25: =IF(AA25>10%,0,IF(AA25>5%,P25*0.04,IF(AA25>0%,P25*0.075, P25*0.1))) -> 33.675 | AF25: =AC25*LEFT(I25,1)*12 -> 35928 | AG25: =AF25/R25-1 -> 0.11135857 | AH25: 0 | AI25: =AR25+(AN25/2) -> 0.048494401 | AJ25: 0 | AK25: 3 | AL25: =(AC25-AH25)*AJ25+AK25*AC25*0.5 -> 748.5 | AM25: =AF25-AL25 -> 35179.5 | AN25: =AM25/AF25-1 -> -0.020833333 | AO25: =IFERROR(AM25/H25,"") -> 1.4398158 | AP25: =AM25-X25 -> 3525 | AQ25: =AM25/X25-1 -> 0.11135857 | AR25: =IFERROR(AA25+AQ25*0.5,"") -> 0.058911068 | BV25: 0.02 | BW25: =IF(AA25>19%,AA25-3.8%,AA25) -> 0.0032317803
A26: 2606 | B26: Dishwasher | C26: DST | D26: DFC335HM.ABMPETH | E26: DFC335HM.ABMPETH | G26: =IFERROR(VLOOKUP(D26,[3]전용!E:J,6,0),"") | H26: 38777.778 | I26: 5 | J26: Visit | K26: 12 | L26: 899 | M26: =L26*LEFT(I26,1)*12 -> 53940 | N26: 0.21724138 | P26: 899 | Q26: =L26-P26 -> 0 | R26: =P26*LEFT(I26,1)*12 -> 53940 | S26: =AA26-(Y26/2) -> 0.38496718 | V26: 12 | W26: =(P26-T26)*U26+V26*P26*0.5 -> 5394 | X26: =R26-W26 -> 48546 | Y26: =X26/R26-1 -> -0.1 | Z26: =IFERROR(X26/H26,"") -> 1.2519026 | AA26: 0.33496718 | AB26: 0.072829246 | AC26: =P26+AD26 -> 899 | AE26: =IF(AA26>10%,0,IF(AA26>5%,P26*0.04,IF(AA26>0%,P26*0.075, P26*0.1))) -> 0 | AF26: =AC26*LEFT(I26,1)*12 -> 53940 | AG26: =AF26/R26-1 -> 0 | AH26: 0 | AI26: =AR26+(AN26/2) -> 0.28496718 | AJ26: 0 | AK26: 12 | AL26: =(AC26-AH26)*AJ26+AK26*AC26*0.5 -> 5394 | AM26: =AF26-AL26 -> 48546 | AN26: =AM26/AF26-1 -> -0.1 | AO26: =IFERROR(AM26/H26,"") -> 1.2519026 | AP26: =AM26-X26 -> 0 | AQ26: =AM26/X26-1 -> 0 | AR26: =IFERROR(AA26+AQ26*0.5,"") -> 0.33496718 | BV26: 0.23433964 | BW26: =IF(AA26>19%,AA26-3.8%,AA26) -> 0.29696718
A27: 2606 | B27: Dishwasher | C27: DST | D27: DFC335HM.ABMPETH | E27: DFC335HM.ABMPETH | G27: =IFERROR(VLOOKUP(D27,[3]전용!E:J,6,0),"") | H27: 38777.778 | I27: 5 | J27: Self | K27: 12 | L27: 849 | M27: =L27*LEFT(I27,1)*12 -> 50940 | N27: 0.21724138 | P27: 849 | Q27: =L27-P27 -> 0 | R27: =P27*LEFT(I27,1)*12 -> 50940 | S27: =AA27-(Y27/2) -> 0.38496718 | V27: 12 | W27: =(P27-T27)*U27+V27*P27*0.5 -> 5094 | X27: =R27-W27 -> 45846 | Y27: =X27/R27-1 -> -0.1 | Z27: =IFERROR(X27/H27,"") -> 1.1822751 | AA27: 0.33496718 | AB27: 0.072829246 | AC27: =P27+AD27 -> 849 | AE27: =IF(AA27>10%,0,IF(AA27>5%,P27*0.04,IF(AA27>0%,P27*0.075, P27*0.1))) -> 0 | AF27: =AC27*LEFT(I27,1)*12 -> 50940 | AG27: =AF27/R27-1 -> 0 | AH27: 0 | AI27: =AR27+(AN27/2) -> 0.28496718 | AJ27: 0 | AK27: 12 | AL27: =(AC27-AH27)*AJ27+AK27*AC27*0.5 -> 5094 | AM27: =AF27-AL27 -> 45846 | AN27: =AM27/AF27-1 -> -0.1 | AO27: =IFERROR(AM27/H27,"") -> 1.1822751 | AP27: =AM27-X27 -> 0 | AQ27: =AM27/X27-1 -> 0 | AR27: =IFERROR(AA27+AQ27*0.5,"") -> 0.33496718 | BV27: 0.23433964 | BW27: =IF(AA27>19%,AA27-3.8%,AA27) -> 0.29696718
A28: 2606 | B28: Dishwasher | C28: DST | D28: DFC335HM.ABMPETH | E28: DFC335HM.ABMPETH | G28: =IFERROR(VLOOKUP(D28,[3]전용!E:J,6,0),"") | H28: 38777.778 | I28: 6 | J28: Visit | K28: 12 | L28: 799 | M28: =L28*LEFT(I28,1)*12 -> 57528 | N28: 0.2531499 | P28: 799 | Q28: =L28-P28 -> 0 | R28: =P28*LEFT(I28,1)*12 -> 57528 | S28: =AA28-(Y28/2) -> 0.37663384 | V28: 12 | W28: =(P28-T28)*U28+V28*P28*0.5 -> 4794 | X28: =R28-W28 -> 52734 | Y28: =X28/R28-1 -> -0.083333333 | Z28: =IFERROR(X28/H28,"") -> 1.3599026 | AA28: 0.33496718 | AB28: 0.072829246 | AC28: =P28+AD28 -> 799 | AE28: =IF(AA28>10%,0,IF(AA28>5%,P28*0.04,IF(AA28>0%,P28*0.075, P28*0.1))) -> 0 | AF28: =AC28*LEFT(I28,1)*12 -> 57528 | AG28: =AF28/R28-1 -> 0 | AH28: 0 | AI28: =AR28+(AN28/2) -> 0.29330051 | AJ28: 0 | AK28: 12 | AL28: =(AC28-AH28)*AJ28+AK28*AC28*0.5 -> 4794 | AM28: =AF28-AL28 -> 52734 | AN28: =AM28/AF28-1 -> -0.083333333 | AO28: =IFERROR(AM28/H28,"") -> 1.3599026 | AP28: =AM28-X28 -> 0 | AQ28: =AM28/X28-1 -> 0 | AR28: =IFERROR(AA28+AQ28*0.5,"") -> 0.33496718 | BV28: 0.23433964 | BW28: =IF(AA28>19%,AA28-3.8%,AA28) -> 0.29696718
A29: 2606 | B29: Dishwasher | C29: DST | D29: DFC335HM.ABMPETH | E29: DFC335HM.ABMPETH | G29: =IFERROR(VLOOKUP(D29,[3]전용!E:J,6,0),"") | H29: 38777.778 | I29: 6 | J29: Self | K29: 12 | L29: 749 | M29: =L29*LEFT(I29,1)*12 -> 53928 | N29: 0.26307179 | P29: 749 | Q29: =L29-P29 -> 0 | R29: =P29*LEFT(I29,1)*12 -> 53928 | S29: =AA29-(Y29/2) -> 0.37663384 | V29: 12 | W29: =(P29-T29)*U29+V29*P29*0.5 -> 4494 | X29: =R29-W29 -> 49434 | Y29: =X29/R29-1 -> -0.083333333 | Z29: =IFERROR(X29/H29,"") -> 1.2748023 | AA29: 0.33496718 | AB29: 0.072829246 | AC29: =P29+AD29 -> 749 | AE29: =IF(AA29>10%,0,IF(AA29>5%,P29*0.04,IF(AA29>0%,P29*0.075, P29*0.1))) -> 0 | AF29: =AC29*LEFT(I29,1)*12 -> 53928 | AG29: =AF29/R29-1 -> 0 | AH29: 0 | AI29: =AR29+(AN29/2) -> 0.29330051 | AJ29: 0 | AK29: 12 | AL29: =(AC29-AH29)*AJ29+AK29*AC29*0.5 -> 4494 | AM29: =AF29-AL29 -> 49434 | AN29: =AM29/AF29-1 -> -0.083333333 | AO29: =IFERROR(AM29/H29,"") -> 1.2748023 | AP29: =AM29-X29 -> 0 | AQ29: =AM29/X29-1 -> 0 | AR29: =IFERROR(AA29+AQ29*0.5,"") -> 0.33496718 | BV29: 0.23433964 | BW29: =IF(AA29>19%,AA29-3.8%,AA29) -> 0.29696718
A30: 2606 | B30: Dishwasher | C30: EOL after inventory depletion | D30: DFC533FV.APYPETH | E30: DFC533FV.APYPETH | G30: =IFERROR(VLOOKUP(D30,[3]전용!E:J,6,0),"") | H30: 28777.778 | I30: 5 | J30: Visit | K30: 12 | L30: 749 | M30: =L30*LEFT(I30,1)*12 -> 44940 | N30: 0.15 | P30: 749 | Q30: =L30-P30 -> 0 | R30: =P30*LEFT(I30,1)*12 -> 44940 | S30: =AA30-(Y30/2) -> 0.44748928 | V30: 12 | W30: =(P30-T30)*U30+V30*P30*0.5 -> 4494 | X30: =R30-W30 -> 40446 | Y30: =X30/R30-1 -> -0.1 | Z30: =IFERROR(X30/H30,"") -> 1.4054595 | AA30: 0.39748928 | AB30: 0.0036542546 | AC30: =P30+AD30 -> 749 | AE30: =IF(AA30>10%,0,IF(AA30>5%,P30*0.04,IF(AA30>0%,P30*0.075, P30*0.1))) -> 0 | AF30: =AC30*LEFT(I30,1)*12 -> 44940 | AG30: =AF30/R30-1 -> 0 | AH30: 0 | AI30: =AR30+(AN30/2) -> 0.45304484 | AJ30: 0 | AK30: 0 | AL30: =(AC30-AH30)*AJ30+AK30*AC30*0.5 -> 0 | AM30: =AF30-AL30 -> 44940 | AN30: =AM30/AF30-1 -> 0 | AO30: =IFERROR(AM30/H30,"") -> 1.5616216 | AP30: =AM30-X30 -> 4494 | AQ30: =AM30/X30-1 -> 0.11111111 | AR30: =IFERROR(AA30+AQ30*0.5,"") -> 0.45304484 | BV30: 0.29748928 | BW30: =IF(AA30>19%,AA30-3.8%,AA30) -> 0.35948928
A31: 2606 | B31: Dishwasher | C31: EOL after inventory depletion | D31: DFC533FV.APYPETH | E31: DFC533FV.APYPETH | G31: =IFERROR(VLOOKUP(D31,[3]전용!E:J,6,0),"") | H31: 28777.778 | I31: 5 | J31: Self | K31: 12 | L31: 699 | M31: =L31*LEFT(I31,1)*12 -> 41940 | N31: 0.15 | P31: 699 | Q31: =L31-P31 -> 0 | R31: =P31*LEFT(I31,1)*12 -> 41940 | S31: =AA31-(Y31/2) -> 0.44748928 | V31: 12 | W31: =(P31-T31)*U31+V31*P31*0.5 -> 4194 | X31: =R31-W31 -> 37746 | Y31: =X31/R31-1 -> -0.1 | Z31: =IFERROR(X31/H31,"") -> 1.3116371 | AA31: 0.39748928 | AB31: 0.0036542546 | AC31: =P31+AD31 -> 699 | AE31: =IF(AA31>10%,0,IF(AA31>5%,P31*0.04,IF(AA31>0%,P31*0.075, P31*0.1))) -> 0 | AF31: =AC31*LEFT(I31,1)*12 -> 41940 | AG31: =AF31/R31-1 -> 0 | AH31: 0 | AI31: =AR31+(AN31/2) -> 0.45304484 | AJ31: 0 | AK31: 0 | AL31: =(AC31-AH31)*AJ31+AK31*AC31*0.5 -> 0 | AM31: =AF31-AL31 -> 41940 | AN31: =AM31/AF31-1 -> 0 | AO31: =IFERROR(AM31/H31,"") -> 1.4573745 | AP31: =AM31-X31 -> 4194 | AQ31: =AM31/X31-1 -> 0.11111111 | AR31: =IFERROR(AA31+AQ31*0.5,"") -> 0.45304484 | BV31: 0.29748928 | BW31: =IF(AA31>19%,AA31-3.8%,AA31) -> 0.35948928
A32: 2606 | B32: Dishwasher | C32: EOL after inventory depletion | D32: DFC533FV.APYPETH | E32: DFC533FV.APYPETH | G32: =IFERROR(VLOOKUP(D32,[3]전용!E:J,6,0),"") | H32: 28777.778 | I32: 6 | J32: Visit | K32: 12 | L32: 649 | M32: =L32*LEFT(I32,1)*12 -> 46728 | N32: 0.15 | P32: 649 | Q32: =L32-P32 -> 0 | R32: =P32*LEFT(I32,1)*12 -> 46728 | S32: =AA32-(Y32/2) -> 0.43915595 | V32: 12 | W32: =(P32-T32)*U32+V32*P32*0.5 -> 3894 | X32: =R32-W32 -> 42834 | Y32: =X32/R32-1 -> -0.083333333 | Z32: =IFERROR(X32/H32,"") -> 1.4884402 | AA32: 0.39748928 | AB32: 0.0036542546 | AC32: =P32+AD32 -> 649 | AE32: =IF(AA32>10%,0,IF(AA32>5%,P32*0.04,IF(AA32>0%,P32*0.075, P32*0.1))) -> 0 | AF32: =AC32*LEFT(I32,1)*12 -> 46728 | AG32: =AF32/R32-1 -> 0 | AH32: 0 | AI32: =AR32+(AN32/2) -> 0.44294383 | AJ32: 0 | AK32: 0 | AL32: =(AC32-AH32)*AJ32+AK32*AC32*0.5 -> 0 | AM32: =AF32-AL32 -> 46728 | AN32: =AM32/AF32-1 -> 0 | AO32: =IFERROR(AM32/H32,"") -> 1.6237529 | AP32: =AM32-X32 -> 3894 | AQ32: =AM32/X32-1 -> 0.090909091 | AR32: =IFERROR(AA32+AQ32*0.5,"") -> 0.44294383 | BV32: 0.29748928 | BW32: =IF(AA32>19%,AA32-3.8%,AA32) -> 0.35948928
A33: 2606 | B33: Dishwasher | C33: EOL after inventory depletion | D33: DFC533FV.APYPETH | E33: DFC533FV.APYPETH | G33: =IFERROR(VLOOKUP(D33,[3]전용!E:J,6,0),"") | H33: 28777.778 | I33: 6 | J33: Self | K33: 12 | L33: 599 | M33: =L33*LEFT(I33,1)*12 -> 43128 | N33: 0.15 | P33: 599 | Q33: =L33-P33 -> 0 | R33: =P33*LEFT(I33,1)*12 -> 43128 | S33: =AA33-(Y33/2) -> 0.43915595 | V33: 12 | W33: =(P33-T33)*U33+V33*P33*0.5 -> 3594 | X33: =R33-W33 -> 39534 | Y33: =X33/R33-1 -> -0.083333333 | Z33: =IFERROR(X33/H33,"") -> 1.3737683 | AA33: 0.39748928 | AB33: 0.0036542546 | AC33: =P33+AD33 -> 599 | AE33: =IF(AA33>10%,0,IF(AA33>5%,P33*0.04,IF(AA33>0%,P33*0.075, P33*0.1))) -> 0 | AF33: =AC33*LEFT(I33,1)*12 -> 43128 | AG33: =AF33/R33-1 -> 0 | AH33: 0 | AI33: =AR33+(AN33/2) -> 0.44294383 | AJ33: 0 | AK33: 0 | AL33: =(AC33-AH33)*AJ33+AK33*AC33*0.5 -> 0 | AM33: =AF33-AL33 -> 43128 | AN33: =AM33/AF33-1 -> 0 | AO33: =IFERROR(AM33/H33,"") -> 1.4986564 | AP33: =AM33-X33 -> 3594 | AQ33: =AM33/X33-1 -> 0.090909091 | AR33: =IFERROR(AA33+AQ33*0.5,"") -> 0.44294383 | BV33: 0.29748928 | BW33: =IF(AA33>19%,AA33-3.8%,AA33) -> 0.35948928
A34: 2606 | B34: Cooking | C34: DST | D34: MS4295DIS.BBKPETH | E34: =D34 -> MS4295DIS.BBKPETH | G34: =IFERROR(VLOOKUP(D34,[3]전용!E:J,6,0),"") | H34: 4211.1111 | I34: 6 | J34: Warranty Only | K34: - | L34: 89 | M34: =L34*LEFT(I34,1)*12 -> 6408 | N34: 0.14245193 | P34: 89 | Q34: =L34-P34 -> 0 | R34: =P34*LEFT(I34,1)*12 -> 6408 | S34: =AA34-(Y34/2) -> -0.053671111 | V34: 0 | W34: =(P34-T34)*U34+V34*P34*0.5 -> 0 | X34: =R34-W34 -> 6408 | Y34: =X34/R34-1 -> 0 | Z34: =IFERROR(X34/H34,"") -> 1.5216887 | AA34: -0.053671111 | AB34: 0.073893461 | AC34: =P34+AD34 -> 99 | AD34: 10 | AE34: =IF(AA34>10%,0,IF(AA34>5%,P34*0.04,IF(AA34>0%,P34*0.075, P34*0.1))) -> 8.9 | AF34: =AC34*LEFT(I34,1)*12 -> 7128 | AG34: =AF34/R34-1 -> 0.11235955 | AH34: 0 | AI34: =AR34+(AN34/2) -> 0.030598552 | AJ34: 0 | AK34: 0 | AL34: =(AC34-AH34)*AJ34+AK34*AC34*0.5 -> 0 | AM34: =AF34-AL34 -> 7128 | AN34: =AM34/AF34-1 -> 0 | AO34: =IFERROR(AM34/H34,"") -> 1.6926649 | AP34: =AM34-X34 -> 720 | AQ34: =AM34/X34-1 -> 0.11235955 | AR34: =IFERROR(AA34+AQ34*0.75,"") -> 0.030598552 | BV34: 0.04 | BW34: =IF(AA34>19%,AA34-3.8%,AA34) -> -0.053671111
A35: 2606 | B35: Water Care | C35: DST | D35: WD110MN.ABGPLMT | G35: =IFERROR(VLOOKUP(D35,[3]전용!E:J,6,0),"") | H35: 17000 | I35: 5 | J35: Visit | K35: 6 | L35: 549 | M35: =L35*LEFT(I35,1)*12 -> 32940 | N35: 0.34450002 | P35: 549 | Q35: =L35-P35 -> 0 | R35: =(P35*((I35*12)-V35)) -> 32940 | S35: =AA35-(Y35/2) -> 0.38943751 | T35: 99 | U35: 6 | V35: 0 | W35: =(P35-T35)*U35+V35*P35*0.5 -> 2700 | X35: =R35-W35 -> 30240 | Y35: =X35/R35-1 -> -0.081967213 | Z35: =IFERROR(X35/H35,"") -> 1.7788235 | AA35: 0.34845391 | AB35: 0.02641495 | AC35: =P35+AD35 -> 549 | AE35: =IF(AA35>10%,0,IF(AA35>5%,P35*0.04,IF(AA35>0%,P35*0.075, P35*0.1))) -> 0 | AF35: =AC35*LEFT(I35,1)*12 -> 32940 | AG35: =AF35/R35-1 -> 0 | AH35: 99 | AI35: =AR35+(AN35/2) -> 0.3074703 | AJ35: 6 | AK35: 0 | AL35: =(AC35-AH35)*AJ35+AK35*AC35*0.5 -> 2700 | AM35: =AF35-AL35 -> 30240 | AN35: =AM35/AF35-1 -> -0.081967213 | AO35: =IFERROR(AM35/H35,"") -> 1.7788235 | AP35: =AM35-X35 -> 0 | AQ35: =AM35/X35-1 -> 0 | AR35: =IFERROR(AA35+AQ35*0.5,"") -> 0.34845391 | BV35: 0.34399235 | BW35: =IF(AA35>19%,AA35-3.8%,AA35) -> 0.31045391
A36: 2606 | B36: Water Care | C36: DST | D36: WD110MN.ABGPLMT | G36: =IFERROR(VLOOKUP(D36,[3]전용!E:J,6,0),"") | H36: 17000 | I36: 5 | J36: Self | K36: 6 | L36: 499 | M36: =L36*LEFT(I36,1)*12 -> 29940 | N36: 0.34450002 | P36: 499 | Q36: =L36-P36 -> 0 | R36: =P36*LEFT(I36,1)*12 -> 29940 | S36: =AA36-(Y36/2) -> 0.38853407 | T36: 99 | U36: 6 | V36: 0 | W36: =(P36-T36)*U36+V36*P36*0.5 -> 2400 | X36: =R36-W36 -> 27540 | Y36: =X36/R36-1 -> -0.080160321 | Z36: =IFERROR(X36/H36,"") -> 1.62 | AA36: 0.34845391 | AB36: 0.02641495 | AC36: =P36+AD36 -> 499 | AE36: =IF(AA36>10%,0,IF(AA36>5%,P36*0.04,IF(AA36>0%,P36*0.075, P36*0.1))) -> 0 | AF36: =AC36*LEFT(I36,1)*12 -> 29940 | AG36: =AF36/R36-1 -> 0 | AH36: 99 | AI36: =AR36+(AN36/2) -> 0.30837375 | AJ36: 6 | AK36: 0 | AL36: =(AC36-AH36)*AJ36+AK36*AC36*0.5 -> 2400 | AM36: =AF36-AL36 -> 27540 | AN36: =AM36/AF36-1 -> -0.080160321 | AO36: =IFERROR(AM36/H36,"") -> 1.62 | AP36: =AM36-X36 -> 0 | AQ36: =AM36/X36-1 -> 0 | AR36: =IFERROR(AA36+AQ36*0.5,"") -> 0.34845391 | BV36: 0.34399235 | BW36: =IF(AA36>19%,AA36-3.8%,AA36) -> 0.31045391
A37: 2606 | B37: Water Care | C37: DST | D37: WD110MN.ABGPLMT | G37: =IFERROR(VLOOKUP(D37,[3]전용!E:J,6,0),"") | H37: 17000 | I37: 7 | J37: Visit | K37: 6 | L37: 449 | M37: =L37*LEFT(I37,1)*12 -> 37716 | N37: 0.327406 | P37: 449 | Q37: =L37-P37 -> 0 | R37: =P37*LEFT(I37,1)*12 -> 37716 | S37: =AA37-(Y37/2) -> 0.37629355 | T37: 99 | U37: 6 | V37: 0 | W37: =(P37-T37)*U37+V37*P37*0.5 -> 2100 | X37: =R37-W37 -> 35616 | Y37: =X37/R37-1 -> -0.055679287 | Z37: =IFERROR(X37/H37,"") -> 2.0950588 | AA37: 0.34845391 | AB37: 0.02641495 | AC37: =P37+AD37 -> 449 | AE37: =IF(AA37>10%,0,IF(AA37>5%,P37*0.04,IF(AA37>0%,P37*0.075, P37*0.1))) -> 0 | AF37: =AC37*LEFT(I37,1)*12 -> 37716 | AG37: =AF37/R37-1 -> 0 | AH37: 99 | AI37: =AR37+(AN37/2) -> 0.32061426 | AJ37: 6 | AK37: 0 | AL37: =(AC37-AH37)*AJ37+AK37*AC37*0.5 -> 2100 | AM37: =AF37-AL37 -> 35616 | AN37: =AM37/AF37-1 -> -0.055679287 | AO37: =IFERROR(AM37/H37,"") -> 2.0950588 | AP37: =AM37-X37 -> 0 | AQ37: =AM37/X37-1 -> 0 | AR37: =IFERROR(AA37+AQ37*0.5,"") -> 0.34845391 | BV37: 0.34399235 | BW37: =IF(AA37>19%,AA37-3.8%,AA37) -> 0.31045391
A38: 2606 | B38: Water Care | C38: DST | D38: WD110MN.ABGPLMT | G38: =IFERROR(VLOOKUP(D38,[3]전용!E:J,6,0),"") | H38: 17000 | I38: 7 | J38: Self | K38: 6 | L38: 399 | M38: =L38*LEFT(I38,1)*12 -> 33516 | N38: 0.327406 | P38: 399 | Q38: =L38-P38 -> 0 | R38: =P38*LEFT(I38,1)*12 -> 33516 | S38: =AA38-(Y38/2) -> 0.37530675 | T38: 99 | U38: 6 | V38: 0 | W38: =(P38-T38)*U38+V38*P38*0.5 -> 1800 | X38: =R38-W38 -> 31716 | Y38: =X38/R38-1 -> -0.053705693 | Z38: =IFERROR(X38/H38,"") -> 1.8656471 | AA38: 0.34845391 | AB38: 0.02641495 | AC38: =P38+AD38 -> 399 | AE38: =IF(AA38>10%,0,IF(AA38>5%,P38*0.04,IF(AA38>0%,P38*0.075, P38*0.1))) -> 0 | AF38: =AC38*LEFT(I38,1)*12 -> 33516 | AG38: =AF38/R38-1 -> 0 | AH38: 99 | AI38: =AR38+(AN38/2) -> 0.32160106 | AJ38: 6 | AK38: 0 | AL38: =(AC38-AH38)*AJ38+AK38*AC38*0.5 -> 1800 | AM38: =AF38-AL38 -> 31716 | AN38: =AM38/AF38-1 -> -0.053705693 | AO38: =IFERROR(AM38/H38,"") -> 1.8656471 | AP38: =AM38-X38 -> 0 | AQ38: =AM38/X38-1 -> 0 | AR38: =IFERROR(AA38+AQ38*0.5,"") -> 0.34845391 | BV38: 0.34399235 | BW38: =IF(AA38>19%,AA38-3.8%,AA38) -> 0.31045391
A39: 2606 | B39: Water Care | C39: DST | D39: WD516AN.ACNPLMT | G39: =IFERROR(VLOOKUP(D39,[3]전용!E:J,6,0),"") | H39: 25000 | I39: 5 | J39: Visit | K39: 6 | L39: 799 | M39: =L39*LEFT(I39,1)*12 -> 47940 | N39: 0.27555556 | P39: 799 | Q39: =L39-P39 -> 0 | R39: =(P39*((I39*12)-V39)) -> 47940 | S39: =AA39-(Y39/2) -> 0.22811429 | T39: 149 | U39: 6 | V39: 0 | W39: =(P39-T39)*U39+V39*P39*0.5 -> 3900 | X39: =R39-W39 -> 44040 | Y39: =X39/R39-1 -> -0.08135169 | Z39: =IFERROR(X39/H39,"") -> 1.7616 | AA39: 0.18743845 | AB39: 0.02435034 | AC39: =P39+AD39 -> 799 | AE39: =IF(AA39>10%,0,IF(AA39>5%,P39*0.04,IF(AA39>0%,P39*0.075, P39*0.1))) -> 0 | AF39: =AC39*LEFT(I39,1)*12 -> 47940 | AG39: =AF39/R39-1 -> 0 | AH39: 149 | AI39: =AR39+(AN39/2) -> 0.1467626 | AJ39: 6 | AK39: 0 | AL39: =(AC39-AH39)*AJ39+AK39*AC39*0.5 -> 3900 | AM39: =AF39-AL39 -> 44040 | AN39: =AM39/AF39-1 -> -0.08135169 | AO39: =IFERROR(AM39/H39,"") -> 1.7616 | AP39: =AM39-X39 -> 0 | AQ39: =AM39/X39-1 -> 0 | AR39: =IFERROR(AA39+AQ39*0.5,"") -> 0.18743845 | BV39: 0.18701085 | BW39: =IF(AA39>19%,AA39-3.8%,AA39) -> 0.18743845
A40: 2606 | B40: Water Care | C40: DST | D40: WD516AN.ACNPLMT | G40: =IFERROR(VLOOKUP(D40,[3]전용!E:J,6,0),"") | H40: 25000 | I40: 5 | J40: Self | K40: 6 | L40: 699 | M40: =L40*LEFT(I40,1)*12 -> 41940 | N40: 0.27555556 | P40: 699 | Q40: =L40-P40 -> 0 | R40: =P40*LEFT(I40,1)*12 -> 41940 | S40: =AA40-(Y40/2) -> 0.22678036 | T40: 149 | U40: 6 | V40: 0 | W40: =(P40-T40)*U40+V40*P40*0.5 -> 3300 | X40: =R40-W40 -> 38640 | Y40: =X40/R40-1 -> -0.078683834 | Z40: =IFERROR(X40/H40,"") -> 1.5456 | AA40: 0.18743845 | AB40: 0.02435034 | AC40: =P40+AD40 -> 699 | AE40: =IF(AA40>10%,0,IF(AA40>5%,P40*0.04,IF(AA40>0%,P40*0.075, P40*0.1))) -> 0 | AF40: =AC40*LEFT(I40,1)*12 -> 41940 | AG40: =AF40/R40-1 -> 0 | AH40: 149 | AI40: =AR40+(AN40/2) -> 0.14809653 | AJ40: 6 | AK40: 0 | AL40: =(AC40-AH40)*AJ40+AK40*AC40*0.5 -> 3300 | AM40: =AF40-AL40 -> 38640 | AN40: =AM40/AF40-1 -> -0.078683834 | AO40: =IFERROR(AM40/H40,"") -> 1.5456 | AP40: =AM40-X40 -> 0 | AQ40: =AM40/X40-1 -> 0 | AR40: =IFERROR(AA40+AQ40*0.5,"") -> 0.18743845 | BV40: 0.18701085 | BW40: =IF(AA40>19%,AA40-3.8%,AA40) -> 0.18743845
A41: 2606 | B41: Water Care | C41: DST | D41: WD516AN.ACNPLMT | G41: =IFERROR(VLOOKUP(D41,[3]전용!E:J,6,0),"") | H41: 25000 | I41: 7 | J41: Visit | K41: 6 | L41: 599 | M41: =L41*LEFT(I41,1)*12 -> 50316 | N41: 0.25846154 | P41: 599 | Q41: =L41-P41 -> 0 | R41: =P41*LEFT(I41,1)*12 -> 50316 | S41: =AA41-(Y41/2) -> 0.21426888 | T41: 149 | U41: 6 | V41: 0 | W41: =(P41-T41)*U41+V41*P41*0.5 -> 2700 | X41: =R41-W41 -> 47616 | Y41: =X41/R41-1 -> -0.053660863 | Z41: =IFERROR(X41/H41,"") -> 1.90464 | AA41: 0.18743845 | AB41: 0.02435034 | AC41: =P41+AD41 -> 599 | AE41: =IF(AA41>10%,0,IF(AA41>5%,P41*0.04,IF(AA41>0%,P41*0.075, P41*0.1))) -> 0 | AF41: =AC41*LEFT(I41,1)*12 -> 50316 | AG41: =AF41/R41-1 -> 0 | AH41: 149 | AI41: =AR41+(AN41/2) -> 0.16060801 | AJ41: 6 | AK41: 0 | AL41: =(AC41-AH41)*AJ41+AK41*AC41*0.5 -> 2700 | AM41: =AF41-AL41 -> 47616 | AN41: =AM41/AF41-1 -> -0.053660863 | AO41: =IFERROR(AM41/H41,"") -> 1.90464 | AP41: =AM41-X41 -> 0 | AQ41: =AM41/X41-1 -> 0 | AR41: =IFERROR(AA41+AQ41*0.5,"") -> 0.18743845 | BV41: 0.18701085 | BW41: =IF(AA41>19%,AA41-3.8%,AA41) -> 0.18743845
A42: 2606 | B42: Water Care | C42: DST | D42: WD516AN.ACNPLMT | G42: =IFERROR(VLOOKUP(D42,[3]전용!E:J,6,0),"") | H42: 25000 | I42: 7 | J42: Self | K42: 6 | L42: 499 | M42: =L42*LEFT(I42,1)*12 -> 41916 | N42: 0.25846154 | P42: 499 | Q42: =L42-P42 -> 0 | R42: =P42*LEFT(I42,1)*12 -> 41916 | S42: =AA42-(Y42/2) -> 0.21248855 | T42: 149 | U42: 6 | V42: 0 | W42: =(P42-T42)*U42+V42*P42*0.5 -> 2100 | X42: =R42-W42 -> 39816 | Y42: =X42/R42-1 -> -0.0501002 | Z42: =IFERROR(X42/H42,"") -> 1.59264 | AA42: 0.18743845 | AB42: 0.02435034 | AC42: =P42+AD42 -> 499 | AE42: =IF(AA42>10%,0,IF(AA42>5%,P42*0.04,IF(AA42>0%,P42*0.075, P42*0.1))) -> 0 | AF42: =AC42*LEFT(I42,1)*12 -> 41916 | AG42: =AF42/R42-1 -> 0 | AH42: 149 | AI42: =AR42+(AN42/2) -> 0.16238835 | AJ42: 6 | AK42: 0 | AL42: =(AC42-AH42)*AJ42+AK42*AC42*0.5 -> 2100 | AM42: =AF42-AL42 -> 39816 | AN42: =AM42/AF42-1 -> -0.0501002 | AO42: =IFERROR(AM42/H42,"") -> 1.59264 | AP42: =AM42-X42 -> 0 | AQ42: =AM42/X42-1 -> 0 | AR42: =IFERROR(AA42+AQ42*0.5,"") -> 0.18743845 | BV42: 0.18701085 | BW42: =IF(AA42>19%,AA42-3.8%,AA42) -> 0.18743845
A43: 2606 | B43: Water Care | C43: DST | D43: WD516AN.AEWPLMT | G43: =IFERROR(VLOOKUP(D43,[3]전용!E:J,6,0),"") | H43: 25000 | I43: 5 | J43: Visit | K43: 6 | L43: 799 | M43: =L43*LEFT(I43,1)*12 -> 47940 | N43: 0.27555556 | P43: 799 | Q43: =L43-P43 -> 0 | R43: =(P43*((I43*12)-V43)) -> 47940 | S43: =AA43-(Y43/2) -> 0.23720396 | T43: 149 | U43: 6 | V43: 0 | W43: =(P43-T43)*U43+V43*P43*0.5 -> 3900 | X43: =R43-W43 -> 44040 | Y43: =X43/R43-1 -> -0.08135169 | Z43: =IFERROR(X43/H43,"") -> 1.7616 | AA43: 0.19652811 | AB43: 0.036628147 | AC43: =P43+AD43 -> 799 | AE43: =IF(AA43>10%,0,IF(AA43>5%,P43*0.04,IF(AA43>0%,P43*0.075, P43*0.1))) -> 0 | AF43: =AC43*LEFT(I43,1)*12 -> 47940 | AG43: =AF43/R43-1 -> 0 | AH43: 149 | AI43: =AR43+(AN43/2) -> 0.15585227 | AJ43: 6 | AK43: 0 | AL43: =(AC43-AH43)*AJ43+AK43*AC43*0.5 -> 3900 | AM43: =AF43-AL43 -> 44040 | AN43: =AM43/AF43-1 -> -0.08135169 | AO43: =IFERROR(AM43/H43,"") -> 1.7616 | AP43: =AM43-X43 -> 0 | AQ43: =AM43/X43-1 -> 0 | AR43: =IFERROR(AA43+AQ43*0.5,"") -> 0.19652811 | BV43: 0.19203679 | BW43: =IF(AA43>19%,AA43-3.8%,AA43) -> 0.15852811
A44: 2606 | B44: Water Care | C44: DST | D44: WD516AN.AEWPLMT | G44: =IFERROR(VLOOKUP(D44,[3]전용!E:J,6,0),"") | H44: 25000 | I44: 5 | J44: Self | K44: 6 | L44: 699 | M44: =L44*LEFT(I44,1)*12 -> 41940 | N44: 0.27555556 | P44: 699 | Q44: =L44-P44 -> 0 | R44: =P44*LEFT(I44,1)*12 -> 41940 | S44: =AA44-(Y44/2) -> 0.23587003 | T44: 149 | U44: 6 | V44: 0 | W44: =(P44-T44)*U44+V44*P44*0.5 -> 3300 | X44: =R44-W44 -> 38640 | Y44: =X44/R44-1 -> -0.078683834 | Z44: =IFERROR(X44/H44,"") -> 1.5456 | AA44: 0.19652811 | AB44: 0.036628147 | AC44: =P44+AD44 -> 699 | AE44: =IF(AA44>10%,0,IF(AA44>5%,P44*0.04,IF(AA44>0%,P44*0.075, P44*0.1))) -> 0 | AF44: =AC44*LEFT(I44,1)*12 -> 41940 | AG44: =AF44/R44-1 -> 0 | AH44: 149 | AI44: =AR44+(AN44/2) -> 0.15718619 | AJ44: 6 | AK44: 0 | AL44: =(AC44-AH44)*AJ44+AK44*AC44*0.5 -> 3300 | AM44: =AF44-AL44 -> 38640 | AN44: =AM44/AF44-1 -> -0.078683834 | AO44: =IFERROR(AM44/H44,"") -> 1.5456 | AP44: =AM44-X44 -> 0 | AQ44: =AM44/X44-1 -> 0 | AR44: =IFERROR(AA44+AQ44*0.5,"") -> 0.19652811 | BV44: 0.19203679 | BW44: =IF(AA44>19%,AA44-3.8%,AA44) -> 0.15852811
A45: 2606 | B45: Water Care | C45: DST | D45: WD516AN.AEWPLMT | G45: =IFERROR(VLOOKUP(D45,[3]전용!E:J,6,0),"") | H45: 25000 | I45: 7 | J45: Visit | K45: 6 | L45: 599 | M45: =L45*LEFT(I45,1)*12 -> 50316 | N45: 0.25846154 | P45: 599 | Q45: =L45-P45 -> 0 | R45: =P45*LEFT(I45,1)*12 -> 50316 | S45: =AA45-(Y45/2) -> 0.22335854 | T45: 149 | U45: 6 | V45: 0 | W45: =(P45-T45)*U45+V45*P45*0.5 -> 2700 | X45: =R45-W45 -> 47616 | Y45: =X45/R45-1 -> -0.053660863 | Z45: =IFERROR(X45/H45,"") -> 1.90464 | AA45: 0.19652811 | AB45: 0.036628147 | AC45: =P45+AD45 -> 599 | AE45: =IF(AA45>10%,0,IF(AA45>5%,P45*0.04,IF(AA45>0%,P45*0.075, P45*0.1))) -> 0 | AF45: =AC45*LEFT(I45,1)*12 -> 50316 | AG45: =AF45/R45-1 -> 0 | AH45: 149 | AI45: =AR45+(AN45/2) -> 0.16969768 | AJ45: 6 | AK45: 0 | AL45: =(AC45-AH45)*AJ45+AK45*AC45*0.5 -> 2700 | AM45: =AF45-AL45 -> 47616 | AN45: =AM45/AF45-1 -> -0.053660863 | AO45: =IFERROR(AM45/H45,"") -> 1.90464 | AP45: =AM45-X45 -> 0 | AQ45: =AM45/X45-1 -> 0 | AR45: =IFERROR(AA45+AQ45*0.5,"") -> 0.19652811 | BV45: 0.19203679 | BW45: =IF(AA45>19%,AA45-3.8%,AA45) -> 0.15852811
A46: 2606 | B46: Water Care | C46: DST | D46: WD516AN.AEWPLMT | G46: =IFERROR(VLOOKUP(D46,[3]전용!E:J,6,0),"") | H46: 25000 | I46: 7 | J46: Self | K46: 6 | L46: 499 | M46: =L46*LEFT(I46,1)*12 -> 41916 | N46: 0.25846154 | P46: 499 | Q46: =L46-P46 -> 0 | R46: =P46*LEFT(I46,1)*12 -> 41916 | S46: =AA46-(Y46/2) -> 0.22157821 | T46: 149 | U46: 6 | V46: 0 | W46: =(P46-T46)*U46+V46*P46*0.5 -> 2100 | X46: =R46-W46 -> 39816 | Y46: =X46/R46-1 -> -0.0501002 | Z46: =IFERROR(X46/H46,"") -> 1.59264 | AA46: 0.19652811 | AB46: 0.036628147 | AC46: =P46+AD46 -> 499 | AE46: =IF(AA46>10%,0,IF(AA46>5%,P46*0.04,IF(AA46>0%,P46*0.075, P46*0.1))) -> 0 | AF46: =AC46*LEFT(I46,1)*12 -> 41916 | AG46: =AF46/R46-1 -> 0 | AH46: 149 | AI46: =AR46+(AN46/2) -> 0.17147801 | AJ46: 6 | AK46: 0 | AL46: =(AC46-AH46)*AJ46+AK46*AC46*0.5 -> 2100 | AM46: =AF46-AL46 -> 39816 | AN46: =AM46/AF46-1 -> -0.0501002 | AO46: =IFERROR(AM46/H46,"") -> 1.59264 | AP46: =AM46-X46 -> 0 | AQ46: =AM46/X46-1 -> 0 | AR46: =IFERROR(AA46+AQ46*0.5,"") -> 0.19652811 | BV46: 0.19203679 | BW46: =IF(AA46>19%,AA46-3.8%,AA46) -> 0.15852811
A47: 2606 | B47: Water Care | C47: DST | D47: WD516AN.ASLPLMT | G47: =IFERROR(VLOOKUP(D47,[3]전용!E:J,6,0),"") | H47: 25000 | I47: 5 | J47: Visit | K47: 6 | L47: 799 | M47: =L47*LEFT(I47,1)*12 -> 47940 | N47: 0.27555556 | P47: 799 | Q47: =L47-P47 -> 0 | R47: =(P47*((I47*12)-V47)) -> 47940 | S47: =AA47-(Y47/2) -> 0.23278536 | T47: 149 | U47: 6 | V47: 0 | W47: =(P47-T47)*U47+V47*P47*0.5 -> 3900 | X47: =R47-W47 -> 44040 | Y47: =X47/R47-1 -> -0.08135169 | Z47: =IFERROR(X47/H47,"") -> 1.7616 | AA47: 0.19210951 | AB47: 0.028620681 | AC47: =P47+AD47 -> 799 | AE47: =IF(AA47>10%,0,IF(AA47>5%,P47*0.04,IF(AA47>0%,P47*0.075, P47*0.1))) -> 0 | AF47: =AC47*LEFT(I47,1)*12 -> 47940 | AG47: =AF47/R47-1 -> 0 | AH47: 149 | AI47: =AR47+(AN47/2) -> 0.15143367 | AJ47: 6 | AK47: 0 | AL47: =(AC47-AH47)*AJ47+AK47*AC47*0.5 -> 3900 | AM47: =AF47-AL47 -> 44040 | AN47: =AM47/AF47-1 -> -0.08135169 | AO47: =IFERROR(AM47/H47,"") -> 1.7616 | AP47: =AM47-X47 -> 0 | AQ47: =AM47/X47-1 -> 0 | AR47: =IFERROR(AA47+AQ47*0.5,"") -> 0.19210951 | BV47: 0.19515117 | BW47: =IF(AA47>19%,AA47-3.8%,AA47) -> 0.15410951
A48: 2606 | B48: Water Care | C48: DST | D48: WD516AN.ASLPLMT | G48: =IFERROR(VLOOKUP(D48,[3]전용!E:J,6,0),"") | H48: 25000 | I48: 5 | J48: Self | K48: 6 | L48: 699 | M48: =L48*LEFT(I48,1)*12 -> 41940 | N48: 0.27555556 | P48: 699 | Q48: =L48-P48 -> 0 | R48: =P48*LEFT(I48,1)*12 -> 41940 | S48: =AA48-(Y48/2) -> 0.23145143 | T48: 149 | U48: 6 | V48: 0 | W48: =(P48-T48)*U48+V48*P48*0.5 -> 3300 | X48: =R48-W48 -> 38640 | Y48: =X48/R48-1 -> -0.078683834 | Z48: =IFERROR(X48/H48,"") -> 1.5456 | AA48: 0.19210951 | AB48: 0.028620681 | AC48: =P48+AD48 -> 699 | AE48: =IF(AA48>10%,0,IF(AA48>5%,P48*0.04,IF(AA48>0%,P48*0.075, P48*0.1))) -> 0 | AF48: =AC48*LEFT(I48,1)*12 -> 41940 | AG48: =AF48/R48-1 -> 0 | AH48: 149 | AI48: =AR48+(AN48/2) -> 0.15276759 | AJ48: 6 | AK48: 0 | AL48: =(AC48-AH48)*AJ48+AK48*AC48*0.5 -> 3300 | AM48: =AF48-AL48 -> 38640 | AN48: =AM48/AF48-1 -> -0.078683834 | AO48: =IFERROR(AM48/H48,"") -> 1.5456 | AP48: =AM48-X48 -> 0 | AQ48: =AM48/X48-1 -> 0 | AR48: =IFERROR(AA48+AQ48*0.5,"") -> 0.19210951 | BV48: 0.19515117 | BW48: =IF(AA48>19%,AA48-3.8%,AA48) -> 0.15410951
A49: 2606 | B49: Water Care | C49: DST | D49: WD516AN.ASLPLMT | G49: =IFERROR(VLOOKUP(D49,[3]전용!E:J,6,0),"") | H49: 25000 | I49: 7 | J49: Visit | K49: 6 | L49: 599 | M49: =L49*LEFT(I49,1)*12 -> 50316 | N49: 0.25846154 | P49: 599 | Q49: =L49-P49 -> 0 | R49: =P49*LEFT(I49,1)*12 -> 50316 | S49: =AA49-(Y49/2) -> 0.21893994 | T49: 149 | U49: 6 | V49: 0 | W49: =(P49-T49)*U49+V49*P49*0.5 -> 2700 | X49: =R49-W49 -> 47616 | Y49: =X49/R49-1 -> -0.053660863 | Z49: =IFERROR(X49/H49,"") -> 1.90464 | AA49: 0.19210951 | AB49: 0.028620681 | AC49: =P49+AD49 -> 599 | AE49: =IF(AA49>10%,0,IF(AA49>5%,P49*0.04,IF(AA49>0%,P49*0.075, P49*0.1))) -> 0 | AF49: =AC49*LEFT(I49,1)*12 -> 50316 | AG49: =AF49/R49-1 -> 0 | AH49: 149 | AI49: =AR49+(AN49/2) -> 0.16527908 | AJ49: 6 | AK49: 0 | AL49: =(AC49-AH49)*AJ49+AK49*AC49*0.5 -> 2700 | AM49: =AF49-AL49 -> 47616 | AN49: =AM49/AF49-1 -> -0.053660863 | AO49: =IFERROR(AM49/H49,"") -> 1.90464 | AP49: =AM49-X49 -> 0 | AQ49: =AM49/X49-1 -> 0 | AR49: =IFERROR(AA49+AQ49*0.5,"") -> 0.19210951 | BV49: 0.19515117 | BW49: =IF(AA49>19%,AA49-3.8%,AA49) -> 0.15410951
A50: 2606 | B50: Water Care | C50: DST | D50: WD516AN.ASLPLMT | G50: =IFERROR(VLOOKUP(D50,[3]전용!E:J,6,0),"") | H50: 25000 | I50: 7 | J50: Self | K50: 6 | L50: 499 | M50: =L50*LEFT(I50,1)*12 -> 41916 | N50: 0.25846154 | P50: 499 | Q50: =L50-P50 -> 0 | R50: =P50*LEFT(I50,1)*12 -> 41916 | S50: =AA50-(Y50/2) -> 0.21715961 | T50: 149 | U50: 6 | V50: 0 | W50: =(P50-T50)*U50+V50*P50*0.5 -> 2100 | X50: =R50-W50 -> 39816 | Y50: =X50/R50-1 -> -0.0501002 | Z50: =IFERROR(X50/H50,"") -> 1.59264 | AA50: 0.19210951 | AB50: 0.028620681 | AC50: =P50+AD50 -> 499 | AE50: =IF(AA50>10%,0,IF(AA50>5%,P50*0.04,IF(AA50>0%,P50*0.075, P50*0.1))) -> 0 | AF50: =AC50*LEFT(I50,1)*12 -> 41916 | AG50: =AF50/R50-1 -> 0 | AH50: 149 | AI50: =AR50+(AN50/2) -> 0.16705941 | AJ50: 6 | AK50: 0 | AL50: =(AC50-AH50)*AJ50+AK50*AC50*0.5 -> 2100 | AM50: =AF50-AL50 -> 39816 | AN50: =AM50/AF50-1 -> -0.0501002 | AO50: =IFERROR(AM50/H50,"") -> 1.59264 | AP50: =AM50-X50 -> 0 | AQ50: =AM50/X50-1 -> 0 | AR50: =IFERROR(AA50+AQ50*0.5,"") -> 0.19210951 | BV50: 0.19515117 | BW50: =IF(AA50>19%,AA50-3.8%,AA50) -> 0.15410951
A51: 2606 | B51: Water Care | C51: DST | D51: WD518AN.ABGPLMT | G51: =IFERROR(VLOOKUP(D51,[3]전용!E:J,6,0),"") | H51: 25000 | I51: 5 | J51: Visit | K51: 6 | L51: 799 | M51: =L51*LEFT(I51,1)*12 -> 47940 | N51: 0.23555556 | P51: 799 | Q51: =L51-P51 -> 0 | R51: =(P51*((I51*12)-V51)) -> 47940 | S51: =AA51-(Y51/2) -> 0.22972217 | T51: 149 | U51: 6 | V51: 0 | W51: =(P51-T51)*U51+V51*P51*0.5 -> 3900 | X51: =R51-W51 -> 44040 | Y51: =X51/R51-1 -> -0.08135169 | Z51: =IFERROR(X51/H51,"") -> 1.7616 | AA51: 0.18904632 | AB51: 0.039647706 | AC51: =P51+AD51 -> 799 | AE51: =IF(AA51>10%,0,IF(AA51>5%,P51*0.04,IF(AA51>0%,P51*0.075, P51*0.1))) -> 0 | AF51: =AC51*LEFT(I51,1)*12 -> 47940 | AG51: =AF51/R51-1 -> 0 | AH51: 149 | AI51: =AR51+(AN51/2) -> 0.14837048 | AJ51: 6 | AK51: 0 | AL51: =(AC51-AH51)*AJ51+AK51*AC51*0.5 -> 3900 | AM51: =AF51-AL51 -> 44040 | AN51: =AM51/AF51-1 -> -0.08135169 | AO51: =IFERROR(AM51/H51,"") -> 1.7616 | AP51: =AM51-X51 -> 0 | AQ51: =AM51/X51-1 -> 0 | AR51: =IFERROR(AA51+AQ51*0.5,"") -> 0.18904632 | BV51: 0.18441507 | BW51: =IF(AA51>19%,AA51-3.8%,AA51) -> 0.18904632
A52: 2606 | B52: Water Care | C52: DST | D52: WD518AN.ABGPLMT | G52: =IFERROR(VLOOKUP(D52,[3]전용!E:J,6,0),"") | H52: 25000 | I52: 5 | J52: Self | K52: 6 | L52: 699 | M52: =L52*LEFT(I52,1)*12 -> 41940 | N52: 0.23555556 | P52: 699 | Q52: =L52-P52 -> 0 | R52: =P52*LEFT(I52,1)*12 -> 41940 | S52: =AA52-(Y52/2) -> 0.22838824 | T52: 149 | U52: 6 | V52: 0 | W52: =(P52-T52)*U52+V52*P52*0.5 -> 3300 | X52: =R52-W52 -> 38640 | Y52: =X52/R52-1 -> -0.078683834 | Z52: =IFERROR(X52/H52,"") -> 1.5456 | AA52: 0.18904632 | AB52: 0.039647706 | AC52: =P52+AD52 -> 699 | AE52: =IF(AA52>10%,0,IF(AA52>5%,P52*0.04,IF(AA52>0%,P52*0.075, P52*0.1))) -> 0 | AF52: =AC52*LEFT(I52,1)*12 -> 41940 | AG52: =AF52/R52-1 -> 0 | AH52: 149 | AI52: =AR52+(AN52/2) -> 0.1497044 | AJ52: 6 | AK52: 0 | AL52: =(AC52-AH52)*AJ52+AK52*AC52*0.5 -> 3300 | AM52: =AF52-AL52 -> 38640 | AN52: =AM52/AF52-1 -> -0.078683834 | AO52: =IFERROR(AM52/H52,"") -> 1.5456 | AP52: =AM52-X52 -> 0 | AQ52: =AM52/X52-1 -> 0 | AR52: =IFERROR(AA52+AQ52*0.5,"") -> 0.18904632 | BV52: 0.18441507 | BW52: =IF(AA52>19%,AA52-3.8%,AA52) -> 0.18904632
A53: 2606 | B53: Water Care | C53: DST | D53: WD518AN.ABGPLMT | G53: =IFERROR(VLOOKUP(D53,[3]전용!E:J,6,0),"") | H53: 25000 | I53: 7 | J53: Visit | K53: 6 | L53: 599 | M53: =L53*LEFT(I53,1)*12 -> 50316 | N53: 0.21846154 | P53: 599 | Q53: =L53-P53 -> 0 | R53: =P53*LEFT(I53,1)*12 -> 50316 | S53: =AA53-(Y53/2) -> 0.21587675 | T53: 149 | U53: 6 | V53: 0 | W53: =(P53-T53)*U53+V53*P53*0.5 -> 2700 | X53: =R53-W53 -> 47616 | Y53: =X53/R53-1 -> -0.053660863 | Z53: =IFERROR(X53/H53,"") -> 1.90464 | AA53: 0.18904632 | AB53: 0.039647706 | AC53: =P53+AD53 -> 599 | AE53: =IF(AA53>10%,0,IF(AA53>5%,P53*0.04,IF(AA53>0%,P53*0.075, P53*0.1))) -> 0 | AF53: =AC53*LEFT(I53,1)*12 -> 50316 | AG53: =AF53/R53-1 -> 0 | AH53: 149 | AI53: =AR53+(AN53/2) -> 0.16221589 | AJ53: 6 | AK53: 0 | AL53: =(AC53-AH53)*AJ53+AK53*AC53*0.5 -> 2700 | AM53: =AF53-AL53 -> 47616 | AN53: =AM53/AF53-1 -> -0.053660863 | AO53: =IFERROR(AM53/H53,"") -> 1.90464 | AP53: =AM53-X53 -> 0 | AQ53: =AM53/X53-1 -> 0 | AR53: =IFERROR(AA53+AQ53*0.5,"") -> 0.18904632 | BV53: 0.18441507 | BW53: =IF(AA53>19%,AA53-3.8%,AA53) -> 0.18904632
A54: 2606 | B54: Water Care | C54: DST | D54: WD518AN.ABGPLMT | G54: =IFERROR(VLOOKUP(D54,[3]전용!E:J,6,0),"") | H54: 25000 | I54: 7 | J54: Self | K54: 6 | L54: 499 | M54: =L54*LEFT(I54,1)*12 -> 41916 | N54: 0.21846154 | P54: 499 | Q54: =L54-P54 -> 0 | R54: =P54*LEFT(I54,1)*12 -> 41916 | S54: =AA54-(Y54/2) -> 0.21409642 | T54: 149 | U54: 6 | V54: 0 | W54: =(P54-T54)*U54+V54*P54*0.5 -> 2100 | X54: =R54-W54 -> 39816 | Y54: =X54/R54-1 -> -0.0501002 | Z54: =IFERROR(X54/H54,"") -> 1.59264 | AA54: 0.18904632 | AB54: 0.039647706 | AC54: =P54+AD54 -> 499 | AE54: =IF(AA54>10%,0,IF(AA54>5%,P54*0.04,IF(AA54>0%,P54*0.075, P54*0.1))) -> 0 | AF54: =AC54*LEFT(I54,1)*12 -> 41916 | AG54: =AF54/R54-1 -> 0 | AH54: 149 | AI54: =AR54+(AN54/2) -> 0.16399622 | AJ54: 6 | AK54: 0 | AL54: =(AC54-AH54)*AJ54+AK54*AC54*0.5 -> 2100 | AM54: =AF54-AL54 -> 39816 | AN54: =AM54/AF54-1 -> -0.0501002 | AO54: =IFERROR(AM54/H54,"") -> 1.59264 | AP54: =AM54-X54 -> 0 | AQ54: =AM54/X54-1 -> 0 | AR54: =IFERROR(AA54+AQ54*0.5,"") -> 0.18904632 | BV54: 0.18441507 | BW54: =IF(AA54>19%,AA54-3.8%,AA54) -> 0.18904632
A55: 2606 | B55: Water Care | C55: DST | D55: WD518AN.ACGPLMT | G55: =IFERROR(VLOOKUP(D55,[3]전용!E:J,6,0),"") | H55: 25000 | I55: 5 | J55: Visit | K55: 6 | L55: 799 | M55: =L55*LEFT(I55,1)*12 -> 47940 | N55: 0.23555556 | P55: 799 | Q55: =L55-P55 -> 0 | R55: =P55*LEFT(I55,1)*12 -> 47940 | S55: =AA55-(Y55/2) -> 0.23459265 | T55: 149 | U55: 6 | V55: 0 | W55: =(P55-T55)*U55+V55*P55*0.5 -> 3900 | X55: =R55-W55 -> 44040 | Y55: =X55/R55-1 -> -0.08135169 | Z55: =IFERROR(X55/H55,"") -> 1.7616 | AA55: 0.19391681 | AB55: 0.028163618 | AC55: =P55+AD55 -> 799 | AE55: =IF(AA55>10%,0,IF(AA55>5%,P55*0.04,IF(AA55>0%,P55*0.075, P55*0.1))) -> 0 | AF55: =AC55*LEFT(I55,1)*12 -> 47940 | AG55: =AF55/R55-1 -> 0 | AH55: 149 | AI55: =AR55+(AN55/2) -> 0.15324096 | AJ55: 6 | AK55: 0 | AL55: =(AC55-AH55)*AJ55+AK55*AC55*0.5 -> 3900 | AM55: =AF55-AL55 -> 44040 | AN55: =AM55/AF55-1 -> -0.08135169 | AO55: =IFERROR(AM55/H55,"") -> 1.7616 | AP55: =AM55-X55 -> 0 | AQ55: =AM55/X55-1 -> 0 | AR55: =IFERROR(AA55+AQ55*0.5,"") -> 0.19391681 | BV55: 0.1927519 | BW55: =IF(AA55>19%,AA55-3.8%,AA55) -> 0.15591681
A56: 2606 | B56: Water Care | C56: DST | D56: WD518AN.ACGPLMT | G56: =IFERROR(VLOOKUP(D56,[3]전용!E:J,6,0),"") | H56: 25000 | I56: 5 | J56: Self | K56: 6 | L56: 699 | M56: =L56*LEFT(I56,1)*12 -> 41940 | N56: 0.23555556 | P56: 699 | Q56: =L56-P56 -> 0 | R56: =P56*LEFT(I56,1)*12 -> 41940 | S56: =AA56-(Y56/2) -> 0.23325873 | T56: 149 | U56: 6 | V56: 0 | W56: =(P56-T56)*U56+V56*P56*0.5 -> 3300 | X56: =R56-W56 -> 38640 | Y56: =X56/R56-1 -> -0.078683834 | Z56: =IFERROR(X56/H56,"") -> 1.5456 | AA56: 0.19391681 | AB56: 0.028163618 | AC56: =P56+AD56 -> 699 | AE56: =IF(AA56>10%,0,IF(AA56>5%,P56*0.04,IF(AA56>0%,P56*0.075, P56*0.1))) -> 0 | AF56: =AC56*LEFT(I56,1)*12 -> 41940 | AG56: =AF56/R56-1 -> 0 | AH56: 149 | AI56: =AR56+(AN56/2) -> 0.15457489 | AJ56: 6 | AK56: 0 | AL56: =(AC56-AH56)*AJ56+AK56*AC56*0.5 -> 3300 | AM56: =AF56-AL56 -> 38640 | AN56: =AM56/AF56-1 -> -0.078683834 | AO56: =IFERROR(AM56/H56,"") -> 1.5456 | AP56: =AM56-X56 -> 0 | AQ56: =AM56/X56-1 -> 0 | AR56: =IFERROR(AA56+AQ56*0.5,"") -> 0.19391681 | BV56: 0.1927519 | BW56: =IF(AA56>19%,AA56-3.8%,AA56) -> 0.15591681
A57: 2606 | B57: Water Care | C57: DST | D57: WD518AN.ACGPLMT | G57: =IFERROR(VLOOKUP(D57,[3]전용!E:J,6,0),"") | H57: 25000 | I57: 7 | J57: Visit | K57: 6 | L57: 599 | M57: =L57*LEFT(I57,1)*12 -> 50316 | N57: 0.21846154 | P57: 599 | Q57: =L57-P57 -> 0 | R57: =P57*LEFT(I57,1)*12 -> 50316 | S57: =AA57-(Y57/2) -> 0.22074724 | T57: 149 | U57: 6 | V57: 0 | W57: =(P57-T57)*U57+V57*P57*0.5 -> 2700 | X57: =R57-W57 -> 47616 | Y57: =X57/R57-1 -> -0.053660863 | Z57: =IFERROR(X57/H57,"") -> 1.90464 | AA57: 0.19391681 | AB57: 0.028163618 | AC57: =P57+AD57 -> 599 | AE57: =IF(AA57>10%,0,IF(AA57>5%,P57*0.04,IF(AA57>0%,P57*0.075, P57*0.1))) -> 0 | AF57: =AC57*LEFT(I57,1)*12 -> 50316 | AG57: =AF57/R57-1 -> 0 | AH57: 149 | AI57: =AR57+(AN57/2) -> 0.16708638 | AJ57: 6 | AK57: 0 | AL57: =(AC57-AH57)*AJ57+AK57*AC57*0.5 -> 2700 | AM57: =AF57-AL57 -> 47616 | AN57: =AM57/AF57-1 -> -0.053660863 | AO57: =IFERROR(AM57/H57,"") -> 1.90464 | AP57: =AM57-X57 -> 0 | AQ57: =AM57/X57-1 -> 0 | AR57: =IFERROR(AA57+AQ57*0.5,"") -> 0.19391681 | BV57: 0.1927519 | BW57: =IF(AA57>19%,AA57-3.8%,AA57) -> 0.15591681
A58: 2606 | B58: Water Care | C58: DST | D58: WD518AN.ACGPLMT | G58: =IFERROR(VLOOKUP(D58,[3]전용!E:J,6,0),"") | H58: 25000 | I58: 7 | J58: Self | K58: 6 | L58: 499 | M58: =L58*LEFT(I58,1)*12 -> 41916 | N58: 0.21846154 | P58: 499 | Q58: =L58-P58 -> 0 | R58: =P58*LEFT(I58,1)*12 -> 41916 | S58: =AA58-(Y58/2) -> 0.21896691 | T58: 149 | U58: 6 | V58: 0 | W58: =(P58-T58)*U58+V58*P58*0.5 -> 2100 | X58: =R58-W58 -> 39816 | Y58: =X58/R58-1 -> -0.0501002 | Z58: =IFERROR(X58/H58,"") -> 1.59264 | AA58: 0.19391681 | AB58: 0.028163618 | AC58: =P58+AD58 -> 499 | AE58: =IF(AA58>10%,0,IF(AA58>5%,P58*0.04,IF(AA58>0%,P58*0.075, P58*0.1))) -> 0 | AF58: =AC58*LEFT(I58,1)*12 -> 41916 | AG58: =AF58/R58-1 -> 0 | AH58: 149 | AI58: =AR58+(AN58/2) -> 0.16886671 | AJ58: 6 | AK58: 0 | AL58: =(AC58-AH58)*AJ58+AK58*AC58*0.5 -> 2100 | AM58: =AF58-AL58 -> 39816 | AN58: =AM58/AF58-1 -> -0.0501002 | AO58: =IFERROR(AM58/H58,"") -> 1.59264 | AP58: =AM58-X58 -> 0 | AQ58: =AM58/X58-1 -> 0 | AR58: =IFERROR(AA58+AQ58*0.5,"") -> 0.19391681 | BV58: 0.1927519 | BW58: =IF(AA58>19%,AA58-3.8%,AA58) -> 0.15591681
A59: 2606 | B59: Water Care | C59: DST | D59: WD518AN.AWHPLMT | G59: =IFERROR(VLOOKUP(D59,[3]전용!E:J,6,0),"") | H59: 25000 | I59: 5 | J59: Visit | K59: 6 | L59: 799 | M59: =L59*LEFT(I59,1)*12 -> 47940 | N59: 0.24025604 | P59: 799 | Q59: =L59-P59 -> 0 | R59: =(P59*((I59*12)-V59)) -> 47940 | S59: =AA59-(Y59/2) -> 0.24551051 | T59: 149 | U59: 6 | V59: 0 | W59: =(P59-T59)*U59+V59*P59*0.5 -> 3900 | X59: =R59-W59 -> 44040 | Y59: =X59/R59-1 -> -0.08135169 | Z59: =IFERROR(X59/H59,"") -> 1.7616 | AA59: 0.20483467 | AB59: 0.020504603 | AC59: =P59+AD59 -> 799 | AE59: =IF(AA59>10%,0,IF(AA59>5%,P59*0.04,IF(AA59>0%,P59*0.075, P59*0.1))) -> 0 | AF59: =AC59*LEFT(I59,1)*12 -> 47940 | AG59: =AF59/R59-1 -> 0 | AH59: 149 | AI59: =AR59+(AN59/2) -> 0.16415882 | AJ59: 6 | AK59: 0 | AL59: =(AC59-AH59)*AJ59+AK59*AC59*0.5 -> 3900 | AM59: =AF59-AL59 -> 44040 | AN59: =AM59/AF59-1 -> -0.08135169 | AO59: =IFERROR(AM59/H59,"") -> 1.7616 | AP59: =AM59-X59 -> 0 | AQ59: =AM59/X59-1 -> 0 | AR59: =IFERROR(AA59+AQ59*0.5,"") -> 0.20483467 | BV59: 0.20461796 | BW59: =IF(AA59>19%,AA59-3.8%,AA59) -> 0.16683467
A60: 2606 | B60: Water Care | C60: DST | D60: WD518AN.AWHPLMT | G60: =IFERROR(VLOOKUP(D60,[3]전용!E:J,6,0),"") | H60: 25000 | I60: 5 | J60: Self | K60: 6 | L60: 699 | M60: =L60*LEFT(I60,1)*12 -> 41940 | N60: 0.24025604 | P60: 699 | Q60: =L60-P60 -> 0 | R60: =P60*LEFT(I60,1)*12 -> 41940 | S60: =AA60-(Y60/2) -> 0.24417658 | T60: 149 | U60: 6 | V60: 0 | W60: =(P60-T60)*U60+V60*P60*0.5 -> 3300 | X60: =R60-W60 -> 38640 | Y60: =X60/R60-1 -> -0.078683834 | Z60: =IFERROR(X60/H60,"") -> 1.5456 | AA60: 0.20483467 | AB60: 0.020504603 | AC60: =P60+AD60 -> 699 | AE60: =IF(AA60>10%,0,IF(AA60>5%,P60*0.04,IF(AA60>0%,P60*0.075, P60*0.1))) -> 0 | AF60: =AC60*LEFT(I60,1)*12 -> 41940 | AG60: =AF60/R60-1 -> 0 | AH60: 149 | AI60: =AR60+(AN60/2) -> 0.16549275 | AJ60: 6 | AK60: 0 | AL60: =(AC60-AH60)*AJ60+AK60*AC60*0.5 -> 3300 | AM60: =AF60-AL60 -> 38640 | AN60: =AM60/AF60-1 -> -0.078683834 | AO60: =IFERROR(AM60/H60,"") -> 1.5456 | AP60: =AM60-X60 -> 0 | AQ60: =AM60/X60-1 -> 0 | AR60: =IFERROR(AA60+AQ60*0.5,"") -> 0.20483467 | BV60: 0.20461796 | BW60: =IF(AA60>19%,AA60-3.8%,AA60) -> 0.16683467
A61: 2606 | B61: Water Care | C61: DST | D61: WD518AN.AWHPLMT | G61: =IFERROR(VLOOKUP(D61,[3]전용!E:J,6,0),"") | H61: 25000 | I61: 7 | J61: Visit | K61: 6 | L61: 599 | M61: =L61*LEFT(I61,1)*12 -> 50316 | N61: 0.22316202 | P61: 599 | Q61: =L61-P61 -> 0 | R61: =P61*LEFT(I61,1)*12 -> 50316 | S61: =AA61-(Y61/2) -> 0.2316651 | T61: 149 | U61: 6 | V61: 0 | W61: =(P61-T61)*U61+V61*P61*0.5 -> 2700 | X61: =R61-W61 -> 47616 | Y61: =X61/R61-1 -> -0.053660863 | Z61: =IFERROR(X61/H61,"") -> 1.90464 | AA61: 0.20483467 | AB61: 0.020504603 | AC61: =P61+AD61 -> 599 | AE61: =IF(AA61>10%,0,IF(AA61>5%,P61*0.04,IF(AA61>0%,P61*0.075, P61*0.1))) -> 0 | AF61: =AC61*LEFT(I61,1)*12 -> 50316 | AG61: =AF61/R61-1 -> 0 | AH61: 149 | AI61: =AR61+(AN61/2) -> 0.17800424 | AJ61: 6 | AK61: 0 | AL61: =(AC61-AH61)*AJ61+AK61*AC61*0.5 -> 2700 | AM61: =AF61-AL61 -> 47616 | AN61: =AM61/AF61-1 -> -0.053660863 | AO61: =IFERROR(AM61/H61,"") -> 1.90464 | AP61: =AM61-X61 -> 0 | AQ61: =AM61/X61-1 -> 0 | AR61: =IFERROR(AA61+AQ61*0.5,"") -> 0.20483467 | BV61: 0.20461796 | BW61: =IF(AA61>19%,AA61-3.8%,AA61) -> 0.16683467
A62: 2606 | B62: Water Care | C62: DST | D62: WD518AN.AWHPLMT | G62: =IFERROR(VLOOKUP(D62,[3]전용!E:J,6,0),"") | H62: 25000 | I62: 7 | J62: Self | K62: 6 | L62: 499 | M62: =L62*LEFT(I62,1)*12 -> 41916 | N62: 0.22316202 | P62: 499 | Q62: =L62-P62 -> 0 | R62: =P62*LEFT(I62,1)*12 -> 41916 | S62: =AA62-(Y62/2) -> 0.22988477 | T62: 149 | U62: 6 | V62: 0 | W62: =(P62-T62)*U62+V62*P62*0.5 -> 2100 | X62: =R62-W62 -> 39816 | Y62: =X62/R62-1 -> -0.0501002 | Z62: =IFERROR(X62/H62,"") -> 1.59264 | AA62: 0.20483467 | AB62: 0.020504603 | AC62: =P62+AD62 -> 499 | AE62: =IF(AA62>10%,0,IF(AA62>5%,P62*0.04,IF(AA62>0%,P62*0.075, P62*0.1))) -> 0 | AF62: =AC62*LEFT(I62,1)*12 -> 41916 | AG62: =AF62/R62-1 -> 0 | AH62: 149 | AI62: =AR62+(AN62/2) -> 0.17978457 | AJ62: 6 | AK62: 0 | AL62: =(AC62-AH62)*AJ62+AK62*AC62*0.5 -> 2100 | AM62: =AF62-AL62 -> 39816 | AN62: =AM62/AF62-1 -> -0.0501002 | AO62: =IFERROR(AM62/H62,"") -> 1.59264 | AP62: =AM62-X62 -> 0 | AQ62: =AM62/X62-1 -> 0 | AR62: =IFERROR(AA62+AQ62*0.5,"") -> 0.20483467 | BV62: 0.20461796 | BW62: =IF(AA62>19%,AA62-3.8%,AA62) -> 0.16683467
A63: 2606 | B63: Water Care | C63: DST | D63: WS510SN.AWHPLMT | G63: =IFERROR(VLOOKUP(D63,[3]전용!E:J,6,0),"") | H63: 25000 | I63: 5 | J63: Visit | K63: 3 | L63: 1049 | M63: =L63*LEFT(I63,1)*12 -> 62940 | N63: 0.15555556 | P63: 1049 | Q63: =L63-P63 -> 0 | R63: =(P63*((I63*12)-V63)) -> 62940 | S63: =AA63-(Y63/2) -> 0.021888314 | T63: 149 | U63: 6 | V63: 0 | W63: =(P63-T63)*U63+V63*P63*0.5 -> 5400 | X63: =R63-W63 -> 57540 | Y63: =X63/R63-1 -> -0.085795996 | Z63: =IFERROR(X63/H63,"") -> 2.3016 | AA63: -0.021009684 | AB63: 0.12452945 | AC63: =P63+AD63 -> 1099 | AD63: 50 | AE63: =IF(AA63>10%,0,IF(AA63>5%,P63*0.04,IF(AA63>0%,P63*0.075, P63*0.1))) -> 104.9 | AF63: =AC63*LEFT(I63,1)*12 -> 65940 | AG63: =AF63/R63-1 -> 0.047664442 | AH63: 149 | AI63: =AR63+(AN63/2) -> -0.031384079 | AJ63: 6 | AK63: 0 | AL63: =(AC63-AH63)*AJ63+AK63*AC63*0.5 -> 5700 | AM63: =AF63-AL63 -> 60240 | AN63: =AM63/AF63-1 -> -0.08644222 | AO63: =IFERROR(AM63/H63,"") -> 2.4096 | AP63: =AM63-X63 -> 2700 | AQ63: =AM63/X63-1 -> 0.046923879 | AR63: =IFERROR(AA63+AQ63*0.7,"") -> 0.011837031 | AS63: Service Fee: 280 | BV63: 0.101 | BW63: =IF(AA63>19%,AA63-3.8%,AA63) -> -0.021009684
A64: 2606 | B64: Water Care | C64: DST | D64: WS510SN.AWHPLMT | G64: =IFERROR(VLOOKUP(D64,[3]전용!E:J,6,0),"") | H64: 25000 | I64: 7 | J64: Visit | K64: 3 | L64: 849 | M64: =L64*LEFT(I64,1)*12 -> 71316 | N64: 0.13846154 | P64: 849 | Q64: =L64-P64 -> 0 | R64: =P64*LEFT(I64,1)*12 -> 71316 | S64: =AA64-(Y64/2) -> 0.0084367232 | T64: 149 | U64: 6 | V64: 0 | W64: =(P64-T64)*U64+V64*P64*0.5 -> 4200 | X64: =R64-W64 -> 67116 | Y64: =X64/R64-1 -> -0.058892815 | Z64: =IFERROR(X64/H64,"") -> 2.68464 | AA64: -0.021009684 | AB64: 0.12452945 | AC64: =P64+AD64 -> 899 | AD64: 50 | AE64: =IF(AA64>10%,0,IF(AA64>5%,P64*0.04,IF(AA64>0%,P64*0.075, P64*0.1))) -> 84.9 | AF64: =AC64*LEFT(I64,1)*12 -> 75516 | AG64: =AF64/R64-1 -> 0.058892815 | AH64: 149 | AI64: =AR64+(AN64/2) -> -0.02175052 | AJ64: 6 | AK64: 0 | AL64: =(AC64-AH64)*AJ64+AK64*AC64*0.5 -> 4500 | AM64: =AF64-AL64 -> 71016 | AN64: =AM64/AF64-1 -> -0.059590021 | AO64: =IFERROR(AM64/H64,"") -> 2.84064 | AP64: =AM64-X64 -> 3900 | AQ64: =AM64/X64-1 -> 0.05810835 | AR64: =IFERROR(AA64+AQ64*0.5,"") -> 0.0080444906 | AS64: Service Fee: 280 | BV64: 0.101 | BW64: =IF(AA64>19%,AA64-3.8%,AA64) -> -0.021009684
A65: 2606 | B65: W/M | C65: DST | D65: WT2520NHEG.ABGPETH | G65: =IFERROR(VLOOKUP(D65,[3]전용!E:J,6,0),"") | H65: 99900 | I65: 5 | J65: Visit | K65: 12 | L65: 2399 | M65: =L65*LEFT(I65,1)*12 -> 143940 | N65: 0.29 | P65: 2399 | Q65: =L65-P65 -> 0 | R65: =P65*LEFT(I65,1)*12 -> 143940 | S65: =AA65-(Y65/2) -> 0.24837653 | V65: 6 | W65: =(P65-T65)*U65+V65*P65*0.5 -> 7197 | X65: =R65-W65 -> 136743 | Y65: =X65/R65-1 -> -0.05 | Z65: =IFERROR(X65/H65,"") -> 1.3687988 | AA65: 0.22337653 | AB65: 0.0018560851 | AC65: =P65+AD65 -> 2399 | AE65: =IF(AA65>10%,0,IF(AA65>5%,P65*0.04,IF(AA65>0%,P65*0.075, P65*0.1))) -> 0 | AF65: =AC65*LEFT(I65,1)*12 -> 143940 | AG65: =AF65/R65-1 -> 0 | AH65: 0 | AI65: =AR65+(AN65/2) -> 0.19837653 | AJ65: 0 | AK65: 6 | AL65: =(AC65-AH65)*AJ65+AK65*AC65*0.5 -> 7197 | AM65: =AF65-AL65 -> 136743 | AN65: =AM65/AF65-1 -> -0.05 | AO65: =IFERROR(AM65/H65,"") -> 1.3687988 | AP65: =AM65-X65 -> 0 | AQ65: =AM65/X65-1 -> 0 | AR65: =IFERROR(AA65+AQ65*0.5,"") -> 0.22337653 | BV65: 0.22337653 | BW65: =IF(AA65>19%,AA65-3.8%,AA65) -> 0.18537653
A66: 2606 | B66: W/M | C66: DST | D66: WT2520NHEG.ABGPETH | G66: =IFERROR(VLOOKUP(D66,[3]전용!E:J,6,0),"") | H66: 99900 | I66: 5 | J66: Self | K66: 12 | L66: 2199 | M66: =L66*LEFT(I66,1)*12 -> 131940 | N66: 0.28 | P66: 2199 | Q66: =L66-P66 -> 0 | R66: =P66*LEFT(I66,1)*12 -> 131940 | S66: =AA66-(Y66/2) -> 0.24837653 | V66: 6 | W66: =(P66-T66)*U66+V66*P66*0.5 -> 6597 | X66: =R66-W66 -> 125343 | Y66: =X66/R66-1 -> -0.05 | Z66: =IFERROR(X66/H66,"") -> 1.2546847 | AA66: 0.22337653 | AB66: 0.0018560851 | AC66: =P66+AD66 -> 2199 | AE66: =IF(AA66>10%,0,IF(AA66>5%,P66*0.04,IF(AA66>0%,P66*0.075, P66*0.1))) -> 0 | AF66: =AC66*LEFT(I66,1)*12 -> 131940 | AG66: =AF66/R66-1 -> 0 | AH66: 0 | AI66: =AR66+(AN66/2) -> 0.19837653 | AJ66: 0 | AK66: 6 | AL66: =(AC66-AH66)*AJ66+AK66*AC66*0.5 -> 6597 | AM66: =AF66-AL66 -> 125343 | AN66: =AM66/AF66-1 -> -0.05 | AO66: =IFERROR(AM66/H66,"") -> 1.2546847 | AP66: =AM66-X66 -> 0 | AQ66: =AM66/X66-1 -> 0 | AR66: =IFERROR(AA66+AQ66*0.5,"") -> 0.22337653 | BV66: 0.22337653 | BW66: =IF(AA66>19%,AA66-3.8%,AA66) -> 0.18537653
A67: 2606 | B67: W/M | C67: DST | D67: WT2520NHEG.ABGPETH | G67: =IFERROR(VLOOKUP(D67,[3]전용!E:J,6,0),"") | H67: 99900 | I67: 6 | J67: Visit | K67: 12 | L67: 2199 | M67: =L67*LEFT(I67,1)*12 -> 158328 | N67: 0.33 | P67: 2199 | Q67: =L67-P67 -> 0 | R67: =P67*LEFT(I67,1)*12 -> 158328 | S67: =AA67-(Y67/2) -> 0.24420986 | V67: 6 | W67: =(P67-T67)*U67+V67*P67*0.5 -> 6597 | X67: =R67-W67 -> 151731 | Y67: =X67/R67-1 -> -0.041666667 | Z67: =IFERROR(X67/H67,"") -> 1.5188288 | AA67: 0.22337653 | AB67: 0.0018560851 | AC67: =P67+AD67 -> 2199 | AE67: =IF(AA67>10%,0,IF(AA67>5%,P67*0.04,IF(AA67>0%,P67*0.075, P67*0.1))) -> 0 | AF67: =AC67*LEFT(I67,1)*12 -> 158328 | AG67: =AF67/R67-1 -> 0 | AH67: 0 | AI67: =AR67+(AN67/2) -> 0.2025432 | AJ67: 0 | AK67: 6 | AL67: =(AC67-AH67)*AJ67+AK67*AC67*0.5 -> 6597 | AM67: =AF67-AL67 -> 151731 | AN67: =AM67/AF67-1 -> -0.041666667 | AO67: =IFERROR(AM67/H67,"") -> 1.5188288 | AP67: =AM67-X67 -> 0 | AQ67: =AM67/X67-1 -> 0 | AR67: =IFERROR(AA67+AQ67*0.5,"") -> 0.22337653 | BV67: 0.22337653 | BW67: =IF(AA67>19%,AA67-3.8%,AA67) -> 0.18537653
A68: 2606 | B68: W/M | C68: DST | D68: WT2520NHEG.ABGPETH | G68: =IFERROR(VLOOKUP(D68,[3]전용!E:J,6,0),"") | H68: 99900 | I68: 6 | J68: Self | K68: 12 | L68: 1999 | M68: =L68*LEFT(I68,1)*12 -> 143928 | N68: 0.33 | P68: 1999 | Q68: =L68-P68 -> 0 | R68: =P68*LEFT(I68,1)*12 -> 143928 | S68: =AA68-(Y68/2) -> 0.24420986 | V68: 6 | W68: =(P68-T68)*U68+V68*P68*0.5 -> 5997 | X68: =R68-W68 -> 137931 | Y68: =X68/R68-1 -> -0.041666667 | Z68: =IFERROR(X68/H68,"") -> 1.3806907 | AA68: 0.22337653 | AB68: 0.0018560851 | AC68: =P68+AD68 -> 1999 | AE68: =IF(AA68>10%,0,IF(AA68>5%,P68*0.04,IF(AA68>0%,P68*0.075, P68*0.1))) -> 0 | AF68: =AC68*LEFT(I68,1)*12 -> 143928 | AG68: =AF68/R68-1 -> 0 | AH68: 0 | AI68: =AR68+(AN68/2) -> 0.2025432 | AJ68: 0 | AK68: 6 | AL68: =(AC68-AH68)*AJ68+AK68*AC68*0.5 -> 5997 | AM68: =AF68-AL68 -> 137931 | AN68: =AM68/AF68-1 -> -0.041666667 | AO68: =IFERROR(AM68/H68,"") -> 1.3806907 | AP68: =AM68-X68 -> 0 | AQ68: =AM68/X68-1 -> 0 | AR68: =IFERROR(AA68+AQ68*0.5,"") -> 0.22337653 | BV68: 0.22337653 | BW68: =IF(AA68>19%,AA68-3.8%,AA68) -> 0.18537653
A69: 2606 | B69: W/M | C69: DST | D69: WT2520NHEN.ABNPETH | G69: =IFERROR(VLOOKUP(D69,[3]전용!E:J,6,0),"") | H69: 99900 | I69: 5 | J69: Visit | K69: 12 | L69: 2399 | M69: =L69*LEFT(I69,1)*12 -> 143940 | N69: 0.29 | P69: 2399 | Q69: =L69-P69 -> 0 | R69: =P69*LEFT(I69,1)*12 -> 143940 | S69: =AA69-(Y69/2) -> 0.26625741 | V69: 6 | W69: =(P69-T69)*U69+V69*P69*0.5 -> 7197 | X69: =R69-W69 -> 136743 | Y69: =X69/R69-1 -> -0.05 | Z69: =IFERROR(X69/H69,"") -> 1.3687988 | AA69: 0.24125741 | AB69: 0.0014753771 | AC69: =P69+AD69 -> 2399 | AE69: =IF(AA69>10%,0,IF(AA69>5%,P69*0.04,IF(AA69>0%,P69*0.075, P69*0.1))) -> 0 | AF69: =AC69*LEFT(I69,1)*12 -> 143940 | AG69: =AF69/R69-1 -> 0 | AH69: 0 | AI69: =AR69+(AN69/2) -> 0.21625741 | AJ69: 0 | AK69: 6 | AL69: =(AC69-AH69)*AJ69+AK69*AC69*0.5 -> 7197 | AM69: =AF69-AL69 -> 136743 | AN69: =AM69/AF69-1 -> -0.05 | AO69: =IFERROR(AM69/H69,"") -> 1.3687988 | AP69: =AM69-X69 -> 0 | AQ69: =AM69/X69-1 -> 0 | AR69: =IFERROR(AA69+AQ69*0.5,"") -> 0.24125741 | BV69: 0.24125741 | BW69: =IF(AA69>19%,AA69-3.8%,AA69) -> 0.20325741
A70: 2606 | B70: W/M | C70: DST | D70: WT2520NHEN.ABNPETH | G70: =IFERROR(VLOOKUP(D70,[3]전용!E:J,6,0),"") | H70: 99900 | I70: 5 | J70: Self | K70: 12 | L70: 2199 | M70: =L70*LEFT(I70,1)*12 -> 131940 | N70: 0.28 | P70: 2199 | Q70: =L70-P70 -> 0 | R70: =P70*LEFT(I70,1)*12 -> 131940 | S70: =AA70-(Y70/2) -> 0.26625741 | V70: 6 | W70: =(P70-T70)*U70+V70*P70*0.5 -> 6597 | X70: =R70-W70 -> 125343 | Y70: =X70/R70-1 -> -0.05 | Z70: =IFERROR(X70/H70,"") -> 1.2546847 | AA70: 0.24125741 | AB70: 0.0014753771 | AC70: =P70+AD70 -> 2199 | AE70: =IF(AA70>10%,0,IF(AA70>5%,P70*0.04,IF(AA70>0%,P70*0.075, P70*0.1))) -> 0 | AF70: =AC70*LEFT(I70,1)*12 -> 131940 | AG70: =AF70/R70-1 -> 0 | AH70: 0 | AI70: =AR70+(AN70/2) -> 0.21625741 | AJ70: 0 | AK70: 6 | AL70: =(AC70-AH70)*AJ70+AK70*AC70*0.5 -> 6597 | AM70: =AF70-AL70 -> 125343 | AN70: =AM70/AF70-1 -> -0.05 | AO70: =IFERROR(AM70/H70,"") -> 1.2546847 | AP70: =AM70-X70 -> 0 | AQ70: =AM70/X70-1 -> 0 | AR70: =IFERROR(AA70+AQ70*0.5,"") -> 0.24125741 | BV70: 0.24125741 | BW70: =IF(AA70>19%,AA70-3.8%,AA70) -> 0.20325741
A71: 2606 | B71: W/M | C71: DST | D71: WT2520NHEN.ABNPETH | G71: =IFERROR(VLOOKUP(D71,[3]전용!E:J,6,0),"") | H71: 99900 | I71: 6 | J71: Visit | K71: 12 | L71: 2199 | M71: =L71*LEFT(I71,1)*12 -> 158328 | N71: 0.33 | P71: 2199 | Q71: =L71-P71 -> 0 | R71: =P71*LEFT(I71,1)*12 -> 158328 | S71: =AA71-(Y71/2) -> 0.26209074 | V71: 6 | W71: =(P71-T71)*U71+V71*P71*0.5 -> 6597 | X71: =R71-W71 -> 151731 | Y71: =X71/R71-1 -> -0.041666667 | Z71: =IFERROR(X71/H71,"") -> 1.5188288 | AA71: 0.24125741 | AB71: 0.0014753771 | AC71: =P71+AD71 -> 2199 | AE71: =IF(AA71>10%,0,IF(AA71>5%,P71*0.04,IF(AA71>0%,P71*0.075, P71*0.1))) -> 0 | AF71: =AC71*LEFT(I71,1)*12 -> 158328 | AG71: =AF71/R71-1 -> 0 | AH71: 0 | AI71: =AR71+(AN71/2) -> 0.22042407 | AJ71: 0 | AK71: 6 | AL71: =(AC71-AH71)*AJ71+AK71*AC71*0.5 -> 6597 | AM71: =AF71-AL71 -> 151731 | AN71: =AM71/AF71-1 -> -0.041666667 | AO71: =IFERROR(AM71/H71,"") -> 1.5188288 | AP71: =AM71-X71 -> 0 | AQ71: =AM71/X71-1 -> 0 | AR71: =IFERROR(AA71+AQ71*0.5,"") -> 0.24125741 | BV71: 0.24125741 | BW71: =IF(AA71>19%,AA71-3.8%,AA71) -> 0.20325741
A72: 2606 | B72: W/M | C72: DST | D72: WT2520NHEN.ABNPETH | G72: =IFERROR(VLOOKUP(D72,[3]전용!E:J,6,0),"") | H72: 99900 | I72: 6 | J72: Self | K72: 12 | L72: 1999 | M72: =L72*LEFT(I72,1)*12 -> 143928 | N72: 0.33 | P72: 1999 | Q72: =L72-P72 -> 0 | R72: =P72*LEFT(I72,1)*12 -> 143928 | S72: =AA72-(Y72/2) -> 0.26209074 | V72: 6 | W72: =(P72-T72)*U72+V72*P72*0.5 -> 5997 | X72: =R72-W72 -> 137931 | Y72: =X72/R72-1 -> -0.041666667 | Z72: =IFERROR(X72/H72,"") -> 1.3806907 | AA72: 0.24125741 | AB72: 0.0014753771 | AC72: =P72+AD72 -> 1999 | AE72: =IF(AA72>10%,0,IF(AA72>5%,P72*0.04,IF(AA72>0%,P72*0.075, P72*0.1))) -> 0 | AF72: =AC72*LEFT(I72,1)*12 -> 143928 | AG72: =AF72/R72-1 -> 0 | AH72: 0 | AI72: =AR72+(AN72/2) -> 0.22042407 | AJ72: 0 | AK72: 6 | AL72: =(AC72-AH72)*AJ72+AK72*AC72*0.5 -> 5997 | AM72: =AF72-AL72 -> 137931 | AN72: =AM72/AF72-1 -> -0.041666667 | AO72: =IFERROR(AM72/H72,"") -> 1.3806907 | AP72: =AM72-X72 -> 0 | AQ72: =AM72/X72-1 -> 0 | AR72: =IFERROR(AA72+AQ72*0.5,"") -> 0.24125741 | BV72: 0.24125741 | BW72: =IF(AA72>19%,AA72-3.8%,AA72) -> 0.20325741
A73: 2606 | B73: W/M | C73: DST | D73: WT2116SHEG.ABGPETH | G73: =IFERROR(VLOOKUP(D73,[3]전용!E:J,6,0),"") | H73: 84900 | I73: 5 | J73: Self | K73: 12 | L73: 1899 | M73: =L73*LEFT(I73,1)*12 -> 113940 | N73: 0.2964165 | P73: 1899 | Q73: =L73-P73 -> 0 | R73: =P73*LEFT(I73,1)*12 -> 113940 | S73: =AA73-(Y73/2) -> 0.16629925 | V73: 6 | W73: =(P73-T73)*U73+V73*P73*0.5 -> 5697 | X73: =R73-W73 -> 108243 | Y73: =X73/R73-1 -> -0.05 | Z73: =IFERROR(X73/H73,"") -> 1.274947 | AA73: 0.14129925 | AB73: 0.081716208 | AC73: =P73+AD73 -> 1899 | AE73: =IF(AA73>10%,0,IF(AA73>5%,P73*0.04,IF(AA73>0%,P73*0.075, P73*0.1))) -> 0 | AF73: =AC73*LEFT(I73,1)*12 -> 113940 | AG73: =AF73/R73-1 -> 0 | AH73: 0 | AI73: =AR73+(AN73/2) -> 0.11629925 | AJ73: 0 | AK73: 6 | AL73: =(AC73-AH73)*AJ73+AK73*AC73*0.5 -> 5697 | AM73: =AF73-AL73 -> 108243 | AN73: =AM73/AF73-1 -> -0.05 | AO73: =IFERROR(AM73/H73,"") -> 1.274947 | AP73: =AM73-X73 -> 0 | AQ73: =AM73/X73-1 -> 0 | AR73: =IFERROR(AA73+AQ73*0.5,"") -> 0.14129925 | BV73: 0.1411209 | BW73: =IF(AA73>19%,AA73-3.8%,AA73) -> 0.14129925
A74: 2606 | B74: W/M | C74: DST | D74: WT2116SHEG.ABGPETH | G74: =IFERROR(VLOOKUP(D74,[3]전용!E:J,6,0),"") | H74: 84900 | I74: 5 | J74: Visit | K74: 12 | L74: 1749 | M74: =L74*LEFT(I74,1)*12 -> 104940 | N74: 0.29734495 | P74: 1749 | Q74: =L74-P74 -> 0 | R74: =P74*LEFT(I74,1)*12 -> 104940 | S74: =AA74-(Y74/2) -> 0.16629925 | V74: 6 | W74: =(P74-T74)*U74+V74*P74*0.5 -> 5247 | X74: =R74-W74 -> 99693 | Y74: =X74/R74-1 -> -0.05 | Z74: =IFERROR(X74/H74,"") -> 1.1742403 | AA74: 0.14129925 | AB74: 0.081716208 | AC74: =P74+AD74 -> 1749 | AE74: =IF(AA74>10%,0,IF(AA74>5%,P74*0.04,IF(AA74>0%,P74*0.075, P74*0.1))) -> 0 | AF74: =AC74*LEFT(I74,1)*12 -> 104940 | AG74: =AF74/R74-1 -> 0 | AH74: 0 | AI74: =AR74+(AN74/2) -> 0.11629925 | AJ74: 0 | AK74: 6 | AL74: =(AC74-AH74)*AJ74+AK74*AC74*0.5 -> 5247 | AM74: =AF74-AL74 -> 99693 | AN74: =AM74/AF74-1 -> -0.05 | AO74: =IFERROR(AM74/H74,"") -> 1.1742403 | AP74: =AM74-X74 -> 0 | AQ74: =AM74/X74-1 -> 0 | AR74: =IFERROR(AA74+AQ74*0.5,"") -> 0.14129925 | BV74: 0.1411209 | BW74: =IF(AA74>19%,AA74-3.8%,AA74) -> 0.14129925
A75: 2606 | B75: W/M | C75: DST | D75: WT2116SHEG.ABGPETH | G75: =IFERROR(VLOOKUP(D75,[3]전용!E:J,6,0),"") | H75: 84900 | I75: 6 | J75: Self | K75: 12 | L75: 1899 | M75: =L75*LEFT(I75,1)*12 -> 136728 | N75: 0.2964165 | P75: 1899 | Q75: =L75-P75 -> 0 | R75: =P75*LEFT(I75,1)*12 -> 136728 | S75: =AA75-(Y75/2) -> 0.16213258 | V75: 6 | W75: =(P75-T75)*U75+V75*P75*0.5 -> 5697 | X75: =R75-W75 -> 131031 | Y75: =X75/R75-1 -> -0.041666667 | Z75: =IFERROR(X75/H75,"") -> 1.5433569 | AA75: 0.14129925 | AB75: 0.081716208 | AC75: =P75+AD75 -> 1899 | AE75: =IF(AA75>10%,0,IF(AA75>5%,P75*0.04,IF(AA75>0%,P75*0.075, P75*0.1))) -> 0 | AF75: =AC75*LEFT(I75,1)*12 -> 136728 | AG75: =AF75/R75-1 -> 0 | AH75: 0 | AI75: =AR75+(AN75/2) -> 0.12046591 | AJ75: 0 | AK75: 6 | AL75: =(AC75-AH75)*AJ75+AK75*AC75*0.5 -> 5697 | AM75: =AF75-AL75 -> 131031 | AN75: =AM75/AF75-1 -> -0.041666667 | AO75: =IFERROR(AM75/H75,"") -> 1.5433569 | AP75: =AM75-X75 -> 0 | AQ75: =AM75/X75-1 -> 0 | AR75: =IFERROR(AA75+AQ75*0.5,"") -> 0.14129925 | BV75: 0.1411209 | BW75: =IF(AA75>19%,AA75-3.8%,AA75) -> 0.14129925
A76: 2606 | B76: W/M | C76: DST | D76: WT2116SHEG.ABGPETH | G76: =IFERROR(VLOOKUP(D76,[3]전용!E:J,6,0),"") | H76: 84900 | I76: 6 | J76: Self | K76: 12 | L76: 1649 | M76: =L76*LEFT(I76,1)*12 -> 118728 | N76: 0.30056339 | P76: 1649 | Q76: =L76-P76 -> 0 | R76: =P76*LEFT(I76,1)*12 -> 118728 | S76: =AA76-(Y76/2) -> 0.16213258 | V76: 6 | W76: =(P76-T76)*U76+V76*P76*0.5 -> 4947 | X76: =R76-W76 -> 113781 | Y76: =X76/R76-1 -> -0.041666667 | Z76: =IFERROR(X76/H76,"") -> 1.3401767 | AA76: 0.14129925 | AB76: 0.081716208 | AC76: =P76+AD76 -> 1649 | AE76: =IF(AA76>10%,0,IF(AA76>5%,P76*0.04,IF(AA76>0%,P76*0.075, P76*0.1))) -> 0 | AF76: =AC76*LEFT(I76,1)*12 -> 118728 | AG76: =AF76/R76-1 -> 0 | AH76: 0 | AI76: =AR76+(AN76/2) -> 0.12046591 | AJ76: 0 | AK76: 6 | AL76: =(AC76-AH76)*AJ76+AK76*AC76*0.5 -> 4947 | AM76: =AF76-AL76 -> 113781 | AN76: =AM76/AF76-1 -> -0.041666667 | AO76: =IFERROR(AM76/H76,"") -> 1.3401767 | AP76: =AM76-X76 -> 0 | AQ76: =AM76/X76-1 -> 0 | AR76: =IFERROR(AA76+AQ76*0.5,"") -> 0.14129925 | BV76: 0.1411209 | BW76: =IF(AA76>19%,AA76-3.8%,AA76) -> 0.14129925
A77: 2606 | B77: W/M | C77: DST | D77: WT1410NHEG.ABGPQTH | E77: WT1410NHEG.ABGPPTH | G77: =IFERROR(VLOOKUP(D77,[3]전용!E:J,6,0),"") | H77: 82410 | I77: 5 | J77: Visit | K77: 12 | L77: 1599 | M77: =L77*LEFT(I77,1)*12 -> 95940 | N77: 0.3202734 | P77: 1599 | Q77: =L77-P77 -> 0 | R77: =P77*LEFT(I77,1)*12 -> 95940 | S77: =AA77-(Y77/2) -> 0.27241923 | V77: 6 | W77: =(P77-T77)*U77+V77*P77*0.5 -> 4797 | X77: =R77-W77 -> 91143 | Y77: =X77/R77-1 -> -0.05 | Z77: =IFERROR(X77/H77,"") -> 1.1059701 | AA77: 0.24741923 | AB77: -0.00011098753 | AC77: =P77+AD77 -> 1599 | AE77: =IF(AA77>10%,0,IF(AA77>5%,P77*0.04,IF(AA77>0%,P77*0.075, P77*0.1))) -> 0 | AF77: =AC77*LEFT(I77,1)*12 -> 95940 | AG77: =AF77/R77-1 -> 0 | AH77: 0 | AI77: =AR77+(AN77/2) -> 0.22241923 | AJ77: 0 | AK77: 6 | AL77: =(AC77-AH77)*AJ77+AK77*AC77*0.5 -> 4797 | AM77: =AF77-AL77 -> 91143 | AN77: =AM77/AF77-1 -> -0.05 | AO77: =IFERROR(AM77/H77,"") -> 1.1059701 | AP77: =AM77-X77 -> 0 | AQ77: =AM77/X77-1 -> 0 | AR77: =IFERROR(AA77+AQ77*0.5,"") -> 0.24741923 | BV77: 0.24741923 | BW77: =IF(AA77>19%,AA77-3.8%,AA77) -> 0.20941923
A78: 2606 | B78: W/M | C78: DST | D78: WT1410NHEG.ABGPQTH | E78: WT1410NHEG.ABGPPTH | G78: =IFERROR(VLOOKUP(D78,[3]전용!E:J,6,0),"") | H78: 82410 | I78: 5 | J78: Self | K78: 12 | L78: 1499 | M78: =L78*LEFT(I78,1)*12 -> 89940 | N78: 0.32424261 | P78: 1499 | Q78: =L78-P78 -> 0 | R78: =P78*LEFT(I78,1)*12 -> 89940 | S78: =AA78-(Y78/2) -> 0.27241923 | V78: 6 | W78: =(P78-T78)*U78+V78*P78*0.5 -> 4497 | X78: =R78-W78 -> 85443 | Y78: =X78/R78-1 -> -0.05 | Z78: =IFERROR(X78/H78,"") -> 1.0368038 | AA78: 0.24741923 | AB78: -0.00011098753 | AC78: =P78+AD78 -> 1499 | AE78: =IF(AA78>10%,0,IF(AA78>5%,P78*0.04,IF(AA78>0%,P78*0.075, P78*0.1))) -> 0 | AF78: =AC78*LEFT(I78,1)*12 -> 89940 | AG78: =AF78/R78-1 -> 0 | AH78: 0 | AI78: =AR78+(AN78/2) -> 0.22241923 | AJ78: 0 | AK78: 6 | AL78: =(AC78-AH78)*AJ78+AK78*AC78*0.5 -> 4497 | AM78: =AF78-AL78 -> 85443 | AN78: =AM78/AF78-1 -> -0.05 | AO78: =IFERROR(AM78/H78,"") -> 1.0368038 | AP78: =AM78-X78 -> 0 | AQ78: =AM78/X78-1 -> 0 | AR78: =IFERROR(AA78+AQ78*0.5,"") -> 0.24741923 | BV78: 0.24741923 | BW78: =IF(AA78>19%,AA78-3.8%,AA78) -> 0.20941923
A79: 2606 | B79: W/M | C79: DST | D79: WT1410NHEG.ABGPQTH | E79: WT1410NHEG.ABGPPTH | G79: =IFERROR(VLOOKUP(D79,[3]전용!E:J,6,0),"") | H79: 82410 | I79: 6 | J79: Visit | K79: 12 | L79: 1399 | M79: =L79*LEFT(I79,1)*12 -> 100728 | N79: 0.32553677 | P79: 1399 | Q79: =L79-P79 -> 0 | R79: =P79*LEFT(I79,1)*12 -> 100728 | S79: =AA79-(Y79/2) -> 0.26825256 | V79: 6 | W79: =(P79-T79)*U79+V79*P79*0.5 -> 4197 | X79: =R79-W79 -> 96531 | Y79: =X79/R79-1 -> -0.041666667 | Z79: =IFERROR(X79/H79,"") -> 1.1713506 | AA79: 0.24741923 | AB79: -0.00011098753 | AC79: =P79+AD79 -> 1399 | AE79: =IF(AA79>10%,0,IF(AA79>5%,P79*0.04,IF(AA79>0%,P79*0.075, P79*0.1))) -> 0 | AF79: =AC79*LEFT(I79,1)*12 -> 100728 | AG79: =AF79/R79-1 -> 0 | AH79: 0 | AI79: =AR79+(AN79/2) -> 0.22658589 | AJ79: 0 | AK79: 6 | AL79: =(AC79-AH79)*AJ79+AK79*AC79*0.5 -> 4197 | AM79: =AF79-AL79 -> 96531 | AN79: =AM79/AF79-1 -> -0.041666667 | AO79: =IFERROR(AM79/H79,"") -> 1.1713506 | AP79: =AM79-X79 -> 0 | AQ79: =AM79/X79-1 -> 0 | AR79: =IFERROR(AA79+AQ79*0.5,"") -> 0.24741923 | BV79: 0.24741923 | BW79: =IF(AA79>19%,AA79-3.8%,AA79) -> 0.20941923
A80: 2606 | B80: W/M | C80: DST | D80: WT1410NHEG.ABGPQTH | E80: WT1410NHEG.ABGPPTH | G80: =IFERROR(VLOOKUP(D80,[3]전용!E:J,6,0),"") | H80: 82410 | I80: 6 | J80: Self | K80: 12 | L80: 1299 | M80: =L80*LEFT(I80,1)*12 -> 93528 | N80: 0.3309122 | P80: 1299 | Q80: =L80-P80 -> 0 | R80: =P80*LEFT(I80,1)*12 -> 93528 | S80: =AA80-(Y80/2) -> 0.26825256 | V80: 6 | W80: =(P80-T80)*U80+V80*P80*0.5 -> 3897 | X80: =R80-W80 -> 89631 | Y80: =X80/R80-1 -> -0.041666667 | Z80: =IFERROR(X80/H80,"") -> 1.0876229 | AA80: 0.24741923 | AB80: -0.00011098753 | AC80: =P80+AD80 -> 1299 | AE80: =IF(AA80>10%,0,IF(AA80>5%,P80*0.04,IF(AA80>0%,P80*0.075, P80*0.1))) -> 0 | AF80: =AC80*LEFT(I80,1)*12 -> 93528 | AG80: =AF80/R80-1 -> 0 | AH80: 0 | AI80: =AR80+(AN80/2) -> 0.22658589 | AJ80: 0 | AK80: 6 | AL80: =(AC80-AH80)*AJ80+AK80*AC80*0.5 -> 3897 | AM80: =AF80-AL80 -> 89631 | AN80: =AM80/AF80-1 -> -0.041666667 | AO80: =IFERROR(AM80/H80,"") -> 1.0876229 | AP80: =AM80-X80 -> 0 | AQ80: =AM80/X80-1 -> 0 | AR80: =IFERROR(AA80+AQ80*0.5,"") -> 0.24741923 | BV80: 0.24741923 | BW80: =IF(AA80>19%,AA80-3.8%,AA80) -> 0.20941923
A81: 2606 | B81: W/M | C81: DST | D81: WT1410NHEN.ABNPQTH | E81: WT1410NHEN.ABNPPTH | G81: =IFERROR(VLOOKUP(D81,[3]전용!E:J,6,0),"") | H81: 82410 | I81: 5 | J81: Visit | K81: 12 | L81: 1599 | M81: =L81*LEFT(I81,1)*12 -> 95940 | N81: 0.31936842 | P81: 1599 | Q81: =L81-P81 -> 0 | R81: =P81*LEFT(I81,1)*12 -> 95940 | S81: =AA81-(Y81/2) -> 0.26070459 | V81: 6 | W81: =(P81-T81)*U81+V81*P81*0.5 -> 4797 | X81: =R81-W81 -> 91143 | Y81: =X81/R81-1 -> -0.05 | Z81: =IFERROR(X81/H81,"") -> 1.1059701 | AA81: 0.23570459 | AB81: -0.00011057862 | AC81: =P81+AD81 -> 1599 | AE81: =IF(AA81>10%,0,IF(AA81>5%,P81*0.04,IF(AA81>0%,P81*0.075, P81*0.1))) -> 0 | AF81: =AC81*LEFT(I81,1)*12 -> 95940 | AG81: =AF81/R81-1 -> 0 | AH81: 0 | AI81: =AR81+(AN81/2) -> 0.21070459 | AJ81: 0 | AK81: 6 | AL81: =(AC81-AH81)*AJ81+AK81*AC81*0.5 -> 4797 | AM81: =AF81-AL81 -> 91143 | AN81: =AM81/AF81-1 -> -0.05 | AO81: =IFERROR(AM81/H81,"") -> 1.1059701 | AP81: =AM81-X81 -> 0 | AQ81: =AM81/X81-1 -> 0 | AR81: =IFERROR(AA81+AQ81*0.5,"") -> 0.23570459 | BV81: 0.23570459 | BW81: =IF(AA81>19%,AA81-3.8%,AA81) -> 0.19770459
A82: 2606 | B82: W/M | C82: DST | D82: WT1410NHEN.ABNPQTH | E82: WT1410NHEN.ABNPPTH | G82: =IFERROR(VLOOKUP(D82,[3]전용!E:J,6,0),"") | H82: 82410 | I82: 5 | J82: Self | K82: 12 | L82: 1499 | M82: =L82*LEFT(I82,1)*12 -> 89940 | N82: 0.32333763 | P82: 1499 | Q82: =L82-P82 -> 0 | R82: =P82*LEFT(I82,1)*12 -> 89940 | S82: =AA82-(Y82/2) -> 0.26070459 | V82: 6 | W82: =(P82-T82)*U82+V82*P82*0.5 -> 4497 | X82: =R82-W82 -> 85443 | Y82: =X82/R82-1 -> -0.05 | Z82: =IFERROR(X82/H82,"") -> 1.0368038 | AA82: 0.23570459 | AB82: -0.00011057862 | AC82: =P82+AD82 -> 1499 | AE82: =IF(AA82>10%,0,IF(AA82>5%,P82*0.04,IF(AA82>0%,P82*0.075, P82*0.1))) -> 0 | AF82: =AC82*LEFT(I82,1)*12 -> 89940 | AG82: =AF82/R82-1 -> 0 | AH82: 0 | AI82: =AR82+(AN82/2) -> 0.21070459 | AJ82: 0 | AK82: 6 | AL82: =(AC82-AH82)*AJ82+AK82*AC82*0.5 -> 4497 | AM82: =AF82-AL82 -> 85443 | AN82: =AM82/AF82-1 -> -0.05 | AO82: =IFERROR(AM82/H82,"") -> 1.0368038 | AP82: =AM82-X82 -> 0 | AQ82: =AM82/X82-1 -> 0 | AR82: =IFERROR(AA82+AQ82*0.5,"") -> 0.23570459 | BV82: 0.23570459 | BW82: =IF(AA82>19%,AA82-3.8%,AA82) -> 0.19770459
A83: 2606 | B83: W/M | C83: DST | D83: WT1410NHEN.ABNPQTH | E83: WT1410NHEN.ABNPPTH | G83: =IFERROR(VLOOKUP(D83,[3]전용!E:J,6,0),"") | H83: 82410 | I83: 6 | J83: Visit | K83: 12 | L83: 1399 | M83: =L83*LEFT(I83,1)*12 -> 100728 | N83: 0.3246318 | P83: 1399 | Q83: =L83-P83 -> 0 | R83: =P83*LEFT(I83,1)*12 -> 100728 | S83: =AA83-(Y83/2) -> 0.25653793 | V83: 6 | W83: =(P83-T83)*U83+V83*P83*0.5 -> 4197 | X83: =R83-W83 -> 96531 | Y83: =X83/R83-1 -> -0.041666667 | Z83: =IFERROR(X83/H83,"") -> 1.1713506 | AA83: 0.23570459 | AB83: -0.00011057862 | AC83: =P83+AD83 -> 1399 | AE83: =IF(AA83>10%,0,IF(AA83>5%,P83*0.04,IF(AA83>0%,P83*0.075, P83*0.1))) -> 0 | AF83: =AC83*LEFT(I83,1)*12 -> 100728 | AG83: =AF83/R83-1 -> 0 | AH83: 0 | AI83: =AR83+(AN83/2) -> 0.21487126 | AJ83: 0 | AK83: 6 | AL83: =(AC83-AH83)*AJ83+AK83*AC83*0.5 -> 4197 | AM83: =AF83-AL83 -> 96531 | AN83: =AM83/AF83-1 -> -0.041666667 | AO83: =IFERROR(AM83/H83,"") -> 1.1713506 | AP83: =AM83-X83 -> 0 | AQ83: =AM83/X83-1 -> 0 | AR83: =IFERROR(AA83+AQ83*0.5,"") -> 0.23570459 | BV83: 0.23570459 | BW83: =IF(AA83>19%,AA83-3.8%,AA83) -> 0.19770459
A84: 2606 | B84: W/M | C84: DST | D84: WT1410NHEN.ABNPQTH | E84: WT1410NHEN.ABNPPTH | G84: =IFERROR(VLOOKUP(D84,[3]전용!E:J,6,0),"") | H84: 82410 | I84: 6 | J84: Self | K84: 12 | L84: 1299 | M84: =L84*LEFT(I84,1)*12 -> 93528 | N84: 0.33000723 | P84: 1299 | Q84: =L84-P84 -> 0 | R84: =P84*LEFT(I84,1)*12 -> 93528 | S84: =AA84-(Y84/2) -> 0.25653793 | V84: 6 | W84: =(P84-T84)*U84+V84*P84*0.5 -> 3897 | X84: =R84-W84 -> 89631 | Y84: =X84/R84-1 -> -0.041666667 | Z84: =IFERROR(X84/H84,"") -> 1.0876229 | AA84: 0.23570459 | AB84: -0.00011057862 | AC84: =P84+AD84 -> 1299 | AE84: =IF(AA84>10%,0,IF(AA84>5%,P84*0.04,IF(AA84>0%,P84*0.075, P84*0.1))) -> 0 | AF84: =AC84*LEFT(I84,1)*12 -> 93528 | AG84: =AF84/R84-1 -> 0 | AH84: 0 | AI84: =AR84+(AN84/2) -> 0.21487126 | AJ84: 0 | AK84: 6 | AL84: =(AC84-AH84)*AJ84+AK84*AC84*0.5 -> 3897 | AM84: =AF84-AL84 -> 89631 | AN84: =AM84/AF84-1 -> -0.041666667 | AO84: =IFERROR(AM84/H84,"") -> 1.0876229 | AP84: =AM84-X84 -> 0 | AQ84: =AM84/X84-1 -> 0 | AR84: =IFERROR(AA84+AQ84*0.5,"") -> 0.23570459 | BV84: 0.23570459 | BW84: =IF(AA84>19%,AA84-3.8%,AA84) -> 0.19770459
A85: 2606 | B85: W/M | C85: DST | D85: F2520RNTB.AEBPETH | G85: =IFERROR(VLOOKUP(D85,[3]전용!E:J,6,0),"") | H85: 62833.333 | I85: 5 | J85: Visit | K85: 12 | L85: 899 | M85: =L85*LEFT(I85,1)*12 -> 53940 | N85: 0.15 | P85: 899 | Q85: =L85-P85 -> 0 | R85: =P85*LEFT(I85,1)*12 -> 53940 | S85: =AA85-(Y85/2) -> 0.24758933 | V85: 6 | W85: =(P85-T85)*U85+V85*P85*0.5 -> 2697 | X85: =R85-W85 -> 51243 | Y85: =X85/R85-1 -> -0.05 | Z85: =IFERROR(X85/H85,"") -> 0.81553846 | AA85: 0.22258933 | AB85: 0.027306106 | AC85: =P85+AD85 -> 899 | AE85: =IF(AA85>10%,0,IF(AA85>5%,P85*0.04,IF(AA85>0%,P85*0.075, P85*0.1))) -> 0 | AF85: =AC85*LEFT(I85,1)*12 -> 53940 | AG85: =AF85/R85-1 -> 0 | AH85: 0 | AI85: =AR85+(AN85/2) -> 0.19758933 | AJ85: 0 | AK85: 6 | AL85: =(AC85-AH85)*AJ85+AK85*AC85*0.5 -> 2697 | AM85: =AF85-AL85 -> 51243 | AN85: =AM85/AF85-1 -> -0.05 | AO85: =IFERROR(AM85/H85,"") -> 0.81553846 | AP85: =AM85-X85 -> 0 | AQ85: =AM85/X85-1 -> 0 | AR85: =IFERROR(AA85+AQ85*0.5,"") -> 0.22258933 | BV85: 0.22325637 | BW85: =IF(AA85>19%,AA85-3.8%,AA85) -> 0.18458933
A86: 2606 | B86: W/M | C86: DST | D86: F2520RNTB.AEBPETH | G86: =IFERROR(VLOOKUP(D86,[3]전용!E:J,6,0),"") | H86: 62833.333 | I86: 5 | J86: Self | K86: 12 | L86: 849 | M86: =L86*LEFT(I86,1)*12 -> 50940 | N86: 0.15 | P86: 849 | Q86: =L86-P86 -> 0 | R86: =P86*LEFT(I86,1)*12 -> 50940 | S86: =AA86-(Y86/2) -> 0.24758933 | V86: 6 | W86: =(P86-T86)*U86+V86*P86*0.5 -> 2547 | X86: =R86-W86 -> 48393 | Y86: =X86/R86-1 -> -0.05 | Z86: =IFERROR(X86/H86,"") -> 0.77018037 | AA86: 0.22258933 | AB86: 0.027306106 | AC86: =P86+AD86 -> 849 | AE86: =IF(AA86>10%,0,IF(AA86>5%,P86*0.04,IF(AA86>0%,P86*0.075, P86*0.1))) -> 0 | AF86: =AC86*LEFT(I86,1)*12 -> 50940 | AG86: =AF86/R86-1 -> 0 | AH86: 0 | AI86: =AR86+(AN86/2) -> 0.19758933 | AJ86: 0 | AK86: 6 | AL86: =(AC86-AH86)*AJ86+AK86*AC86*0.5 -> 2547 | AM86: =AF86-AL86 -> 48393 | AN86: =AM86/AF86-1 -> -0.05 | AO86: =IFERROR(AM86/H86,"") -> 0.77018037 | AP86: =AM86-X86 -> 0 | AQ86: =AM86/X86-1 -> 0 | AR86: =IFERROR(AA86+AQ86*0.5,"") -> 0.22258933 | BV86: 0.22325637 | BW86: =IF(AA86>19%,AA86-3.8%,AA86) -> 0.18458933
A87: 2606 | B87: W/M | C87: DST | D87: F2520RNTB.AEBPETH | G87: =IFERROR(VLOOKUP(D87,[3]전용!E:J,6,0),"") | H87: 62833.333 | I87: 6 | J87: Visit | K87: 12 | L87: 849 | M87: =L87*LEFT(I87,1)*12 -> 61128 | N87: 0.15 | P87: 849 | Q87: =L87-P87 -> 0 | R87: =P87*LEFT(I87,1)*12 -> 61128 | S87: =AA87-(Y87/2) -> 0.24342266 | V87: 6 | W87: =(P87-T87)*U87+V87*P87*0.5 -> 2547 | X87: =R87-W87 -> 58581 | Y87: =X87/R87-1 -> -0.041666667 | Z87: =IFERROR(X87/H87,"") -> 0.93232361 | AA87: 0.22258933 | AB87: 0.027306106 | AC87: =P87+AD87 -> 849 | AE87: =IF(AA87>10%,0,IF(AA87>5%,P87*0.04,IF(AA87>0%,P87*0.075, P87*0.1))) -> 0 | AF87: =AC87*LEFT(I87,1)*12 -> 61128 | AG87: =AF87/R87-1 -> 0 | AH87: 0 | AI87: =AR87+(AN87/2) -> 0.201756 | AJ87: 0 | AK87: 6 | AL87: =(AC87-AH87)*AJ87+AK87*AC87*0.5 -> 2547 | AM87: =AF87-AL87 -> 58581 | AN87: =AM87/AF87-1 -> -0.041666667 | AO87: =IFERROR(AM87/H87,"") -> 0.93232361 | AP87: =AM87-X87 -> 0 | AQ87: =AM87/X87-1 -> 0 | AR87: =IFERROR(AA87+AQ87*0.5,"") -> 0.22258933 | BV87: 0.22325637 | BW87: =IF(AA87>19%,AA87-3.8%,AA87) -> 0.18458933
A88: 2606 | B88: W/M | C88: DST | D88: F2520RNTB.AEBPETH | G88: =IFERROR(VLOOKUP(D88,[3]전용!E:J,6,0),"") | H88: 62833.333 | I88: 6 | J88: Self | K88: 12 | L88: 799 | M88: =L88*LEFT(I88,1)*12 -> 57528 | N88: 0.15 | P88: 799 | Q88: =L88-P88 -> 0 | R88: =P88*LEFT(I88,1)*12 -> 57528 | S88: =AA88-(Y88/2) -> 0.24342266 | V88: 6 | W88: =(P88-T88)*U88+V88*P88*0.5 -> 2397 | X88: =R88-W88 -> 55131 | Y88: =X88/R88-1 -> -0.041666667 | Z88: =IFERROR(X88/H88,"") -> 0.87741645 | AA88: 0.22258933 | AB88: 0.027306106 | AC88: =P88+AD88 -> 799 | AE88: =IF(AA88>10%,0,IF(AA88>5%,P88*0.04,IF(AA88>0%,P88*0.075, P88*0.1))) -> 0 | AF88: =AC88*LEFT(I88,1)*12 -> 57528 | AG88: =AF88/R88-1 -> 0 | AH88: 0 | AI88: =AR88+(AN88/2) -> 0.201756 | AJ88: 0 | AK88: 6 | AL88: =(AC88-AH88)*AJ88+AK88*AC88*0.5 -> 2397 | AM88: =AF88-AL88 -> 55131 | AN88: =AM88/AF88-1 -> -0.041666667 | AO88: =IFERROR(AM88/H88,"") -> 0.87741645 | AP88: =AM88-X88 -> 0 | AQ88: =AM88/X88-1 -> 0 | AR88: =IFERROR(AA88+AQ88*0.5,"") -> 0.22258933 | BV88: 0.22325637 | BW88: =IF(AA88>19%,AA88-3.8%,AA88) -> 0.18458933
A89: 2606 | B89: W/M | C89: DST | D89: FV1413H4M.AMBPETH | G89: =IFERROR(VLOOKUP(D89,[3]전용!E:J,6,0),"") | H89: 27900 | I89: 5 | J89: Visit | K89: 12 | L89: 749 | M89: =L89*LEFT(I89,1)*12 -> 44940 | N89: 0.32327784 | P89: 749 | Q89: =L89-P89 -> 0 | R89: =P89*LEFT(I89,1)*12 -> 44940 | S89: =AA89-(Y89/2) -> 0.22955732 | U89: 6 | W89: =(P89-T89)*U89+V89*P89*0.5 -> 4494 | X89: =R89-W89 -> 40446 | Y89: =X89/R89-1 -> -0.1 | Z89: =IFERROR(X89/H89,"") -> 1.4496774 | AA89: 0.17955732 | AB89: 0.091360126 | AC89: =P89+AD89 -> 749 | AE89: =IF(AA89>10%,0,IF(AA89>5%,P89*0.04,IF(AA89>0%,P89*0.075, P89*0.1))) -> 0 | AF89: =AC89*LEFT(I89,1)*12 -> 44940 | AG89: =AF89/R89-1 -> 0 | AH89: 0 | AI89: =AR89+(AN89/2) -> 0.18233509 | AJ89: 3 | AK89: 0 | AL89: =(AC89-AH89)*AJ89+AK89*AC89*0.5 -> 2247 | AM89: =AF89-AL89 -> 42693 | AN89: =AM89/AF89-1 -> -0.05 | AO89: =IFERROR(AM89/H89,"") -> 1.5302151 | AP89: =AM89-X89 -> 2247 | AQ89: =AM89/X89-1 -> 0.055555556 | AR89: =IFERROR(AA89+AQ89*0.5,"") -> 0.20733509 | BV89: 0.17902733 | BW89: =IF(AA89>19%,AA89-3.8%,AA89) -> 0.17955732
A90: 2606 | B90: W/M | C90: DST | D90: FV1413H4M.AMBPETH | G90: =IFERROR(VLOOKUP(D90,[3]전용!E:J,6,0),"") | H90: 27900 | I90: 5 | J90: Self | K90: 12 | L90: 649 | M90: =L90*LEFT(I90,1)*12 -> 38940 | N90: 0.32327784 | P90: 649 | Q90: =L90-P90 -> 0 | R90: =P90*LEFT(I90,1)*12 -> 38940 | S90: =AA90-(Y90/2) -> 0.22955732 | U90: 6 | W90: =(P90-T90)*U90+V90*P90*0.5 -> 3894 | X90: =R90-W90 -> 35046 | Y90: =X90/R90-1 -> -0.1 | Z90: =IFERROR(X90/H90,"") -> 1.256129 | AA90: 0.17955732 | AB90: 0.091360126 | AC90: =P90+AD90 -> 649 | AE90: =IF(AA90>10%,0,IF(AA90>5%,P90*0.04,IF(AA90>0%,P90*0.075, P90*0.1))) -> 0 | AF90: =AC90*LEFT(I90,1)*12 -> 38940 | AG90: =AF90/R90-1 -> 0 | AH90: 0 | AI90: =AR90+(AN90/2) -> 0.18233509 | AJ90: 3 | AK90: 0 | AL90: =(AC90-AH90)*AJ90+AK90*AC90*0.5 -> 1947 | AM90: =AF90-AL90 -> 36993 | AN90: =AM90/AF90-1 -> -0.05 | AO90: =IFERROR(AM90/H90,"") -> 1.325914 | AP90: =AM90-X90 -> 1947 | AQ90: =AM90/X90-1 -> 0.055555556 | AR90: =IFERROR(AA90+AQ90*0.5,"") -> 0.20733509 | BV90: 0.17902733 | BW90: =IF(AA90>19%,AA90-3.8%,AA90) -> 0.17955732
A91: 2606 | B91: W/M | C91: DST | D91: FV1413H4M.AMBPETH | G91: =IFERROR(VLOOKUP(D91,[3]전용!E:J,6,0),"") | H91: 27900 | I91: 6 | J91: Visit | K91: 12 | L91: 649 | M91: =L91*LEFT(I91,1)*12 -> 46728 | N91: 0.32032217 | P91: 649 | Q91: =L91-P91 -> 0 | R91: =P91*LEFT(I91,1)*12 -> 46728 | S91: =AA91-(Y91/2) -> 0.22122398 | U91: 6 | W91: =(P91-T91)*U91+V91*P91*0.5 -> 3894 | X91: =R91-W91 -> 42834 | Y91: =X91/R91-1 -> -0.083333333 | Z91: =IFERROR(X91/H91,"") -> 1.5352688 | AA91: 0.17955732 | AB91: 0.091360126 | AC91: =P91+AD91 -> 649 | AE91: =IF(AA91>10%,0,IF(AA91>5%,P91*0.04,IF(AA91>0%,P91*0.075, P91*0.1))) -> 0 | AF91: =AC91*LEFT(I91,1)*12 -> 46728 | AG91: =AF91/R91-1 -> 0 | AH91: 0 | AI91: =AR91+(AN91/2) -> 0.18145126 | AJ91: 3 | AK91: 0 | AL91: =(AC91-AH91)*AJ91+AK91*AC91*0.5 -> 1947 | AM91: =AF91-AL91 -> 44781 | AN91: =AM91/AF91-1 -> -0.041666667 | AO91: =IFERROR(AM91/H91,"") -> 1.6050538 | AP91: =AM91-X91 -> 1947 | AQ91: =AM91/X91-1 -> 0.045454545 | AR91: =IFERROR(AA91+AQ91*0.5,"") -> 0.20228459 | BV91: 0.17902733 | BW91: =IF(AA91>19%,AA91-3.8%,AA91) -> 0.17955732
A92: 2606 | B92: W/M | C92: DST | D92: FV1413H4M.AMBPETH | G92: =IFERROR(VLOOKUP(D92,[3]전용!E:J,6,0),"") | H92: 27900 | I92: 6 | J92: Self | K92: 12 | L92: 599 | M92: =L92*LEFT(I92,1)*12 -> 43128 | N92: 0.32032217 | P92: 599 | Q92: =L92-P92 -> 0 | R92: =P92*LEFT(I92,1)*12 -> 43128 | S92: =AA92-(Y92/2) -> 0.22122398 | U92: 6 | W92: =(P92-T92)*U92+V92*P92*0.5 -> 3594 | X92: =R92-W92 -> 39534 | Y92: =X92/R92-1 -> -0.083333333 | Z92: =IFERROR(X92/H92,"") -> 1.4169892 | AA92: 0.17955732 | AB92: 0.091360126 | AC92: =P92+AD92 -> 599 | AE92: =IF(AA92>10%,0,IF(AA92>5%,P92*0.04,IF(AA92>0%,P92*0.075, P92*0.1))) -> 0 | AF92: =AC92*LEFT(I92,1)*12 -> 43128 | AG92: =AF92/R92-1 -> 0 | AH92: 0 | AI92: =AR92+(AN92/2) -> 0.18145126 | AJ92: 3 | AK92: 0 | AL92: =(AC92-AH92)*AJ92+AK92*AC92*0.5 -> 1797 | AM92: =AF92-AL92 -> 41331 | AN92: =AM92/AF92-1 -> -0.041666667 | AO92: =IFERROR(AM92/H92,"") -> 1.4813978 | AP92: =AM92-X92 -> 1797 | AQ92: =AM92/X92-1 -> 0.045454545 | AR92: =IFERROR(AA92+AQ92*0.5,"") -> 0.20228459 | BV92: 0.17902733 | BW92: =IF(AA92>19%,AA92-3.8%,AA92) -> 0.17955732
A93: 2606 | B93: W/M | C93: DST | D93: FV1409H4W.ABWPETH | G93: =IFERROR(VLOOKUP(D93,[3]전용!E:J,6,0),"") | H93: 27111.111 | I93: 5 | J93: Visit | K93: 12 | L93: 499 | M93: =L93*LEFT(I93,1)*12 -> 29940 | N93: 0.15 | P93: 499 | Q93: =L93-P93 -> 0 | R93: =P93*LEFT(I93,1)*12 -> 29940 | S93: =AA93-(Y93/2) -> 0.26579706 | V93: 0 | W93: =(P93-T93)*U93+V93*P93*0.5 -> 0 | X93: =R93-W93 -> 29940 | Y93: =X93/R93-1 -> 0 | Z93: =IFERROR(X93/H93,"") -> 1.1043443 | AA93: 0.26579706 | AB93: 0.0050934735 | AC93: =P93+AD93 -> 499 | AE93: =IF(AA93>10%,0,IF(AA93>5%,P93*0.04,IF(AA93>0%,P93*0.075, P93*0.1))) -> 0 | AF93: =AC93*LEFT(I93,1)*12 -> 29940 | AG93: =AF93/R93-1 -> 0 | AH93: 0 | AI93: =AR93+(AN93/2) -> 0.26579706 | AJ93: 0 | AK93: 0 | AL93: =(AC93-AH93)*AJ93+AK93*AC93*0.5 -> 0 | AM93: =AF93-AL93 -> 29940 | AN93: =AM93/AF93-1 -> 0 | AO93: =IFERROR(AM93/H93,"") -> 1.1043443 | AP93: =AM93-X93 -> 0 | AQ93: =AM93/X93-1 -> 0 | AR93: =IFERROR(AA93+AQ93*0.5,"") -> 0.26579706 | BV93: 0.16 | BW93: =IF(AA93>19%,AA93-3.8%,AA93) -> 0.22779706
A94: 2606 | B94: W/M | C94: DST | D94: FV1409H4W.ABWPETH | G94: =IFERROR(VLOOKUP(D94,[3]전용!E:J,6,0),"") | H94: 27111.111 | I94: 5 | J94: Self | K94: 12 | L94: 449 | M94: =L94*LEFT(I94,1)*12 -> 26940 | N94: 0.15 | P94: 449 | Q94: =L94-P94 -> 0 | R94: =P94*LEFT(I94,1)*12 -> 26940 | S94: =AA94-(Y94/2) -> 0.26579706 | V94: 0 | W94: =(P94-T94)*U94+V94*P94*0.5 -> 0 | X94: =R94-W94 -> 26940 | Y94: =X94/R94-1 -> 0 | Z94: =IFERROR(X94/H94,"") -> 0.99368852 | AA94: 0.26579706 | AB94: 0.0050934735 | AC94: =P94+AD94 -> 449 | AE94: =IF(AA94>10%,0,IF(AA94>5%,P94*0.04,IF(AA94>0%,P94*0.075, P94*0.1))) -> 0 | AF94: =AC94*LEFT(I94,1)*12 -> 26940 | AG94: =AF94/R94-1 -> 0 | AH94: 0 | AI94: =AR94+(AN94/2) -> 0.26579706 | AJ94: 0 | AK94: 0 | AL94: =(AC94-AH94)*AJ94+AK94*AC94*0.5 -> 0 | AM94: =AF94-AL94 -> 26940 | AN94: =AM94/AF94-1 -> 0 | AO94: =IFERROR(AM94/H94,"") -> 0.99368852 | AP94: =AM94-X94 -> 0 | AQ94: =AM94/X94-1 -> 0 | AR94: =IFERROR(AA94+AQ94*0.5,"") -> 0.26579706 | BV94: 0.16 | BW94: =IF(AA94>19%,AA94-3.8%,AA94) -> 0.22779706
A95: 2606 | B95: W/M | C95: DST | D95: FV1409H4W.ABWPETH | G95: =IFERROR(VLOOKUP(D95,[3]전용!E:J,6,0),"") | H95: 27111.111 | I95: 6 | J95: Visit | K95: 12 | L95: 749 | M95: =L95*LEFT(I95,1)*12 -> 53928 | N95: 0.15 | P95: 449 | Q95: =L95-P95 -> 300 | R95: =P95*LEFT(I95,1)*12 -> 32328 | S95: =AA95-(Y95/2) -> 0.26579706 | V95: 0 | W95: =(P95-T95)*U95+V95*P95*0.5 -> 0 | X95: =R95-W95 -> 32328 | Y95: =X95/R95-1 -> 0 | Z95: =IFERROR(X95/H95,"") -> 1.1924262 | AA95: 0.26579706 | AB95: 0.0050934735 | AC95: =P95+AD95 -> 449 | AE95: =IF(AA95>10%,0,IF(AA95>5%,P95*0.04,IF(AA95>0%,P95*0.075, P95*0.1))) -> 0 | AF95: =AC95*LEFT(I95,1)*12 -> 32328 | AG95: =AF95/R95-1 -> 0 | AH95: 0 | AI95: =AR95+(AN95/2) -> 0.26579706 | AJ95: 0 | AK95: 0 | AL95: =(AC95-AH95)*AJ95+AK95*AC95*0.5 -> 0 | AM95: =AF95-AL95 -> 32328 | AN95: =AM95/AF95-1 -> 0 | AO95: =IFERROR(AM95/H95,"") -> 1.1924262 | AP95: =AM95-X95 -> 0 | AQ95: =AM95/X95-1 -> 0 | AR95: =IFERROR(AA95+AQ95*0.5,"") -> 0.26579706 | BV95: 0.16 | BW95: =IF(AA95>19%,AA95-3.8%,AA95) -> 0.22779706
A96: 2606 | B96: W/M | C96: DST | D96: FV1409H4W.ABWPETH | G96: =IFERROR(VLOOKUP(D96,[3]전용!E:J,6,0),"") | H96: 27111.111 | I96: 6 | J96: Self | K96: 12 | L96: 649 | M96: =L96*LEFT(I96,1)*12 -> 46728 | N96: 0.15 | P96: 399 | Q96: =L96-P96 -> 250 | R96: =P96*LEFT(I96,1)*12 -> 28728 | S96: =AA96-(Y96/2) -> 0.26579706 | V96: 0 | W96: =(P96-T96)*U96+V96*P96*0.5 -> 0 | X96: =R96-W96 -> 28728 | Y96: =X96/R96-1 -> 0 | Z96: =IFERROR(X96/H96,"") -> 1.0596393 | AA96: 0.26579706 | AB96: 0.0050934735 | AC96: =P96+AD96 -> 399 | AE96: =IF(AA96>10%,0,IF(AA96>5%,P96*0.04,IF(AA96>0%,P96*0.075, P96*0.1))) -> 0 | AF96: =AC96*LEFT(I96,1)*12 -> 28728 | AG96: =AF96/R96-1 -> 0 | AH96: 0 | AI96: =AR96+(AN96/2) -> 0.26579706 | AJ96: 0 | AK96: 0 | AL96: =(AC96-AH96)*AJ96+AK96*AC96*0.5 -> 0 | AM96: =AF96-AL96 -> 28728 | AN96: =AM96/AF96-1 -> 0 | AO96: =IFERROR(AM96/H96,"") -> 1.0596393 | AP96: =AM96-X96 -> 0 | AQ96: =AM96/X96-1 -> 0 | AR96: =IFERROR(AA96+AQ96*0.5,"") -> 0.26579706 | BV96: 0.26579706 | BW96: =IF(AA96>19%,AA96-3.8%,AA96) -> 0.22779706
A97: 2606 | B97: W/M | C97: DST | D97: FV1413S4M.AMBPETH | G97: =IFERROR(VLOOKUP(D97,[3]전용!E:J,6,0),"") | H97: 24300 | I97: 5 | J97: Visit | K97: 12 | L97: 749 | M97: =L97*LEFT(I97,1)*12 -> 44940 | N97: 0.35632358 | P97: 699 | Q97: =L97-P97 -> 50 | R97: =P97*LEFT(I97,1)*12 -> 41940 | S97: =AA97-(Y97/2) -> 0.26896606 | V97: 6 | W97: =(P97-T97)*U97+V97*P97*0.5 -> 2097 | X97: =R97-W97 -> 39843 | Y97: =X97/R97-1 -> -0.05 | Z97: =IFERROR(X97/H97,"") -> 1.6396296 | AA97: 0.24396606 | AB97: 0.065112074 | AC97: =P97+AD97 -> 699 | AE97: =IF(AA97>10%,0,IF(AA97>5%,P97*0.04,IF(AA97>0%,P97*0.075, P97*0.1))) -> 0 | AF97: =AC97*LEFT(I97,1)*12 -> 41940 | AG97: =AF97/R97-1 -> 0 | AH97: 0 | AI97: =AR97+(AN97/2) -> 0.21896606 | AJ97: 0 | AK97: 6 | AL97: =(AC97-AH97)*AJ97+AK97*AC97*0.5 -> 2097 | AM97: =AF97-AL97 -> 39843 | AN97: =AM97/AF97-1 -> -0.05 | AO97: =IFERROR(AM97/H97,"") -> 1.6396296 | AP97: =AM97-X97 -> 0 | AQ97: =AM97/X97-1 -> 0 | AR97: =IFERROR(AA97+AQ97*0.5,"") -> 0.24396606 | BV97: 0.24345988 | BW97: =IF(AA97>19%,AA97-3.8%,AA97) -> 0.20596606
A98: 2606 | B98: W/M | C98: DST | D98: FV1413S4M.AMBPETH | G98: =IFERROR(VLOOKUP(D98,[3]전용!E:J,6,0),"") | H98: 24300 | I98: 5 | J98: Self | K98: 12 | L98: 649 | M98: =L98*LEFT(I98,1)*12 -> 38940 | N98: 0.37305153 | P98: 599 | Q98: =L98-P98 -> 50 | R98: =P98*LEFT(I98,1)*12 -> 35940 | S98: =AA98-(Y98/2) -> 0.26896606 | V98: 6 | W98: =(P98-T98)*U98+V98*P98*0.5 -> 1797 | X98: =R98-W98 -> 34143 | Y98: =X98/R98-1 -> -0.05 | Z98: =IFERROR(X98/H98,"") -> 1.4050617 | AA98: 0.24396606 | AB98: 0.065112074 | AC98: =P98+AD98 -> 599 | AE98: =IF(AA98>10%,0,IF(AA98>5%,P98*0.04,IF(AA98>0%,P98*0.075, P98*0.1))) -> 0 | AF98: =AC98*LEFT(I98,1)*12 -> 35940 | AG98: =AF98/R98-1 -> 0 | AH98: 0 | AI98: =AR98+(AN98/2) -> 0.21896606 | AJ98: 0 | AK98: 6 | AL98: =(AC98-AH98)*AJ98+AK98*AC98*0.5 -> 1797 | AM98: =AF98-AL98 -> 34143 | AN98: =AM98/AF98-1 -> -0.05 | AO98: =IFERROR(AM98/H98,"") -> 1.4050617 | AP98: =AM98-X98 -> 0 | AQ98: =AM98/X98-1 -> 0 | AR98: =IFERROR(AA98+AQ98*0.5,"") -> 0.24396606 | BV98: 0.24345988 | BW98: =IF(AA98>19%,AA98-3.8%,AA98) -> 0.20596606
A99: 2606 | B99: W/M | C99: DST | D99: FV1413S4M.AMBPETH | G99: =IFERROR(VLOOKUP(D99,[3]전용!E:J,6,0),"") | H99: 24300 | I99: 6 | J99: Visit | K99: 12 | L99: 1249 | M99: =L99*LEFT(I99,1)*12 -> 89928 | N99: 0.37305153 | P99: 599 | Q99: =L99-P99 -> 650 | R99: =P99*LEFT(I99,1)*12 -> 43128 | S99: =AA99-(Y99/2) -> 0.26479939 | V99: 6 | W99: =(P99-T99)*U99+V99*P99*0.5 -> 1797 | X99: =R99-W99 -> 41331 | Y99: =X99/R99-1 -> -0.041666667 | Z99: =IFERROR(X99/H99,"") -> 1.7008642 | AA99: 0.24396606 | AB99: 0.065112074 | AC99: =P99+AD99 -> 599 | AE99: =IF(AA99>10%,0,IF(AA99>5%,P99*0.04,IF(AA99>0%,P99*0.075, P99*0.1))) -> 0 | AF99: =AC99*LEFT(I99,1)*12 -> 43128 | AG99: =AF99/R99-1 -> 0 | AH99: 0 | AI99: =AR99+(AN99/2) -> 0.22313272 | AJ99: 0 | AK99: 6 | AL99: =(AC99-AH99)*AJ99+AK99*AC99*0.5 -> 1797 | AM99: =AF99-AL99 -> 41331 | AN99: =AM99/AF99-1 -> -0.041666667 | AO99: =IFERROR(AM99/H99,"") -> 1.7008642 | AP99: =AM99-X99 -> 0 | AQ99: =AM99/X99-1 -> 0 | AR99: =IFERROR(AA99+AQ99*0.5,"") -> 0.24396606 | BV99: 0.24345988 | BW99: =IF(AA99>19%,AA99-3.8%,AA99) -> 0.20596606
A100: 2606 | B100: W/M | C100: DST | D100: FV1413S4M.AMBPETH | G100: =IFERROR(VLOOKUP(D100,[3]전용!E:J,6,0),"") | H100: 24300 | I100: 6 | J100: Self | K100: 12 | L100: 1249 | M100: =L100*LEFT(I100,1)*12 -> 89928 | N100: 0.38420971 | P100: 549 | Q100: =L100-P100 -> 700 | R100: =P100*LEFT(I100,1)*12 -> 39528 | S100: =AA100-(Y100/2) -> 0.26479939 | V100: 6 | W100: =(P100-T100)*U100+V100*P100*0.5 -> 1647 | X100: =R100-W100 -> 37881 | Y100: =X100/R100-1 -> -0.041666667 | Z100: =IFERROR(X100/H100,"") -> 1.5588889 | AA100: 0.24396606 | AB100: 0.065112074 | AC100: =P100+AD100 -> 549 | AE100: =IF(AA100>10%,0,IF(AA100>5%,P100*0.04,IF(AA100>0%,P100*0.075, P100*0.1))) -> 0 | AF100: =AC100*LEFT(I100,1)*12 -> 39528 | AG100: =AF100/R100-1 -> 0 | AH100: 0 | AI100: =AR100+(AN100/2) -> 0.22313272 | AJ100: 0 | AK100: 6 | AL100: =(AC100-AH100)*AJ100+AK100*AC100*0.5 -> 1647 | AM100: =AF100-AL100 -> 37881 | AN100: =AM100/AF100-1 -> -0.041666667 | AO100: =IFERROR(AM100/H100,"") -> 1.5588889 | AP100: =AM100-X100 -> 0 | AQ100: =AM100/X100-1 -> 0 | AR100: =IFERROR(AA100+AQ100*0.5,"") -> 0.24396606 | BV100: 0.24345988 | BW100: =IF(AA100>19%,AA100-3.8%,AA100) -> 0.20596606
...

Sheet 2606_RAW_OBS Exclusive
AG1: =AVERAGE(AG4:AG206) -> -0.00092812848 | AQ1: =AVERAGE(AQ4:AQ206) -> 0.012425569
P2: As Is | AC2: To Be | BH2: To Be (August)
A3: Month | B3: Division | C3: Operation | D3: Model | G3: Exclusive Model | H3: Outright Price | I3: Contract (Year) | J3: Care Type | K3: Service Cycle (M) | L3: Original Price | M3: Original Total Price | N3: COI 2026 | O3: Sales (EA/Mon) | P3: As Is Price (THB) | Q3: Discount (THB) | R3: As Is Total Price (THB) | S3: COI | T3: Special Price | U3: Special Price Discount (Month) | V3: 50% Discount (Month) | W3: Total Promotion (THB) | X3: Total Promotion Price (THB) | Y3: Promotion % | Z3: vs Outright | AA3: COI Promotion | AB3: Bad Debt | AC3: To Be Price (THB) | AD3: Increase (To be - As Is) | AE3: Logic | AF3: To be Total Price (THB) | AG3: Increase Total Price (To be - As Is) | AH3: Special Price | AI3: COI | AJ3: Special Price Discount (Month) | AK3: 50% Discount (Month) | AL3: Total Promotion (THB) | AM3: Total Promotion Price (THB) | AN3: Promotion % | AO3: vs Outright | AP3: Increase (To be - As Is) | AQ3: Increase % (To be - As Is) | AR3: COI Promotion | AS3: Remark | AT3: Reflection | AU3: As Is Norma l - To be | AV3: Same | AW3: To Be Price (THB) | AX3: Increase (To be - As) | AY3: To be Total Price (THB) | AZ3: Special Price | BA3: 50% Discount (Month) | BB3: Total Promotion (THB) | BC3: Total Operation Price (THB) | BD3: Increase (To be - As) | BE3: Increase % (To be - As) | BF3: COI Promotion | BG3: Remark | BH3: To Be Price (THB) | BI3: To Be Price (THB) | BJ3: Increase (To be - As) | BK3: To be Total Price (THB) | BL3: Special Price | BM3: 50% Discount (Month) | BN3: Total Promotion (THB) | BO3: Total Operation Price (THB) | BP3: Increase (To be - As) | BQ3: Increase % (To be - As) | BR3: COI Promotion | BS3: Remark | BT3: Apr Sales | BW3: =IF(AA4>17%,AA4-2%,AA4) -> -0.10188921
A4: 2606 | B4: REF | C4: DST | D4: PTOX24FFCR2.APTO | E4: GC-X24FFCRB.AEVPLM1 | F4: REF3FILTER2.AETC | G4: =IFERROR(VLOOKUP(D4,[3]전용!E:J,6,0),"") | H4: 77666.667 | I4: 5 | J4: Visit | K4: 6 | L4: 1749 | M4: =L4*LEFT(I4,1)*12 -> 104940 | N4: 0.15 | P4: 1349 | Q4: =L4-P4 -> 400 | R4: =P4*LEFT(I4,1)*12 -> 80940 | S4: =AA4-(Y4/2) -> -0.089389211 | V4: 3 | W4: =(P4-T4)*U4+V4*P4*0.5 -> 2023.5 | X4: =R4-W4 -> 78916.5 | Y4: =X4/R4-1 -> -0.025 | Z4: =IFERROR(X4/H4,"") -> 1.0160923 | AA4: -0.10188921 | AB4: 0.0213149 | AC4: =P4+AD4 -> 1449 | AD4: 100 | AE4: =IF(AA4>10%,0,IF(AA4>5%,P4*0.04,IF(AA4>0%,P4*0.04, P4*0.1))) -> 134.9 | AF4: =AC4*LEFT(I4,1)*12 -> 86940 | AG4: =AF4/R4-1 -> 0.074128984 | AH4: 149 | AI4: =AR4+(AN4/2) -> -0.048192758 | AJ4: 3 | AK4: 0 | AL4: =(AC4-AH4)*AJ4+AK4*AC4*0.5 -> 3900 | AM4: =AF4-AL4 -> 83040 | AN4: =AM4/AF4-1 -> -0.044858523 | AO4: =IFERROR(AM4/H4,"") -> 1.0691845 | AP4: =AM4-X4 -> 4123.5 | AQ4: =AM4/X4-1 -> 0.05225143 | AR4: =IFERROR(AA4+AQ4*0.5,"")+5% -> -0.025763496 | AS4: Service Fee: 250 | BT4: {=vlook} -> #NAME? | BU4: =AP4/X4 -> 0.05225143 | BV4: 0.05 | BW4: =IF(AA4>19%,AA4-3.8%,AA4) -> -0.10188921
A5: 2606 | B5: REF | C5: DST | D5: PTOX24FFCR2.APTO | E5: GC-X24FFCRB.AEVPLM1 | F5: REF3FILTER2.AETC | G5: =IFERROR(VLOOKUP(D5,[3]전용!E:J,6,0),"") | H5: 77666.667 | I5: 6 | J5: Visit | K5: 6 | L5: 1549 | M5: =L5*LEFT(I5,1)*12 -> 111528 | N5: 0.15 | P5: 1149 | Q5: =L5-P5 -> 400 | R5: =P5*LEFT(I5,1)*12 -> 82728 | S5: =AA5-(Y5/2) -> -0.091472545 | V5: 3 | W5: =(P5-T5)*U5+V5*P5*0.5 -> 1723.5 | X5: =R5-W5 -> 81004.5 | Y5: =X5/R5-1 -> -0.020833333 | Z5: =IFERROR(X5/H5,"") -> 1.0429764 | AA5: -0.10188921 | AB5: 0.0213149 | AC5: =P5+AD5 -> 1249 | AD5: 100 | AE5: =IF(AA5>10%,0,IF(AA5>5%,P5*0.04,IF(AA5>0%,P5*0.04, P5*0.1))) -> 114.9 | AF5: =AC5*LEFT(I5,1)*12 -> 89928 | AG5: =AF5/R5-1 -> 0.087032202 | AH5: 149 | AI5: =AR5+(AN5/2) -> -0.035526189 | AJ5: 3 | AK5: 0 | AL5: =(AC5-AH5)*AJ5+AK5*AC5*0.5 -> 3300 | AM5: =AF5-AL5 -> 86628 | AN5: =AM5/AF5-1 -> -0.036696023 | AO5: =IFERROR(AM5/H5,"") -> 1.115382 | AP5: =AM5-X5 -> 5623.5 | AQ5: =AM5/X5-1 -> 0.069422069 | AR5: =IFERROR(AA5+AQ5*0.5,"")+5% -> -0.017178177 | AS5: Service Fee: 250 | BU5: =AP5/X5 -> 0.069422069 | BV5: 0.05 | BW5: =IF(AA5>19%,AA5-3.8%,AA5) -> -0.10188921
A6: 2606 | B6: REF | C6: EOL after inventory depletion | D6: PTOL24FFCB2.APTO | E6: GC-L24FFCBB.AEVPLM1 | F6: REF3FILTER2.AETC | G6: =IFERROR(VLOOKUP(D6,[3]전용!E:J,6,0),"") | H6: 62111.111 | I6: 5 | J6: Visit | K6: 6 | L6: 1549 | M6: =L6*LEFT(I6,1)*12 -> 92940 | N6: 0.15 | P6: 1149 | Q6: =L6-P6 -> 400 | R6: =P6*LEFT(I6,1)*12 -> 68940 | S6: =AA6-(Y6/2) -> -0.25137495 | V6: 3 | W6: =(P6-T6)*U6+V6*P6*0.5 -> 1723.5 | X6: =R6-W6 -> 67216.5 | Y6: =X6/R6-1 -> -0.025 | Z6: =IFERROR(X6/H6,"") -> 1.0821977 | AA6: -0.26387495 | AB6: 0.018432619 | AC6: =P6+AD6 -> 1249 | AD6: 100 | AE6: =IF(AA6>10%,0,IF(AA6>5%,P6*0.04,IF(AA6>0%,P6*0.04, P6*0.1))) -> 114.9 | AF6: =AC6*LEFT(I6,1)*12 -> 74940 | AG6: =AF6/R6-1 -> 0.087032202 | AH6: 149 | AI6: =AR6+(AN6/2) -> -0.11324478 | AJ6: 3 | AK6: 0 | AL6: =(AC6-AH6)*AJ6+AK6*AC6*0.5 -> 3300 | AM6: =AF6-AL6 -> 71640 | AN6: =AM6/AF6-1 -> -0.044035228 | AO6: =IFERROR(AM6/H6,"") -> 1.1534168 | AP6: =AM6-X6 -> 4423.5 | AQ6: =AM6/X6-1 -> 0.065809734 | AR6: =IFERROR(AA6+AQ6*0.8,"")+12% -> -0.091227167 | AS6: Service Fee: 200 | BU6: =AP6/X6 -> 0.065809734 | BV6: 0.03 | BW6: =IF(AA6>19%,AA6-3.8%,AA6) -> -0.26387495
A7: 2606 | B7: REF | C7: EOL after inventory depletion | D7: PTOL24FFCB2.APTO | E7: GC-L24FFCBB.AEVPLM1 | F7: REF3FILTER2.AETC | G7: =IFERROR(VLOOKUP(D7,[3]전용!E:J,6,0),"") | H7: 62111.111 | I7: 6 | J7: Visit | K7: 6 | L7: 1349 | M7: =L7*LEFT(I7,1)*12 -> 97128 | N7: 0.15 | P7: 949 | Q7: =L7-P7 -> 400 | R7: =P7*LEFT(I7,1)*12 -> 68328 | S7: =AA7-(Y7/2) -> -0.25345829 | V7: 3 | W7: =(P7-T7)*U7+V7*P7*0.5 -> 1423.5 | X7: =R7-W7 -> 66904.5 | Y7: =X7/R7-1 -> -0.020833333 | Z7: =IFERROR(X7/H7,"") -> 1.0771744 | AA7: -0.26387495 | AB7: 0.018432619 | AC7: =P7+AD7 -> 1049 | AD7: 100 | AE7: =IF(AA7>10%,0,IF(AA7>5%,P7*0.04,IF(AA7>0%,P7*0.04, P7*0.1))) -> 94.9 | AF7: =AC7*LEFT(I7,1)*12 -> 75528 | AG7: =AF7/R7-1 -> 0.10537408 | AH7: 149 | AI7: =AR7+(AN7/2) -> -0.1109198 | AJ7: 3 | AK7: 0 | AL7: =(AC7-AH7)*AJ7+AK7*AC7*0.5 -> 2700 | AM7: =AF7-AL7 -> 72828 | AN7: =AM7/AF7-1 -> -0.035748332 | AO7: =IFERROR(AM7/H7,"") -> 1.1725438 | AP7: =AM7-X7 -> 5923.5 | AQ7: =AM7/X7-1 -> 0.088536646 | AR7: =IFERROR(AA7+AQ7*0.8,"")+10% -> -0.093045638 | AS7: Service Fee: 200 | BU7: =AP7/X7 -> 0.088536646 | BV7: 0.03 | BW7: =IF(AA7>19%,AA7-3.8%,AA7) -> -0.26387495
A8: 2606 | B8: REF | C8: DST | D8: PTOV25FFGR3.APTO | E8: GV-V25FFGRB.ABMPLMT | G8: =IFERROR(VLOOKUP(D8,[3]전용!E:J,6,0),"") | H8: 53222.222 | I8: 5 | J8: Visit | K8: 24 | L8: 949 | M8: =L8*LEFT(I8,1)*12 -> 56940 | N8: 0.18477592 | P8: 949 | Q8: =L8-P8 -> 0 | R8: =P8*LEFT(I8,1)*12 -> 56940 | S8: =AA8-(Y8/2) -> -0.049170477 | V8: 6 | W8: =(P8-T8)*U8+V8*P8*0.5 -> 2847 | X8: =R8-W8 -> 54093 | Y8: =X8/R8-1 -> -0.05 | Z8: =IFERROR(X8/H8,"") -> 1.0163612 | AA8: -0.074170477 | AB8: 0.075190742 | AC8: =P8+AD8 -> 999 | AD8: 50 | AE8: =IF(AA8>10%,0,IF(AA8>5%,P8*0.04,IF(AA8>0%,P8*0.075, P8*0.1))) -> 94.9 | AF8: =AC8*LEFT(I8,1)*12 -> 59940 | AG8: =AF8/R8-1 -> 0.052687039 | AH8: 0 | AI8: =AR8+(AN8/2) -> -0.018436879 | AJ8: 0 | AK8: 3 | AL8: =(AC8-AH8)*AJ8+AK8*AC8*0.5 -> 1498.5 | AM8: =AF8-AL8 -> 58441.5 | AN8: =AM8/AF8-1 -> -0.025 | AO8: =IFERROR(AM8/H8,"") -> 1.0980658 | AP8: =AM8-X8 -> 4348.5 | AQ8: =AM8/X8-1 -> 0.080389329 | AR8: =IFERROR(AA8+AQ8*0.6,"")+2% -> -0.0059368794 | BU8: =AP8/X8 -> 0.080389329 | BV8: 0.01 | BW8: =IF(AA8>19%,AA8-3.8%,AA8) -> -0.074170477
A9: 2606 | B9: REF | C9: DST | D9: PTOV25FFGR3.APTO | E9: GV-V25FFGRB.ABMPLMT | G9: =IFERROR(VLOOKUP(D9,[3]전용!E:J,6,0),"") | H9: 53222.222 | I9: 6 | J9: Visit | K9: 24 | L9: 899 | M9: =L9*LEFT(I9,1)*12 -> 64728 | N9: 0.18477592 | P9: 899 | Q9: =L9-P9 -> 0 | R9: =P9*LEFT(I9,1)*12 -> 64728 | S9: =AA9-(Y9/2) -> -0.053337144 | V9: 6 | W9: =(P9-T9)*U9+V9*P9*0.5 -> 2697 | X9: =R9-W9 -> 62031 | Y9: =X9/R9-1 -> -0.041666667 | Z9: =IFERROR(X9/H9,"") -> 1.1655094 | AA9: -0.074170477 | AB9: 0.075190742 | AC9: =P9+AD9 -> 949 | AD9: 50 | AE9: =IF(AA9>10%,0,IF(AA9>5%,P9*0.04,IF(AA9>0%,P9*0.075, P9*0.1))) -> 89.9 | AF9: =AC9*LEFT(I9,1)*12 -> 68328 | AG9: =AF9/R9-1 -> 0.055617353 | AH9: 0 | AI9: =AR9+(AN9/2) -> -0.01744781 | AJ9: 0 | AK9: 3 | AL9: =(AC9-AH9)*AJ9+AK9*AC9*0.5 -> 1423.5 | AM9: =AF9-AL9 -> 66904.5 | AN9: =AM9/AF9-1 -> -0.020833333 | AO9: =IFERROR(AM9/H9,"") -> 1.2570783 | AP9: =AM9-X9 -> 4873.5 | AQ9: =AM9/X9-1 -> 0.078565556 | AR9: =IFERROR(AA9+AQ9*0.6,"")+2% -> -0.0070311436 | BU9: =AP9/X9 -> 0.078565556 | BV9: 0.01 | BW9: =IF(AA9>19%,AA9-3.8%,AA9) -> -0.074170477
A10: 2606 | B10: REF | C10: DST | D10: GC-G24FFQKB.AEEPLM1 | G10: =IFERROR(VLOOKUP(D10,[3]전용!E:J,6,0),"") | H10: 61000 | I10: 5 | J10: Visit | K10: 24 | L10: 1299 | M10: =L10*LEFT(I10,1)*12 -> 77940 | N10: 0.17841392 | P10: 1299 | Q10: =L10-P10 -> 0 | R10: =P10*LEFT(I10,1)*12 -> 77940 | S10: =AA10-(Y10/2) -> 0.081027598 | V10: 6 | W10: =(P10-T10)*U10+V10*P10*0.5 -> 3897 | X10: =R10-W10 -> 74043 | Y10: =X10/R10-1 -> -0.05 | Z10: =IFERROR(X10/H10,"") -> 1.2138197 | AA10: 0.056027598 | AB10: 0.036888813 | AC10: =P10+AD10 -> 1349 | AD10: 50 | AE10: =IF(AA10>10%,0,IF(AA10>5%,P10*0.04,IF(AA10>0%,P10*0.075, P10*0.1))) -> 51.96 | AF10: =AC10*LEFT(I10,1)*12 -> 80940 | AG10: =AF10/R10-1 -> 0.038491147 | AH10: 0 | AI10: =AR10+(AN10/2) -> 0.076437528 | AJ10: 0 | AK10: 3 | AL10: =(AC10-AH10)*AJ10+AK10*AC10*0.5 -> 2023.5 | AM10: =AF10-AL10 -> 78916.5 | AN10: =AM10/AF10-1 -> -0.025 | AO10: =IFERROR(AM10/H10,"") -> 1.2937131 | AP10: =AM10-X10 -> 4873.5 | AQ10: =AM10/X10-1 -> 0.065819861 | AR10: =IFERROR(AA10+AQ10*0.5,"") -> 0.088937528 | BU10: =AP10/X10 -> 0.065819861 | BV10: 0.087150387 | BW10: =IF(AA10>19%,AA10-3.8%,AA10) -> 0.056027598
A11: 2606 | B11: REF | C11: DST | D11: GC-G24FFQKB.AEEPLM1 | G11: =IFERROR(VLOOKUP(D11,[3]전용!E:J,6,0),"") | H11: 61000 | I11: 6 | J11: Visit | K11: 24 | L11: 1099 | M11: =L11*LEFT(I11,1)*12 -> 79128 | N11: 0.17926517 | P11: 1099 | Q11: =L11-P11 -> 0 | R11: =P11*LEFT(I11,1)*12 -> 79128 | S11: =AA11-(Y11/2) -> 0.076860931 | V11: 6 | W11: =(P11-T11)*U11+V11*P11*0.5 -> 3297 | X11: =R11-W11 -> 75831 | Y11: =X11/R11-1 -> -0.041666667 | Z11: =IFERROR(X11/H11,"") -> 1.2431311 | AA11: 0.056027598 | AB11: 0.036888813 | AC11: =P11+AD11 -> 1149 | AD11: 50 | AE11: =IF(AA11>10%,0,IF(AA11>5%,P11*0.04,IF(AA11>0%,P11*0.075, P11*0.1))) -> 43.96 | AF11: =AC11*LEFT(I11,1)*12 -> 82728 | AG11: =AF11/R11-1 -> 0.045495905 | AH11: 0 | AI11: =AR11+(AN11/2) -> 0.07972297 | AJ11: 0 | AK11: 3 | AL11: =(AC11-AH11)*AJ11+AK11*AC11*0.5 -> 1723.5 | AM11: =AF11-AL11 -> 81004.5 | AN11: =AM11/AF11-1 -> -0.020833333 | AO11: =IFERROR(AM11/H11,"") -> 1.3279426 | AP11: =AM11-X11 -> 5173.5 | AQ11: =AM11/X11-1 -> 0.068224077 | AR11: =IFERROR(AA11+AQ11*0.5,"") -> 0.090139636 | BU11: =AP11/X11 -> 0.068224077 | BV11: 0.057150387 | BW11: =IF(AA11>19%,AA11-3.8%,AA11) -> 0.056027598
A12: 2606 | B12: REF | C12: DST | D12: PTOX257CMHW.APTO | E12: GC-X257CMHW.AEEPLMT | G12: =IFERROR(VLOOKUP(D12,[3]전용!E:J,6,0),"") | H12: 72666.667 | I12: 5 | J12: Visit | K12: 6 | L12: 1349 | M12: =L12*LEFT(I12,1)*12 -> 80940 | N12: 0.08 | P12: 1349 | Q12: =L12-P12 -> 0 | R12: =P12*LEFT(I12,1)*12 -> 80940 | S12: =AA12-(Y12/2) -> 0.011446918 | V12: 0 | W12: =(P12-T12)*U12+V12*P12*0.5 -> 0 | X12: =R12-W12 -> 80940 | Y12: =X12/R12-1 -> 0 | Z12: =IFERROR(X12/H12,"") -> 1.1138532 | AA12: 0.011446918 | AB12: 3.2227929e-05 | AC12: =P12+AD12 -> 1449 | AD12: 100 | AE12: =IF(AA12>10%,0,IF(AA12>5%,P12*0.04,IF(AA12>0%,P12*0.075, P12*0.1))) -> 101.175 | AF12: =AC12*LEFT(I12,1)*12 -> 86940 | AG12: =AF12/R12-1 -> 0.074128984 | AH12: 0 | AI12: =AR12+(AN12/2) -> 0.04851141 | AJ12: 0 | AK12: 0 | AL12: =(AC12-AH12)*AJ12+AK12*AC12*0.5 -> 0 | AM12: =AF12-AL12 -> 86940 | AN12: =AM12/AF12-1 -> 0 | AO12: =IFERROR(AM12/H12,"") -> 1.196422 | AP12: =AM12-X12 -> 6000 | AQ12: =AM12/X12-1 -> 0.074128984 | AR12: =IFERROR(AA12+AQ12*0.5,"") -> 0.04851141 | AS12: Service Fee: 250 | BU12: =AP12/X12 -> 0.074128984 | BV12: 0.02 | BW12: =IF(AA12>19%,AA12-3.8%,AA12) -> 0.011446918
A13: 2606 | B13: REF | C13: DST | D13: PTOX257CMHW.APTO | E13: GC-X257CMHW.AEEPLMT | G13: =IFERROR(VLOOKUP(D13,[3]전용!E:J,6,0),"") | H13: 72666.667 | I13: 6 | J13: Visit | K13: 6 | L13: 1149 | M13: =L13*LEFT(I13,1)*12 -> 82728 | N13: 0.09 | P13: 1149 | Q13: =L13-P13 -> 0 | R13: =P13*LEFT(I13,1)*12 -> 82728 | S13: =AA13-(Y13/2) -> 0.011446918 | V13: 0 | W13: =(P13-T13)*U13+V13*P13*0.5 -> 0 | X13: =R13-W13 -> 82728 | Y13: =X13/R13-1 -> 0 | Z13: =IFERROR(X13/H13,"") -> 1.1384587 | AA13: 0.011446918 | AB13: 3.2227929e-05 | AC13: =P13+AD13 -> 1249 | AD13: 100 | AE13: =IF(AA13>10%,0,IF(AA13>5%,P13*0.04,IF(AA13>0%,P13*0.075, P13*0.1))) -> 86.175 | AF13: =AC13*LEFT(I13,1)*12 -> 89928 | AG13: =AF13/R13-1 -> 0.087032202 | AH13: 0 | AI13: =AR13+(AN13/2) -> 0.054963019 | AJ13: 0 | AK13: 0 | AL13: =(AC13-AH13)*AJ13+AK13*AC13*0.5 -> 0 | AM13: =AF13-AL13 -> 89928 | AN13: =AM13/AF13-1 -> 0 | AO13: =IFERROR(AM13/H13,"") -> 1.2375413 | AP13: =AM13-X13 -> 7200 | AQ13: =AM13/X13-1 -> 0.087032202 | AR13: =IFERROR(AA13+AQ13*0.5,"") -> 0.054963019 | AS13: Service Fee: 250 | BU13: =AP13/X13 -> 0.087032202 | BV13: 0.02 | BW13: =IF(AA13>19%,AA13-3.8%,AA13) -> 0.011446918
A14: 2606 | B14: REF | C14: DST | D14: GC-X257CMEW.ATEPLMT | G14: =IFERROR(VLOOKUP(D14,[3]전용!E:J,6,0),"") | H14: 66555.556 | I14: 5 | J14: Visit | K14: 24 | L14: 1199 | M14: =L14*LEFT(I14,1)*12 -> 71940 | N14: 0.24824138 | P14: 1199 | Q14: =L14-P14 -> 0 | R14: =P14*LEFT(I14,1)*12 -> 71940 | S14: =AA14-(Y14/2) -> 0.062547215 | V14: 6 | W14: =(P14-T14)*U14+V14*P14*0.5 -> 3597 | X14: =R14-W14 -> 68343 | Y14: =X14/R14-1 -> -0.05 | Z14: =IFERROR(X14/H14,"") -> 1.0268564 | AA14: 0.037547215 | AB14: 0.11607894 | AC14: =P14+AD14 -> 1249 | AD14: 50 | AE14: =IF(AA14>10%,0,IF(AA14>5%,P14*0.04,IF(AA14>0%,P14*0.075, P14*0.1))) -> 89.925 | AF14: =AC14*LEFT(I14,1)*12 -> 74940 | AG14: =AF14/R14-1 -> 0.041701418 | AH14: 0 | AI14: =AR14+(AN14/2) -> 0.059604521 | AJ14: 0 | AK14: 3 | AL14: =(AC14-AH14)*AJ14+AK14*AC14*0.5 -> 1873.5 | AM14: =AF14-AL14 -> 73066.5 | AN14: =AM14/AF14-1 -> -0.025 | AO14: =IFERROR(AM14/H14,"") -> 1.0978272 | AP14: =AM14-X14 -> 4723.5 | AQ14: =AM14/X14-1 -> 0.069114613 | AR14: =IFERROR(AA14+AQ14*0.5,"") -> 0.072104521 | BU14: =AP14/X14 -> 0.069114613 | BV14: 0.063 | BW14: =IF(AA14>19%,AA14-3.8%,AA14) -> 0.037547215
A15: 2606 | B15: REF | C15: DST | D15: GC-X257CMEW.ATEPLMT | G15: =IFERROR(VLOOKUP(D15,[3]전용!E:J,6,0),"") | H15: 66555.556 | I15: 6 | J15: Visit | K15: 24 | L15: 999 | M15: =L15*LEFT(I15,1)*12 -> 71928 | N15: 0.2554274 | P15: 999 | Q15: =L15-P15 -> 0 | R15: =P15*LEFT(I15,1)*12 -> 71928 | S15: =AA15-(Y15/2) -> 0.058380548 | V15: 6 | W15: =(P15-T15)*U15+V15*P15*0.5 -> 2997 | X15: =R15-W15 -> 68931 | Y15: =X15/R15-1 -> -0.041666667 | Z15: =IFERROR(X15/H15,"") -> 1.0356912 | AA15: 0.037547215 | AB15: 0.11607894 | AC15: =P15+AD15 -> 1049 | AD15: 50 | AE15: =IF(AA15>10%,0,IF(AA15>5%,P15*0.04,IF(AA15>0%,P15*0.075, P15*0.1))) -> 74.925 | AF15: =AC15*LEFT(I15,1)*12 -> 75528 | AG15: =AF15/R15-1 -> 0.05005005 | AH15: 0 | AI15: =AR15+(AN15/2) -> 0.063569161 | AJ15: 0 | AK15: 3 | AL15: =(AC15-AH15)*AJ15+AK15*AC15*0.5 -> 1573.5 | AM15: =AF15-AL15 -> 73954.5 | AN15: =AM15/AF15-1 -> -0.020833333 | AO15: =IFERROR(AM15/H15,"") -> 1.1111694 | AP15: =AM15-X15 -> 5023.5 | AQ15: =AM15/X15-1 -> 0.072877225 | AR15: =IFERROR(AA15+AQ15*0.5,"") -> 0.073985827 | BU15: =AP15/X15 -> 0.072877225 | BV15: 0.063 | BW15: =IF(AA15>19%,AA15-3.8%,AA15) -> 0.037547215
A16: 2606 | B16: REF | C16: DST | D16: GC-J257SQZW.AEPPLMT | G16: =IFERROR(VLOOKUP(D16,[3]전용!E:J,6,0),"") | H16: 51000 | I16: 5 | J16: Visit | K16: 24 | L16: 999 | M16: =L16*LEFT(I16,1)*12 -> 59940 | N16: 0.18738601 | P16: 999 | Q16: =L16-P16 -> 0 | R16: =P16*LEFT(I16,1)*12 -> 59940 | S16: =AA16-(Y16/2) -> 0.030548057 | V16: 3 | W16: =(P16-T16)*U16+V16*P16*0.5 -> 1498.5 | X16: =R16-W16 -> 58441.5 | Y16: =X16/R16-1 -> -0.025 | Z16: =IFERROR(X16/H16,"") -> 1.1459118 | AA16: 0.018048057 | AB16: 0.086625988 | AC16: =P16+AD16 -> 1049 | AD16: 50 | AE16: =IF(AA16>10%,0,IF(AA16>5%,P16*0.04,IF(AA16>0%,P16*0.075, P16*0.1))) -> 74.925 | AF16: =AC16*LEFT(I16,1)*12 -> 62940 | AG16: =AF16/R16-1 -> 0.05005005 | AH16: 0 | AI16: =AR16+(AN16/2) -> 0.030573082 | AJ16: 0 | AK16: 3 | AL16: =(AC16-AH16)*AJ16+AK16*AC16*0.5 -> 1573.5 | AM16: =AF16-AL16 -> 61366.5 | AN16: =AM16/AF16-1 -> -0.025 | AO16: =IFERROR(AM16/H16,"") -> 1.2032647 | AP16: =AM16-X16 -> 2925 | AQ16: =AM16/X16-1 -> 0.05005005 | AR16: =IFERROR(AA16+AQ16*0.5,"") -> 0.043073082 | BV16: 0.013747711 | BW16: =IF(AA16>19%,AA16-3.8%,AA16) -> 0.018048057
A17: 2606 | B17: REF | C17: DST | D17: GC-J257SQZW.AEPPLMT | G17: =IFERROR(VLOOKUP(D17,[3]전용!E:J,6,0),"") | H17: 51000 | I17: 6 | J17: Visit | K17: 24 | L17: 849 | M17: =L17*LEFT(I17,1)*12 -> 61128 | N17: 0.20178188 | P17: 849 | Q17: =L17-P17 -> 0 | R17: =P17*LEFT(I17,1)*12 -> 61128 | S17: =AA17-(Y17/2) -> 0.028464724 | V17: 3 | W17: =(P17-T17)*U17+V17*P17*0.5 -> 1273.5 | X17: =R17-W17 -> 59854.5 | Y17: =X17/R17-1 -> -0.020833333 | Z17: =IFERROR(X17/H17,"") -> 1.1736176 | AA17: 0.018048057 | AB17: 0.086625988 | AC17: =P17+AD17 -> 899 | AD17: 50 | AE17: =IF(AA17>10%,0,IF(AA17>5%,P17*0.04,IF(AA17>0%,P17*0.075, P17*0.1))) -> 63.675 | AF17: =AC17*LEFT(I17,1)*12 -> 64728 | AG17: =AF17/R17-1 -> 0.058892815 | AH17: 0 | AI17: =AR17+(AN17/2) -> 0.037077798 | AJ17: 0 | AK17: 3 | AL17: =(AC17-AH17)*AJ17+AK17*AC17*0.5 -> 1348.5 | AM17: =AF17-AL17 -> 63379.5 | AN17: =AM17/AF17-1 -> -0.020833333 | AO17: =IFERROR(AM17/H17,"") -> 1.2427353 | AP17: =AM17-X17 -> 3525 | AQ17: =AM17/X17-1 -> 0.058892815 | AR17: =IFERROR(AA17+AQ17*0.5,"") -> 0.047494464 | BV17: 0.013747711 | BW17: =IF(AA17>19%,AA17-3.8%,AA17) -> 0.018048057
A18: 2606 | B18: REF | C18: OBS Exclusive | D18: GV-B25FFGDB.ABMPLMT | G18: =IFERROR(VLOOKUP(D18,[3]전용!E:J,6,0),"") | H18: 44333.333 | I18: 5 | J18: Visit | K18: 24 | L18: 849 | M18: =L18*LEFT(I18,1)*12 -> 50940 | N18: 0.15 | P18: 849 | Q18: =L18-P18 -> 0 | R18: =P18*LEFT(I18,1)*12 -> 50940 | S18: =AA18-(Y18/2) -> 0.049556824 | V18: 12 | W18: =(P18-T18)*U18+V18*P18*0.5 -> 5094 | X18: =R18-W18 -> 45846 | Y18: =X18/R18-1 -> -0.1 | Z18: =IFERROR(X18/H18,"") -> 1.0341203 | AA18: -0.00044317629 | AB18: -0.0034577876 | AC18: 749 | AD18: =AC18-P18 -> -100 | AE18: =IF(AA18>10%,0,IF(AA18>5%,P18*0.04,IF(AA18>0%,P18*0.075, P18*0.1))) -> 84.9 | AF18: =AC18*LEFT(I18,1)*12 -> 44940 | AG18: =AF18/R18-1 -> -0.11778563 | AH18: 0 | AI18: 0.162 | AJ18: 0 | AK18: 0 | AL18: =(AC18-AH18)*AJ18+AK18*AC18*0.5 -> 0 | AM18: =AF18-AL18 -> 44940 | AN18: =AM18/AF18-1 -> 0 | AO18: =IFERROR(AM18/H18,"") -> 1.0136842 | AP18: =AM18-X18 -> -906 | AQ18: =AM18/X18-1 -> -0.019761811 | AR18: =IFERROR(AA18-AG18*0.5,"")+5% -> 0.10844964 | BV18: 0.02 | BW18: =IF(AA18>19%,AA18-3.8%,AA18) -> -0.00044317629
A19: 2606 | B19: REF | C19: OBS Exclusive | D19: GV-B25FFGDB.ABMPLMT | G19: =IFERROR(VLOOKUP(D19,[3]전용!E:J,6,0),"") | H19: 44333.333 | I19: 6 | J19: Visit | K19: 24 | L19: 699 | M19: =L19*LEFT(I19,1)*12 -> 50328 | N19: 0.15 | P19: 699 | Q19: =L19-P19 -> 0 | R19: =P19*LEFT(I19,1)*12 -> 50328 | S19: =AA19-(Y19/2) -> 0.04122349 | V19: 12 | W19: =(P19-T19)*U19+V19*P19*0.5 -> 4194 | X19: =R19-W19 -> 46134 | Y19: =X19/R19-1 -> -0.083333333 | Z19: =IFERROR(X19/H19,"") -> 1.0406165 | AA19: -0.00044317629 | AB19: -0.0034577876 | AC19: 649 | AD19: =AC19-P19 -> -50 | AE19: =IF(AA19>10%,0,IF(AA19>5%,P19*0.04,IF(AA19>0%,P19*0.075, P19*0.1))) -> 69.9 | AF19: =AC19*LEFT(I19,1)*12 -> 46728 | AG19: =AF19/R19-1 -> -0.071530758 | AH19: 0 | AI19: 0.169 | AJ19: 0 | AK19: 0 | AL19: =(AC19-AH19)*AJ19+AK19*AC19*0.5 -> 0 | AM19: =AF19-AL19 -> 46728 | AN19: =AM19/AF19-1 -> 0 | AO19: =IFERROR(AM19/H19,"") -> 1.054015 | AP19: =AM19-X19 -> 594 | AQ19: =AM19/X19-1 -> 0.012875536 | AR19: =IFERROR(AA19-AG19*0.5,"")+5% -> 0.085322203 | BV19: 0.02 | BW19: =IF(AA19>19%,AA19-3.8%,AA19) -> -0.00044317629
A20: 2606 | B20: REF | C20: DST | D20: GC-V22FFQMB.AEPPLMT | G20: =IFERROR(VLOOKUP(D20,[3]전용!E:J,6,0),"") | H20: 51000 | I20: 5 | J20: Visit | K20: 24 | L20: 899 | M20: =L20*LEFT(I20,1)*12 -> 53940 | N20: 0.14146421 | P20: 899 | Q20: =L20-P20 -> 0 | R20: =P20*LEFT(I20,1)*12 -> 53940 | S20: =AA20-(Y20/2) -> 0.038275817 | V20: 6 | W20: =(P20-T20)*U20+V20*P20*0.5 -> 2697 | X20: =R20-W20 -> 51243 | Y20: =X20/R20-1 -> -0.05 | Z20: =IFERROR(X20/H20,"") -> 1.0047647 | AA20: 0.013275817 | AB20: 0.081203062 | AC20: =P20+AD20 -> 949 | AD20: 50 | AE20: =IF(AA20>10%,0,IF(AA20>5%,P20*0.04,IF(AA20>0%,P20*0.075, P20*0.1))) -> 67.425 | AF20: =AC20*LEFT(I20,1)*12 -> 56940 | AG20: =AF20/R20-1 -> 0.055617353 | AH20: 0 | AI20: =AR20+(AN20/2) -> 0.042474195 | AJ20: 0 | AK20: 3 | AL20: =(AC20-AH20)*AJ20+AK20*AC20*0.5 -> 1423.5 | AM20: =AF20-AL20 -> 55516.5 | AN20: =AM20/AF20-1 -> -0.025 | AO20: =IFERROR(AM20/H20,"") -> 1.0885588 | AP20: =AM20-X20 -> 4273.5 | AQ20: =AM20/X20-1 -> 0.083396757 | AR20: =IFERROR(AA20+AQ20*0.5,"") -> 0.054974195 | BV20: 0.0063999121 | BW20: =IF(AA20>19%,AA20-3.8%,AA20) -> 0.013275817
A21: 2606 | B21: REF | C21: DST | D21: GC-V22FFQMB.AEPPLMT | G21: =IFERROR(VLOOKUP(D21,[3]전용!E:J,6,0),"") | H21: 51000 | I21: 6 | J21: Visit | K21: 24 | L21: 749 | M21: =L21*LEFT(I21,1)*12 -> 53928 | N21: 0.16213639 | P21: 749 | Q21: =L21-P21 -> 0 | R21: =P21*LEFT(I21,1)*12 -> 53928 | S21: =AA21-(Y21/2) -> 0.03410915 | V21: 6 | W21: =(P21-T21)*U21+V21*P21*0.5 -> 2247 | X21: =R21-W21 -> 51681 | Y21: =X21/R21-1 -> -0.041666667 | Z21: =IFERROR(X21/H21,"") -> 1.0133529 | AA21: 0.013275817 | AB21: 0.081203062 | AC21: =P21+AD21 -> 799 | AD21: 50 | AE21: =IF(AA21>10%,0,IF(AA21>5%,P21*0.04,IF(AA21>0%,P21*0.075, P21*0.1))) -> 56.175 | AF21: =AC21*LEFT(I21,1)*12 -> 57528 | AG21: =AF21/R21-1 -> 0.066755674 | AH21: 0 | AI21: =AR21+(AN21/2) -> 0.047832157 | AJ21: 0 | AK21: 3 | AL21: =(AC21-AH21)*AJ21+AK21*AC21*0.5 -> 1198.5 | AM21: =AF21-AL21 -> 56329.5 | AN21: =AM21/AF21-1 -> -0.020833333 | AO21: =IFERROR(AM21/H21,"") -> 1.1045 | AP21: =AM21-X21 -> 4648.5 | AQ21: =AM21/X21-1 -> 0.089946015 | AR21: =IFERROR(AA21+AQ21*0.5,"") -> 0.058248824 | BV21: 0.0063999121 | BW21: =IF(AA21>19%,AA21-3.8%,AA21) -> 0.013275817
A22: 2606 | B22: REF | C22: OBS Exclusive | D22: GC-L257KQKW.AEPPLMT | G22: =IFERROR(VLOOKUP(D22,[3]전용!E:J,6,0),"") | H22: 45444.444 | I22: 5 | J22: Visit | K22: 24 | L22: 849 | M22: =L22*LEFT(I22,1)*12 -> 50940 | N22: 0.13491501 | P22: 849 | Q22: =L22-P22 -> 0 | R22: =P22*LEFT(I22,1)*12 -> 50940 | S22: =AA22-(Y22/2) -> -0.045902456 | V22: 3 | W22: =(P22-T22)*U22+V22*P22*0.5 -> 1273.5 | X22: =R22-W22 -> 49666.5 | Y22: =X22/R22-1 -> -0.025 | Z22: =IFERROR(X22/H22,"") -> 1.0929059 | AA22: -0.058402456 | AB22: 0.18901258 | AC22: 749 | AD22: =AC22-P22 -> -100 | AE22: =IF(AA22>10%,0,IF(AA22>5%,P22*0.04,IF(AA22>0%,P22*0.075, P22*0.1))) -> 84.9 | AF22: =AC22*LEFT(I22,1)*12 -> 44940 | AG22: =AF22/R22-1 -> -0.11778563 | AH22: 0 | AI22: 0.169 | AJ22: 0 | AK22: 3 | AL22: =(AC22-AH22)*AJ22+AK22*AC22*0.5 -> 1123.5 | AM22: =AF22-AL22 -> 43816.5 | AN22: =AM22/AF22-1 -> -0.025 | AO22: =IFERROR(AM22/H22,"") -> 0.96417726 | AP22: =AM22-X22 -> -5850 | AQ22: =AM22/X22-1 -> -0.11778563 | AR22: =IFERROR(AA22-AG22*0.5,"")+5% -> 0.05049036 | BV22: 0.06 | BW22: =IF(AA22>19%,AA22-3.8%,AA22) -> -0.058402456
A23: 2606 | B23: REF | C23: OBS Exclusive | D23: GC-L257KQKW.AEPPLMT | G23: =IFERROR(VLOOKUP(D23,[3]전용!E:J,6,0),"") | H23: 45444.444 | I23: 6 | J23: Visit | K23: 24 | L23: 749 | M23: =L23*LEFT(I23,1)*12 -> 53928 | N23: 0.19072175 | P23: 749 | Q23: =L23-P23 -> 0 | R23: =P23*LEFT(I23,1)*12 -> 53928 | S23: =AA23-(Y23/2) -> -0.047985789 | V23: 3 | W23: =(P23-T23)*U23+V23*P23*0.5 -> 1123.5 | X23: =R23-W23 -> 52804.5 | Y23: =X23/R23-1 -> -0.020833333 | Z23: =IFERROR(X23/H23,"") -> 1.1619572 | AA23: -0.058402456 | AB23: 0.18901258 | AC23: 649 | AD23: =AC23-P23 -> -100 | AE23: =IF(AA23>10%,0,IF(AA23>5%,P23*0.04,IF(AA23>0%,P23*0.075, P23*0.1))) -> 74.9 | AF23: =AC23*LEFT(I23,1)*12 -> 46728 | AG23: =AF23/R23-1 -> -0.13351135 | AH23: 0 | AI23: 0.244 | AJ23: 0 | AK23: 3 | AL23: =(AC23-AH23)*AJ23+AK23*AC23*0.5 -> 973.5 | AM23: =AF23-AL23 -> 45754.5 | AN23: =AM23/AF23-1 -> -0.020833333 | AO23: =IFERROR(AM23/H23,"") -> 1.0068227 | AP23: =AM23-X23 -> -7050 | AQ23: =AM23/X23-1 -> -0.13351135 | AR23: =IFERROR(AA23-AG23*0.5,"")+5% -> 0.058353219 | BV23: 0.06 | BW23: =IF(AA23>19%,AA23-3.8%,AA23) -> -0.058402456
A24: 2606 | B24: REF | C24: DST | D24: GN-V389FQEF.AEPPLMT | G24: =IFERROR(VLOOKUP(D24,[3]전용!E:J,6,0),"") | H24: 27766.667 | I24: 5 | J24: Visit | K24: 24 | L24: 649 | M24: =L24*LEFT(I24,1)*12 -> 38940 | N24: 0.22972636 | P24: 649 | Q24: =L24-P24 -> 0 | R24: =P24*LEFT(I24,1)*12 -> 38940 | S24: =AA24-(Y24/2) -> 0.14611356 | V24: 3 | W24: =(P24-T24)*U24+V24*P24*0.5 -> 973.5 | X24: =R24-W24 -> 37966.5 | Y24: =X24/R24-1 -> -0.025 | Z24: =IFERROR(X24/H24,"") -> 1.3673409 | AA24: 0.13361356 | AB24: 0.016592189 | AC24: =P24+AD24 -> 649 | AE24: =IF(AA24>10%,0,IF(AA24>5%,P24*0.04,IF(AA24>0%,P24*0.075, P24*0.1))) -> 0 | AF24: =AC24*LEFT(I24,1)*12 -> 38940 | AG24: =AF24/R24-1 -> 0 | AH24: 0 | AI24: =AR24+(AN24/2) -> 0.12111356 | AJ24: 0 | AK24: 3 | AL24: =(AC24-AH24)*AJ24+AK24*AC24*0.5 -> 973.5 | AM24: =AF24-AL24 -> 37966.5 | AN24: =AM24/AF24-1 -> -0.025 | AO24: =IFERROR(AM24/H24,"") -> 1.3673409 | AP24: =AM24-X24 -> 0 | AQ24: =AM24/X24-1 -> 0 | AR24: =IFERROR(AA24+AQ24*0.5,"") -> 0.13361356 | BV24: 0.13361356 | BW24: =IF(AA24>19%,AA24-3.8%,AA24) -> 0.13361356
A25: 2606 | B25: REF | C25: DST | D25: GN-V389FQEF.AEPPLMT | G25: =IFERROR(VLOOKUP(D25,[3]전용!E:J,6,0),"") | H25: 27766.667 | I25: 6 | J25: Visit | K25: 24 | L25: 549 | M25: =L25*LEFT(I25,1)*12 -> 39528 | N25: 0.21962535 | P25: 549 | Q25: =L25-P25 -> 0 | R25: =P25*LEFT(I25,1)*12 -> 39528 | S25: =AA25-(Y25/2) -> 0.14403022 | V25: 3 | W25: =(P25-T25)*U25+V25*P25*0.5 -> 823.5 | X25: =R25-W25 -> 38704.5 | Y25: =X25/R25-1 -> -0.020833333 | Z25: =IFERROR(X25/H25,"") -> 1.3939196 | AA25: 0.13361356 | AB25: 0.016592189 | AC25: =P25+AD25 -> 549 | AE25: =IF(AA25>10%,0,IF(AA25>5%,P25*0.04,IF(AA25>0%,P25*0.075, P25*0.1))) -> 0 | AF25: =AC25*LEFT(I25,1)*12 -> 39528 | AG25: =AF25/R25-1 -> 0 | AH25: 0 | AI25: =AR25+(AN25/2) -> 0.12319689 | AJ25: 0 | AK25: 3 | AL25: =(AC25-AH25)*AJ25+AK25*AC25*0.5 -> 823.5 | AM25: =AF25-AL25 -> 38704.5 | AN25: =AM25/AF25-1 -> -0.020833333 | AO25: =IFERROR(AM25/H25,"") -> 1.3939196 | AP25: =AM25-X25 -> 0 | AQ25: =AM25/X25-1 -> 0 | AR25: =IFERROR(AA25+AQ25*0.5,"") -> 0.13361356 | BV25: 0.13361356 | BW25: =IF(AA25>19%,AA25-3.8%,AA25) -> 0.13361356
A26: 2606 | B26: REF | C26: OBS Exclusive | D26: GC-B257SQYL.AMCPLMT | G26: =IFERROR(VLOOKUP(D26,[3]전용!E:J,6,0),"") | H26: 37666.667 | I26: 5 | J26: Visit | K26: 24 | L26: 599 | M26: =L26*LEFT(I26,1)*12 -> 35940 | N26: 0.15 | P26: 599 | Q26: =L26-P26 -> 0 | R26: =P26*LEFT(I26,1)*12 -> 35940 | S26: =AA26-(Y26/2) -> -0.052590504 | V26: 0 | W26: =(P26-T26)*U26+V26*P26*0.5 -> 0 | X26: =R26-W26 -> 35940 | Y26: =X26/R26-1 -> 0 | Z26: =IFERROR(X26/H26,"") -> 0.95415929 | AA26: -0.052590504 | AB26: 0.074784115 | AC26: 499 | AD26: =AC26-P26 -> -100 | AE26: =IF(AA26>10%,0,IF(AA26>5%,P26*0.04,IF(AA26>0%,P26*0.075, P26*0.1))) -> 59.9 | AF26: =AC26*LEFT(I26,1)*12 -> 29940 | AG26: =AF26/R26-1 -> -0.16694491 | AH26: 0 | AI26: 0.13 | AJ26: 0 | AK26: 0 | AL26: =(AC26-AH26)*AJ26+AK26*AC26*0.5 -> 0 | AM26: =AF26-AL26 -> 29940 | AN26: =AM26/AF26-1 -> 0 | AO26: =IFERROR(AM26/H26,"") -> 0.79486726 | AP26: =AM26-X26 -> -6000 | AQ26: =AM26/X26-1 -> -0.16694491 | AR26: =IFERROR(AA26-AG26*0.5,"")+5% -> 0.08088195 | BV26: 0.03 | BW26: =IF(AA26>19%,AA26-3.8%,AA26) -> -0.052590504
A27: 2606 | B27: REF | C27: OBS Exclusive | D27: GC-B257SQYL.AMCPLMT | G27: =IFERROR(VLOOKUP(D27,[3]전용!E:J,6,0),"") | H27: 37666.667 | I27: 6 | J27: Visit | K27: 24 | L27: 499 | M27: =L27*LEFT(I27,1)*12 -> 35928 | N27: 0.15 | P27: 499 | Q27: =L27-P27 -> 0 | R27: =P27*LEFT(I27,1)*12 -> 35928 | S27: =AA27-(Y27/2) -> -0.052590504 | V27: 0 | W27: =(P27-T27)*U27+V27*P27*0.5 -> 0 | X27: =R27-W27 -> 35928 | Y27: =X27/R27-1 -> 0 | Z27: =IFERROR(X27/H27,"") -> 0.95384071 | AA27: -0.052590504 | AB27: 0.074784115 | AC27: 449 | AD27: =AC27-P27 -> -50 | AE27: =IF(AA27>10%,0,IF(AA27>5%,P27*0.04,IF(AA27>0%,P27*0.075, P27*0.1))) -> 49.9 | AF27: =AC27*LEFT(I27,1)*12 -> 32328 | AG27: =AF27/R27-1 -> -0.1002004 | AH27: 0 | AI27: 0.097 | AJ27: 0 | AK27: 0 | AL27: =(AC27-AH27)*AJ27+AK27*AC27*0.5 -> 0 | AM27: =AF27-AL27 -> 32328 | AN27: =AM27/AF27-1 -> 0 | AO27: =IFERROR(AM27/H27,"") -> 0.85826549 | AP27: =AM27-X27 -> -3600 | AQ27: =AM27/X27-1 -> -0.1002004 | AR27: =IFERROR(AA27-AG27*0.5,"")+5% -> 0.047509697 | BV27: 0.03 | BW27: =IF(AA27>19%,AA27-3.8%,AA27) -> -0.052590504
A28: 2606 | B28: REF | C28: EOL after inventory depletion | D28: GC-L257SFZW.APYPLMT | G28: =IFERROR(VLOOKUP(D28,[3]전용!E:J,6,0),"") | H28: 39888.889 | I28: 5 | J28: Visit | K28: 24 | L28: 849 | M28: =L28*LEFT(I28,1)*12 -> 50940 | N28: 0.15 | P28: 849 | Q28: =L28-P28 -> 0 | R28: =P28*LEFT(I28,1)*12 -> 50940 | S28: =AA28-(Y28/2) -> 0.10151141 | V28: 3 | W28: =(P28-T28)*U28+V28*P28*0.5 -> 1273.5 | X28: =R28-W28 -> 49666.5 | Y28: =X28/R28-1 -> -0.025 | Z28: =IFERROR(X28/H28,"") -> 1.2451212 | AA28: 0.089011414 | AB28: 0.098248976 | AC28: =P28+AD28 -> 849 | AE28: =IF(AA28>10%,0,IF(AA28>5%,P28*0.04,IF(AA28>0%,P28*0.075, P28*0.1))) -> 33.96 | AF28: =AC28*LEFT(I28,1)*12 -> 50940 | AG28: =AF28/R28-1 -> 0 | AH28: 0 | AI28: =AR28+(AN28/2) -> 0.076511414 | AJ28: 0 | AK28: 3 | AL28: =(AC28-AH28)*AJ28+AK28*AC28*0.5 -> 1273.5 | AM28: =AF28-AL28 -> 49666.5 | AN28: =AM28/AF28-1 -> -0.025 | AO28: =IFERROR(AM28/H28,"") -> 1.2451212 | AP28: =AM28-X28 -> 0 | AQ28: =AM28/X28-1 -> 0 | AR28: =IFERROR(AA28+AQ28*0.5,"") -> 0.089011414 | BV28: 0.091559924 | BW28: =IF(AA28>19%,AA28-3.8%,AA28) -> 0.089011414
A29: 2606 | B29: REF | C29: EOL after inventory depletion | D29: GC-L257SFZW.APYPLMT | G29: =IFERROR(VLOOKUP(D29,[3]전용!E:J,6,0),"") | H29: 39888.889 | I29: 6 | J29: Visit | K29: 24 | L29: 749 | M29: =L29*LEFT(I29,1)*12 -> 53928 | N29: 0.15 | P29: 749 | Q29: =L29-P29 -> 0 | R29: =P29*LEFT(I29,1)*12 -> 53928 | S29: =AA29-(Y29/2) -> 0.099428081 | V29: 3 | W29: =(P29-T29)*U29+V29*P29*0.5 -> 1123.5 | X29: =R29-W29 -> 52804.5 | Y29: =X29/R29-1 -> -0.020833333 | Z29: =IFERROR(X29/H29,"") -> 1.3237897 | AA29: 0.089011414 | AB29: 0.098248976 | AC29: =P29+AD29 -> 749 | AE29: =IF(AA29>10%,0,IF(AA29>5%,P29*0.04,IF(AA29>0%,P29*0.075, P29*0.1))) -> 29.96 | AF29: =AC29*LEFT(I29,1)*12 -> 53928 | AG29: =AF29/R29-1 -> 0 | AH29: 0 | AI29: =AR29+(AN29/2) -> 0.078594748 | AJ29: 0 | AK29: 3 | AL29: =(AC29-AH29)*AJ29+AK29*AC29*0.5 -> 1123.5 | AM29: =AF29-AL29 -> 52804.5 | AN29: =AM29/AF29-1 -> -0.020833333 | AO29: =IFERROR(AM29/H29,"") -> 1.3237897 | AP29: =AM29-X29 -> 0 | AQ29: =AM29/X29-1 -> 0 | AR29: =IFERROR(AA29+AQ29*0.5,"") -> 0.089011414 | BV29: 0.091559924 | BW29: =IF(AA29>19%,AA29-3.8%,AA29) -> 0.089011414
A30: 2606 | B30: REF | C30: DST | D30: GN-F452PQAK.AEPPLMT | G30: =IFERROR(VLOOKUP(D30,[3]전용!E:J,6,0),"") | H30: 24433.333 | I30: 5 | J30: Visit | K30: 24 | L30: 549 | M30: =L30*LEFT(I30,1)*12 -> 32940 | N30: 0.23679272 | P30: 549 | Q30: =L30-P30 -> 0 | R30: =P30*LEFT(I30,1)*12 -> 32940 | S30: =AA30-(Y30/2) -> 0.01573178 | V30: 3 | W30: =(P30-T30)*U30+V30*P30*0.5 -> 823.5 | X30: =R30-W30 -> 32116.5 | Y30: =X30/R30-1 -> -0.025 | Z30: =IFERROR(X30/H30,"") -> 1.3144543 | AA30: 0.0032317803 | AB30: 0.14451313 | AC30: =P30+AD30 -> 599 | AD30: 50 | AE30: =IF(AA30>10%,0,IF(AA30>5%,P30*0.04,IF(AA30>0%,P30*0.075, P30*0.1))) -> 41.175 | AF30: =AC30*LEFT(I30,1)*12 -> 35940 | AG30: =AF30/R30-1 -> 0.091074681 | AH30: 0 | AI30: =AR30+(AN30/2) -> 0.036269121 | AJ30: 0 | AK30: 3 | AL30: =(AC30-AH30)*AJ30+AK30*AC30*0.5 -> 898.5 | AM30: =AF30-AL30 -> 35041.5 | AN30: =AM30/AF30-1 -> -0.025 | AO30: =IFERROR(AM30/H30,"") -> 1.4341678 | AP30: =AM30-X30 -> 2925 | AQ30: =AM30/X30-1 -> 0.091074681 | AR30: =IFERROR(AA30+AQ30*0.5,"") -> 0.048769121 | BV30: 0.02 | BW30: =IF(AA30>19%,AA30-3.8%,AA30) -> 0.0032317803
A31: 2606 | B31: REF | C31: DST | D31: GN-F452PQAK.AEPPLMT | G31: =IFERROR(VLOOKUP(D31,[3]전용!E:J,6,0),"") | H31: 24433.333 | I31: 6 | J31: Visit | K31: 24 | L31: 449 | M31: =L31*LEFT(I31,1)*12 -> 32328 | N31: 0.18308536 | P31: 449 | Q31: =L31-P31 -> 0 | R31: =P31*LEFT(I31,1)*12 -> 32328 | S31: =AA31-(Y31/2) -> 0.013648447 | V31: 3 | W31: =(P31-T31)*U31+V31*P31*0.5 -> 673.5 | X31: =R31-W31 -> 31654.5 | Y31: =X31/R31-1 -> -0.020833333 | Z31: =IFERROR(X31/H31,"") -> 1.2955457 | AA31: 0.0032317803 | AB31: 0.14451313 | AC31: =P31+AD31 -> 499 | AD31: 50 | AE31: =IF(AA31>10%,0,IF(AA31>5%,P31*0.04,IF(AA31>0%,P31*0.075, P31*0.1))) -> 33.675 | AF31: =AC31*LEFT(I31,1)*12 -> 35928 | AG31: =AF31/R31-1 -> 0.11135857 | AH31: 0 | AI31: =AR31+(AN31/2) -> 0.048494401 | AJ31: 0 | AK31: 3 | AL31: =(AC31-AH31)*AJ31+AK31*AC31*0.5 -> 748.5 | AM31: =AF31-AL31 -> 35179.5 | AN31: =AM31/AF31-1 -> -0.020833333 | AO31: =IFERROR(AM31/H31,"") -> 1.4398158 | AP31: =AM31-X31 -> 3525 | AQ31: =AM31/X31-1 -> 0.11135857 | AR31: =IFERROR(AA31+AQ31*0.5,"") -> 0.058911068 | BV31: 0.02 | BW31: =IF(AA31>19%,AA31-3.8%,AA31) -> 0.0032317803
A32: 2606 | B32: REF | C32: OBS Exclusive | D32: GN-F392PQAK.AEPPLM1 | G32: =IFERROR(VLOOKUP(D32,[3]전용!E:J,6,0),"") | H32: 22211.111 | I32: 5 | J32: Visit | K32: 24 | L32: 499 | M32: =L32*LEFT(I32,1)*12 -> 29940 | N32: 0.2058703 | P32: 499 | Q32: =L32-P32 -> 0 | R32: =P32*LEFT(I32,1)*12 -> 29940 | S32: =AA32-(Y32/2) -> -0.015851221 | V32: 0 | W32: =(P32-T32)*U32+V32*P32*0.5 -> 0 | X32: =R32-W32 -> 29940 | Y32: =X32/R32-1 -> 0 | Z32: =IFERROR(X32/H32,"") -> 1.347974 | AA32: -0.015851221 | AB32: 0.052807378 | AC32: 399 | AD32: =AC32-P32 -> -100 | AE32: =IF(AA32>10%,0,IF(AA32>5%,P32*0.04,IF(AA32>0%,P32*0.075, P32*0.1))) -> 49.9 | AF32: =AC32*LEFT(I32,1)*12 -> 23940 | AG32: =AF32/R32-1 -> -0.2004008 | AH32: 0 | AI32: 0.193 | AJ32: 0 | AK32: 3 | AL32: =(AC32-AH32)*AJ32+AK32*AC32*0.5 -> 598.5 | AM32: =AF32-AL32 -> 23341.5 | AN32: =AM32/AF32-1 -> -0.025 | AO32: =IFERROR(AM32/H32,"") -> 1.0508929 | AP32: =AM32-X32 -> -6598.5 | AQ32: =AM32/X32-1 -> -0.22039078 | AR32: =IFERROR(AA32-AG32*0.5,"")+5% -> 0.13434918 | BV32: 0.02 | BW32: =IF(AA32>19%,AA32-3.8%,AA32) -> -0.015851221
A33: 2606 | B33: REF | C33: OBS Exclusive | D33: GN-F392PQAK.AEPPLM1 | G33: =IFERROR(VLOOKUP(D33,[3]전용!E:J,6,0),"") | H33: 22211.111 | I33: 6 | J33: Visit | K33: 24 | L33: 399 | M33: =L33*LEFT(I33,1)*12 -> 28728 | N33: 0.14696011 | P33: 399 | Q33: =L33-P33 -> 0 | R33: =P33*LEFT(I33,1)*12 -> 28728 | S33: =AA33-(Y33/2) -> -0.015851221 | V33: 0 | W33: =(P33-T33)*U33+V33*P33*0.5 -> 0 | X33: =R33-W33 -> 28728 | Y33: =X33/R33-1 -> 0 | Z33: =IFERROR(X33/H33,"") -> 1.2934067 | AA33: -0.015851221 | AB33: 0.052807378 | AC33: 349 | AD33: =AC33-P33 -> -50 | AE33: =IF(AA33>10%,0,IF(AA33>5%,P33*0.04,IF(AA33>0%,P33*0.075, P33*0.1))) -> 39.9 | AF33: =AC33*LEFT(I33,1)*12 -> 25128 | AG33: =AF33/R33-1 -> -0.12531328 | AH33: 0 | AI33: 0.13 | AJ33: 0 | AK33: 3 | AL33: =(AC33-AH33)*AJ33+AK33*AC33*0.5 -> 523.5 | AM33: =AF33-AL33 -> 24604.5 | AN33: =AM33/AF33-1 -> -0.020833333 | AO33: =IFERROR(AM33/H33,"") -> 1.1077564 | AP33: =AM33-X33 -> -4123.5 | AQ33: =AM33/X33-1 -> -0.14353592 | AR33: =IFERROR(AA33-AG33*0.5,"")+5% -> 0.096805421 | BV33: 0.02 | BW33: =IF(AA33>19%,AA33-3.8%,AA33) -> -0.015851221
A34: 2606 | B34: Dishwasher | C34: DST | D34: DFC335HM.ABMPETH | E34: DFC335HM.ABMPETH | G34: =IFERROR(VLOOKUP(D34,[3]전용!E:J,6,0),"") | H34: 38777.778 | I34: 5 | J34: Visit | K34: 12 | L34: 899 | M34: =L34*LEFT(I34,1)*12 -> 53940 | N34: 0.21724138 | P34: 899 | Q34: =L34-P34 -> 0 | R34: =P34*LEFT(I34,1)*12 -> 53940 | S34: =AA34-(Y34/2) -> 0.38496718 | V34: 12 | W34: =(P34-T34)*U34+V34*P34*0.5 -> 5394 | X34: =R34-W34 -> 48546 | Y34: =X34/R34-1 -> -0.1 | Z34: =IFERROR(X34/H34,"") -> 1.2519026 | AA34: 0.33496718 | AB34: 0.072829246 | AC34: =P34+AD34 -> 899 | AE34: =IF(AA34>10%,0,IF(AA34>5%,P34*0.04,IF(AA34>0%,P34*0.075, P34*0.1))) -> 0 | AF34: =AC34*LEFT(I34,1)*12 -> 53940 | AG34: =AF34/R34-1 -> 0 | AH34: 0 | AI34: =AR34+(AN34/2) -> 0.28496718 | AJ34: 0 | AK34: 12 | AL34: =(AC34-AH34)*AJ34+AK34*AC34*0.5 -> 5394 | AM34: =AF34-AL34 -> 48546 | AN34: =AM34/AF34-1 -> -0.1 | AO34: =IFERROR(AM34/H34,"") -> 1.2519026 | AP34: =AM34-X34 -> 0 | AQ34: =AM34/X34-1 -> 0 | AR34: =IFERROR(AA34+AQ34*0.5,"") -> 0.33496718 | BV34: 0.23433964 | BW34: =IF(AA34>19%,AA34-3.8%,AA34) -> 0.29696718
A35: 2606 | B35: Dishwasher | C35: DST | D35: DFC335HM.ABMPETH | E35: DFC335HM.ABMPETH | G35: =IFERROR(VLOOKUP(D35,[3]전용!E:J,6,0),"") | H35: 38777.778 | I35: 5 | J35: Self | K35: 12 | L35: 849 | M35: =L35*LEFT(I35,1)*12 -> 50940 | N35: 0.21724138 | P35: 849 | Q35: =L35-P35 -> 0 | R35: =P35*LEFT(I35,1)*12 -> 50940 | S35: =AA35-(Y35/2) -> 0.38496718 | V35: 12 | W35: =(P35-T35)*U35+V35*P35*0.5 -> 5094 | X35: =R35-W35 -> 45846 | Y35: =X35/R35-1 -> -0.1 | Z35: =IFERROR(X35/H35,"") -> 1.1822751 | AA35: 0.33496718 | AB35: 0.072829246 | AC35: =P35+AD35 -> 849 | AE35: =IF(AA35>10%,0,IF(AA35>5%,P35*0.04,IF(AA35>0%,P35*0.075, P35*0.1))) -> 0 | AF35: =AC35*LEFT(I35,1)*12 -> 50940 | AG35: =AF35/R35-1 -> 0 | AH35: 0 | AI35: =AR35+(AN35/2) -> 0.28496718 | AJ35: 0 | AK35: 12 | AL35: =(AC35-AH35)*AJ35+AK35*AC35*0.5 -> 5094 | AM35: =AF35-AL35 -> 45846 | AN35: =AM35/AF35-1 -> -0.1 | AO35: =IFERROR(AM35/H35,"") -> 1.1822751 | AP35: =AM35-X35 -> 0 | AQ35: =AM35/X35-1 -> 0 | AR35: =IFERROR(AA35+AQ35*0.5,"") -> 0.33496718 | BV35: 0.23433964 | BW35: =IF(AA35>19%,AA35-3.8%,AA35) -> 0.29696718
A36: 2606 | B36: Dishwasher | C36: DST | D36: DFC335HM.ABMPETH | E36: DFC335HM.ABMPETH | G36: =IFERROR(VLOOKUP(D36,[3]전용!E:J,6,0),"") | H36: 38777.778 | I36: 6 | J36: Visit | K36: 12 | L36: 799 | M36: =L36*LEFT(I36,1)*12 -> 57528 | N36: 0.2531499 | P36: 799 | Q36: =L36-P36 -> 0 | R36: =P36*LEFT(I36,1)*12 -> 57528 | S36: =AA36-(Y36/2) -> 0.37663384 | V36: 12 | W36: =(P36-T36)*U36+V36*P36*0.5 -> 4794 | X36: =R36-W36 -> 52734 | Y36: =X36/R36-1 -> -0.083333333 | Z36: =IFERROR(X36/H36,"") -> 1.3599026 | AA36: 0.33496718 | AB36: 0.072829246 | AC36: =P36+AD36 -> 799 | AE36: =IF(AA36>10%,0,IF(AA36>5%,P36*0.04,IF(AA36>0%,P36*0.075, P36*0.1))) -> 0 | AF36: =AC36*LEFT(I36,1)*12 -> 57528 | AG36: =AF36/R36-1 -> 0 | AH36: 0 | AI36: =AR36+(AN36/2) -> 0.29330051 | AJ36: 0 | AK36: 12 | AL36: =(AC36-AH36)*AJ36+AK36*AC36*0.5 -> 4794 | AM36: =AF36-AL36 -> 52734 | AN36: =AM36/AF36-1 -> -0.083333333 | AO36: =IFERROR(AM36/H36,"") -> 1.3599026 | AP36: =AM36-X36 -> 0 | AQ36: =AM36/X36-1 -> 0 | AR36: =IFERROR(AA36+AQ36*0.5,"") -> 0.33496718 | BV36: 0.23433964 | BW36: =IF(AA36>19%,AA36-3.8%,AA36) -> 0.29696718
A37: 2606 | B37: Dishwasher | C37: DST | D37: DFC335HM.ABMPETH | E37: DFC335HM.ABMPETH | G37: =IFERROR(VLOOKUP(D37,[3]전용!E:J,6,0),"") | H37: 38777.778 | I37: 6 | J37: Self | K37: 12 | L37: 749 | M37: =L37*LEFT(I37,1)*12 -> 53928 | N37: 0.26307179 | P37: 749 | Q37: =L37-P37 -> 0 | R37: =P37*LEFT(I37,1)*12 -> 53928 | S37: =AA37-(Y37/2) -> 0.37663384 | V37: 12 | W37: =(P37-T37)*U37+V37*P37*0.5 -> 4494 | X37: =R37-W37 -> 49434 | Y37: =X37/R37-1 -> -0.083333333 | Z37: =IFERROR(X37/H37,"") -> 1.2748023 | AA37: 0.33496718 | AB37: 0.072829246 | AC37: =P37+AD37 -> 749 | AE37: =IF(AA37>10%,0,IF(AA37>5%,P37*0.04,IF(AA37>0%,P37*0.075, P37*0.1))) -> 0 | AF37: =AC37*LEFT(I37,1)*12 -> 53928 | AG37: =AF37/R37-1 -> 0 | AH37: 0 | AI37: =AR37+(AN37/2) -> 0.29330051 | AJ37: 0 | AK37: 12 | AL37: =(AC37-AH37)*AJ37+AK37*AC37*0.5 -> 4494 | AM37: =AF37-AL37 -> 49434 | AN37: =AM37/AF37-1 -> -0.083333333 | AO37: =IFERROR(AM37/H37,"") -> 1.2748023 | AP37: =AM37-X37 -> 0 | AQ37: =AM37/X37-1 -> 0 | AR37: =IFERROR(AA37+AQ37*0.5,"") -> 0.33496718 | BV37: 0.23433964 | BW37: =IF(AA37>19%,AA37-3.8%,AA37) -> 0.29696718
A38: 2606 | B38: Dishwasher | C38: EOL after inventory depletion | D38: DFC533FV.APYPETH | E38: DFC533FV.APYPETH | G38: =IFERROR(VLOOKUP(D38,[3]전용!E:J,6,0),"") | H38: 28777.778 | I38: 5 | J38: Visit | K38: 12 | L38: 749 | M38: =L38*LEFT(I38,1)*12 -> 44940 | N38: 0.15 | P38: 749 | Q38: =L38-P38 -> 0 | R38: =P38*LEFT(I38,1)*12 -> 44940 | S38: =AA38-(Y38/2) -> 0.44748928 | V38: 12 | W38: =(P38-T38)*U38+V38*P38*0.5 -> 4494 | X38: =R38-W38 -> 40446 | Y38: =X38/R38-1 -> -0.1 | Z38: =IFERROR(X38/H38,"") -> 1.4054595 | AA38: 0.39748928 | AB38: 0.0036542546 | AC38: =P38+AD38 -> 749 | AE38: =IF(AA38>10%,0,IF(AA38>5%,P38*0.04,IF(AA38>0%,P38*0.075, P38*0.1))) -> 0 | AF38: =AC38*LEFT(I38,1)*12 -> 44940 | AG38: =AF38/R38-1 -> 0 | AH38: 0 | AI38: =AR38+(AN38/2) -> 0.45304484 | AJ38: 0 | AK38: 0 | AL38: =(AC38-AH38)*AJ38+AK38*AC38*0.5 -> 0 | AM38: =AF38-AL38 -> 44940 | AN38: =AM38/AF38-1 -> 0 | AO38: =IFERROR(AM38/H38,"") -> 1.5616216 | AP38: =AM38-X38 -> 4494 | AQ38: =AM38/X38-1 -> 0.11111111 | AR38: =IFERROR(AA38+AQ38*0.5,"") -> 0.45304484 | BV38: 0.29748928 | BW38: =IF(AA38>19%,AA38-3.8%,AA38) -> 0.35948928
A39: 2606 | B39: Dishwasher | C39: EOL after inventory depletion | D39: DFC533FV.APYPETH | E39: DFC533FV.APYPETH | G39: =IFERROR(VLOOKUP(D39,[3]전용!E:J,6,0),"") | H39: 28777.778 | I39: 5 | J39: Self | K39: 12 | L39: 699 | M39: =L39*LEFT(I39,1)*12 -> 41940 | N39: 0.15 | P39: 699 | Q39: =L39-P39 -> 0 | R39: =P39*LEFT(I39,1)*12 -> 41940 | S39: =AA39-(Y39/2) -> 0.44748928 | V39: 12 | W39: =(P39-T39)*U39+V39*P39*0.5 -> 4194 | X39: =R39-W39 -> 37746 | Y39: =X39/R39-1 -> -0.1 | Z39: =IFERROR(X39/H39,"") -> 1.3116371 | AA39: 0.39748928 | AB39: 0.0036542546 | AC39: =P39+AD39 -> 699 | AE39: =IF(AA39>10%,0,IF(AA39>5%,P39*0.04,IF(AA39>0%,P39*0.075, P39*0.1))) -> 0 | AF39: =AC39*LEFT(I39,1)*12 -> 41940 | AG39: =AF39/R39-1 -> 0 | AH39: 0 | AI39: =AR39+(AN39/2) -> 0.45304484 | AJ39: 0 | AK39: 0 | AL39: =(AC39-AH39)*AJ39+AK39*AC39*0.5 -> 0 | AM39: =AF39-AL39 -> 41940 | AN39: =AM39/AF39-1 -> 0 | AO39: =IFERROR(AM39/H39,"") -> 1.4573745 | AP39: =AM39-X39 -> 4194 | AQ39: =AM39/X39-1 -> 0.11111111 | AR39: =IFERROR(AA39+AQ39*0.5,"") -> 0.45304484 | BV39: 0.29748928 | BW39: =IF(AA39>19%,AA39-3.8%,AA39) -> 0.35948928
A40: 2606 | B40: Dishwasher | C40: EOL after inventory depletion | D40: DFC533FV.APYPETH | E40: DFC533FV.APYPETH | G40: =IFERROR(VLOOKUP(D40,[3]전용!E:J,6,0),"") | H40: 28777.778 | I40: 6 | J40: Visit | K40: 12 | L40: 649 | M40: =L40*LEFT(I40,1)*12 -> 46728 | N40: 0.15 | P40: 649 | Q40: =L40-P40 -> 0 | R40: =P40*LEFT(I40,1)*12 -> 46728 | S40: =AA40-(Y40/2) -> 0.43915595 | V40: 12 | W40: =(P40-T40)*U40+V40*P40*0.5 -> 3894 | X40: =R40-W40 -> 42834 | Y40: =X40/R40-1 -> -0.083333333 | Z40: =IFERROR(X40/H40,"") -> 1.4884402 | AA40: 0.39748928 | AB40: 0.0036542546 | AC40: =P40+AD40 -> 649 | AE40: =IF(AA40>10%,0,IF(AA40>5%,P40*0.04,IF(AA40>0%,P40*0.075, P40*0.1))) -> 0 | AF40: =AC40*LEFT(I40,1)*12 -> 46728 | AG40: =AF40/R40-1 -> 0 | AH40: 0 | AI40: =AR40+(AN40/2) -> 0.44294383 | AJ40: 0 | AK40: 0 | AL40: =(AC40-AH40)*AJ40+AK40*AC40*0.5 -> 0 | AM40: =AF40-AL40 -> 46728 | AN40: =AM40/AF40-1 -> 0 | AO40: =IFERROR(AM40/H40,"") -> 1.6237529 | AP40: =AM40-X40 -> 3894 | AQ40: =AM40/X40-1 -> 0.090909091 | AR40: =IFERROR(AA40+AQ40*0.5,"") -> 0.44294383 | BV40: 0.29748928 | BW40: =IF(AA40>19%,AA40-3.8%,AA40) -> 0.35948928
A41: 2606 | B41: Dishwasher | C41: EOL after inventory depletion | D41: DFC533FV.APYPETH | E41: DFC533FV.APYPETH | G41: =IFERROR(VLOOKUP(D41,[3]전용!E:J,6,0),"") | H41: 28777.778 | I41: 6 | J41: Self | K41: 12 | L41: 599 | M41: =L41*LEFT(I41,1)*12 -> 43128 | N41: 0.15 | P41: 599 | Q41: =L41-P41 -> 0 | R41: =P41*LEFT(I41,1)*12 -> 43128 | S41: =AA41-(Y41/2) -> 0.43915595 | V41: 12 | W41: =(P41-T41)*U41+V41*P41*0.5 -> 3594 | X41: =R41-W41 -> 39534 | Y41: =X41/R41-1 -> -0.083333333 | Z41: =IFERROR(X41/H41,"") -> 1.3737683 | AA41: 0.39748928 | AB41: 0.0036542546 | AC41: =P41+AD41 -> 599 | AE41: =IF(AA41>10%,0,IF(AA41>5%,P41*0.04,IF(AA41>0%,P41*0.075, P41*0.1))) -> 0 | AF41: =AC41*LEFT(I41,1)*12 -> 43128 | AG41: =AF41/R41-1 -> 0 | AH41: 0 | AI41: =AR41+(AN41/2) -> 0.44294383 | AJ41: 0 | AK41: 0 | AL41: =(AC41-AH41)*AJ41+AK41*AC41*0.5 -> 0 | AM41: =AF41-AL41 -> 43128 | AN41: =AM41/AF41-1 -> 0 | AO41: =IFERROR(AM41/H41,"") -> 1.4986564 | AP41: =AM41-X41 -> 3594 | AQ41: =AM41/X41-1 -> 0.090909091 | AR41: =IFERROR(AA41+AQ41*0.5,"") -> 0.44294383 | BV41: 0.29748928 | BW41: =IF(AA41>19%,AA41-3.8%,AA41) -> 0.35948928
